Workbook

Sheet Sheet1
A1: 楽天ポイント集計Excel | F1: 2026 | G1: 年 | H1: 6 | I1: 月 | O1: ダイヤモンド会員 | X1: Rakuten UN-LIMIT VII | AO1: =+AO625 -> 0 | AP1: =+AP625 -> 0
A3: 購入データ入力 | O3: 条件入力欄 | AI3: 個別② | AJ3: 基本 | AK3: SPU | AL3: 基本 | AM3: SPU | AN3: SPU | AO3: マラソン | AP3: マラソン | AQ3: マラソン | AR3: ポイントアップ祭り | AS3: 個別① | AT3: 個別① | AU3: ポイント | AV3: 特定日 | AW3: 特定日 | AX3: 特定日 | AY3: 個別② | AZ3: 個別② | BA3: 個別② | BB3: 個別② | BC3: 個別② | BD3: 個別② | BE3: 個別② | BF3: 個別② | BG3: 個別② | BH3: 個別② | BI3: 個別② | BJ3: SPU | BK3: SPU | BL3: SPU | BM3: SPU | BN3: SPU | BO3: SPU | BP3: SPU | BQ3: SPU | BR3: SPU | BS3: SPU | BT3: SPU | BU3: SPU | BV3: SPU | BW3: SPU | BX3: 個別① | BY3: 個別① | BZ3: 個別① | CA3: 個別① | CB3: 個別① | CC3: 個別① | CD3: 個別① | CE3: 個別① | CF3: 個別①
A4: 購入年月日 | B4: 購入先 | C4: 商品名 | D4: 商品名(型番) | E4: URL | F4: 単価 | G4: 個数 | H4: 価格 | I4: 値引 | J4: 送料 | K4: ポイント計算ベース100円 税込 | L4: ポイント計算ベース100円 税込 | M4: ポイント計算ベース200円 税抜 | N4: 請求額 | O4: 火・木 プレミアムカードデー | P4: 5の日 | Q4: ワンダフル | R4: 18日 | S4: イーグルス等 | T4: ママ割 | U4: マイカー割 | V4: リピート | W4: 直前 | X4: 39ショップ | AD4: マラソン判定① | AE4: マラソン判定② | AF4: マラソン判定③ | AG4: マラソン判定④ | AI4: 店舗 | AJ4: 基本還元率 | AK4: 楽天モバイル＋会員ランク特典 | AL4: 楽天カード 通常分 | AM4: 楽天カード 特典分 | AN4: 楽天銀行＋楽天カード（引落） | AO4: マラソン① | AP4: マラソン② | AQ4: マラソン③ | AR4: ポイントアップ祭り | AS4: イーグルス他 | AT4: 39ショップ | AU4: 火・木 プレミアムカードデー | AV4: 5の日 | AW4: ワンダフル | AX4: 18日 | AY4: スーパーDEAL | BA4: 店舗 | BB4: カード | BJ4: 楽天モバイルキャリア決済 | BK4: 楽天ひかり | BL4: 楽天プレミアムカード特典分 | BM4: 楽天銀行＋楽天カード(給与等) | BN4: 楽天証券 投資信託 | BO4: 楽天証券 米国株式 | BP4: 楽天ウォレット | BQ4: 楽天トラベル | BR4: 楽天市場アプリ | BS4: 楽天ブックス | BT4: 楽天kobo | BU4: Rakuten Pasha | BV4: Rakuten Fashionアプリ | BW4: 楽天ビューティ | BX4: ママ割 | BY4: マイカー割 | BZ4: リピート割 | CA4: 直前 | CG4: 合計ポイント | CH4: 実質購入金額 | CI4: 実質購入単価 | CK4: ASIN | CL4: Amazon等販売先URL | CM4: 出品価格 | CN4: "入金 予定[円/個]" | CO4: 予定利益/個 | CR4: 予定総利益 | CU4: SKU例
A5: 倍率 | AJ5: 1 | AK5: 3 | AL5: 1 | AM5: 1 | AN5: 0.3 | AO5: =+IF(COUNTA(AD$11:AD$624)-COUNTBLANK(AD$11:AD$624)-1>=9,9,IF(COUNTA(AD$11:AD$624)-COUNTBLANK(AD$11:AD$624)-1<0,0,COUNTA(AD$11:AD$624)-COUNTBLANK(AD$11:AD$624)-1)) -> 0 | AP5: =+IF(COUNTA(AE$11:AE$624)-COUNTBLANK(AE$11:AE$624)-1>=9,9,IF(COUNTA(AE$11:AE$624)-COUNTBLANK(AE$11:AE$624)-1<0,0,COUNTA(AE$11:AE$624)-COUNTBLANK(AE$11:AE$624)-1)) -> 0 | AQ5: =+IF(COUNTA(AF$11:AF$624)-COUNTBLANK(AF$11:AF$624)-1>=9,9,IF(COUNTA(AF$11:AF$624)-COUNTBLANK(AF$11:AF$624)-1<0,0,COUNTA(AF$11:AF$624)-COUNTBLANK(AF$11:AF$624)-1)) -> 0 | AR5: =IF(SUMIFS($H$11:$H$624,$A$11:$A$624,">="&$AR$8,$A$11:$A$624,"<="&$AR$9)+SUMIFS($I$11:$I$624,$A$11:$A$624,">="&$AR$8,$A$11:$A$624,"<="&$AR$9)>=45000,6,IF(SUMIFS($H$11:$H$624,$A$11:$A$624,">="&$AR$8,$A$11:$A$624,"<="&$AR$9)+SUMIFS($I$11:$I$624,$A$11:$A$624,">="&$AR$8,$A$11:$A$624,"<="&$AR$9)>=30000,4,IF(SUMIFS($H$11:$H$624,$A$11:$A$624,">="&$AR$8,$A$11:$A$624,"<="&$AR$9)+SUMIFS($I$11:$I$624,$A$11:$A$624,">="&$AR$8,$A$11:$A$624,"<="&$AR$9)>=10000,2,IF(SUMIFS($H$11:$H$624,$A$11:$A$624,">="&$AR$8,$A$11:$A$624,"<="&$AR$9)+SUMIFS($I$11:$I$624,$A$11:$A$624,">="&$AR$8,$A$11:$A$624,"<="&$AR$9)>=5000,1,"")))) | AS5: - | AT5: 1 | AU5: 1 | AV5: 2 | AW5: 3 | AX5: =VLOOKUP($O$1,[1]マスタ!$B$1:$D$5,3,0) -> 3 | BJ5: 0.5 | BK5: 1 | BL5: 2 | BM5: 0.5 | BN5: 0.5 | BO5: 0.5 | BP5: 0.5 | BQ5: 1 | BR5: 0.5 | BS5: 0.5 | BT5: 0.5 | BU5: 0.5 | BV5: 0.5 | BW5: 0.5 | BX5: 1 | BY5: 2 | BZ5: 1 | CA5: 1
A6: 上限 | AJ6: 99999999 | AK6: 2000 | AL6: 99999999 | AM6: 5000 | AN6: 1000 | AO6: 7000 | AP6: 7000 | AQ6: 7000 | AR6: 5000 | AS6: - | AT6: 3000 | AU6: 10000 | AV6: 3000 | AW6: 1000 | AX6: 1000 | BJ6: 5000 | BK6: 5000 | BL6: 15000 | BM6: 5000 | BN6: 5000 | BO6: 5000 | BP6: 5000 | BQ6: =+SUMIFS([1]マスタ!$C$1:$C$5,[1]マスタ!$B$1:$B$5,$O$1) -> #VALUE! | BR6: =+SUMIFS([1]マスタ!$C$1:$C$5,[1]マスタ!$B$1:$B$5,$O$1) -> #VALUE! | BS6: =+SUMIFS([1]マスタ!$C$1:$C$5,[1]マスタ!$B$1:$B$5,$O$1) -> #VALUE! | BT6: =+SUMIFS([1]マスタ!$C$1:$C$5,[1]マスタ!$B$1:$B$5,$O$1) -> #VALUE! | BU6: 5000 | BV6: =+SUMIFS([1]マスタ!$C$1:$C$5,[1]マスタ!$B$1:$B$5,$O$1) -> #VALUE! | BW6: =+SUMIFS([1]マスタ!$C$1:$C$5,[1]マスタ!$B$1:$B$5,$O$1) -> #VALUE! | BX6: 1000 | BY6: 1000 | BZ6: 1000 | CA6: 1000
A7: 判定 | AJ7: ○ | AK7: ○ | AL7: ○ | AM7: ○ | AN7: ○ | BJ7: ✕ | BK7: ✕ | BL7: ✕ | BM7: ✕ | BN7: ✕ | BO7: ✕ | BP7: ✕ | BQ7: ✕ | BR7: ✕ | BS7: ✕ | BT7: ✕ | BU7: ✕ | BV7: ✕ | BW7: ✕
A8: 開始 | AJ8: =+DATE($F$1,$H$1,1) -> 46174 | AK8: =+DATE($F$1,$H$1,1) -> 46174 | AL8: =+DATE($F$1,$H$1,1) -> 46174 | AM8: =+DATE($F$1,$H$1,1) -> 46174 | AN8: =+DATE($F$1,$H$1,1) -> 46174 | AO8: 46177 | AP8: 46193 | AR8: 46023 | AS8: =+DATE($F$1,$H$1,1) -> 46174 | AT8: 46177 | AU8: =+DATE($F$1,$H$1,1) -> 46174 | AV8: =+DATE($F$1,$H$1,1) -> 46174 | AW8: =+DATE($F$1,$H$1,1) -> 46174 | AX8: =+DATE($F$1,$H$1,1) -> 46174 | BJ8: =+DATE($F$1,$H$1,1) -> 46174 | BK8: =+DATE($F$1,$H$1,1) -> 46174 | BL8: =+DATE($F$1,$H$1,1) -> 46174 | BM8: =+DATE($F$1,$H$1,1) -> 46174 | BN8: =+DATE($F$1,$H$1,1) -> 46174 | BO8: =+DATE($F$1,$H$1,1) -> 46174 | BP8: =+DATE($F$1,$H$1,1) -> 46174 | BQ8: =+DATE($F$1,$H$1,1) -> 46174 | ... CA8: =+DATE($F$1,$H$1,1) -> 46174
A9: 終了 | AJ9: =+EOMONTH(AJ8,0) -> 46203 | AK9: =+EOMONTH(AK8,0) -> 46203 | AL9: =+EOMONTH(AL8,0) -> 46203 | AM9: =+EOMONTH(AM8,0) -> 46203 | AN9: =+EOMONTH(AN8,0) -> 46203 | AO9: 46184 | AP9: 46199 | AR9: 46027 | AS9: =+EOMONTH(AS8,0) -> 46203 | AT9: 46184 | AU9: =+EOMONTH(AU8,0) -> 46203 | AV9: =+EOMONTH(AV8,0) -> 46203 | AW9: =+EOMONTH(AW8,0) -> 46203 | AX9: =+EOMONTH(AX8,0) -> 46203 | BJ9: =+EOMONTH(BJ8,0) -> 46203 | BK9: =+EOMONTH(BK8,0) -> 46203 | BL9: =+EOMONTH(BL8,0) -> 46203 | BM9: =+EOMONTH(BM8,0) -> 46203 | BN9: =+EOMONTH(BN8,0) -> 46203 | BO9: =+EOMONTH(BO8,0) -> 46203 | BP9: =+EOMONTH(BP8,0) -> 46203 | BQ9: =+EOMONTH(BQ8,0) -> 46203 | ... CA9: =+EOMONTH(CA8,0) -> 46203
G11: 1 | H11: =+F11*G11 -> 0 | K11: =+ROUNDDOWN((H11+I11)/100,0)*100 -> 0 | L11: =+ROUNDDOWN((H11+I11)/1.1/100,0)*100 -> 0 | M11: =+ROUNDDOWN((H11+I11)/1.1/200,0)*200 -> 0 | N11: =+H11+I11+J11 -> 0 | O11: =IF(OR(WEEKDAY($A11,2)=2,WEEKDAY($A11,2)=4),"○","✕") -> ✕ | P11: =+IF(MOD(TEXT($A11,"DD"),5)=0,"○","✕") -> ○ | Q11: =+IF((TEXT($A11,"DD")+0)=1,"○","✕") -> ✕ | R11: =+IF((TEXT($A11,"DD")+0)=18,"○","✕") -> ✕ | S11: 0 | T11: ✕ | U11: ✕ | V11: ✕ | W11: ✕ | X11: ○ | Y11: ✕ | Z11: ✕ | AA11: ✕ | AB11: ✕ | AC11: ✕ | AD11: =+IF(ISERROR(VLOOKUP($B11,AD$10:AD10,1,0)),IF(AND($N11>=1000,$A11>=AO$8,$A11<=AO$9),$B11,""),"") | AE11: =+IF(ISERROR(VLOOKUP($B11,AE$10:AE10,1,0)),IF(AND($N11>=1000,$A11>=AP$8,$A11<=AP$9),$B11,""),"") | AF11: =+IF(ISERROR(VLOOKUP($B11,AF$10:AF10,1,0)),IF(AND($N11>=1000,$A11>=AQ$8,$A11<=AQ$9),$B11,""),"") | AG11: =+IF(ISERROR(VLOOKUP($B11,AG$10:AG10,1,0)),IF(AND($N11>=1000,$A11>=AR$8,$A11<=AR$9),$B11,""),"") | AI11: 0 | AJ11: =IF(AND(AJ$7="○",$A11>=AJ$8,$A11<=AJ$9),IF(SUM(AJ$10:AJ10)-ROUNDDOWN($K11*AJ$5/100,0)<-AJ$6,-AJ$6-SUM(AJ$10:AJ10),-ROUNDDOWN($K11*AJ$5/100,0)),0) -> 0 | AK11: =IF(AND(AK$7="○",$A11>=AK$8,$A11<=AK$9),IF(SUM(AK$10:AK10)-ROUNDDOWN($L11*AK$5/100,0)<-AK$6,-AK$6-SUM(AK$10:AK10),-ROUNDDOWN($L11*AK$5/100,0)),0) -> 0 | AL11: =IF(AND(AL$7="○",$A11>=AL$8,$A11<=AL$9),IF(SUM(AL$10:AL10)-ROUNDDOWN($N11*AL$5/100,0)<-AL$6,-AL$6-SUM(AL$10:AL10),-ROUNDDOWN($N11*AL$5/100,0)),0) -> 0 | AM11: =IF(AND(AM$7="○",$A11>=AM$8,$A11<=AM$9),IF(SUM(AM$10:AM10)-ROUNDDOWN($L11*AM$5/100,0)<-AM$6,-AM$6-SUM(AM$10:AM10),-ROUNDDOWN($L11*AM$5/100,0)),0) -> 0 | AN11: =IF(AND(AN$7="○",$A11>=AN$8,$A11<=AN$9),IF(SUM(AN$10:AN10)-ROUNDDOWN($M11*AN$5/100,0)<-AN$6,-AN$6-SUM(AN$10:AN10),-ROUNDDOWN($M11*AN$5/100,0)),0) -> 0 | AO11: =IF(AND($A11>=AO$8,$A11<=AO$9),IF(SUM(AO$10:AO10)-ROUNDDOWN($K11*AO$5/100,0)<-AO$6,-AO$6-SUM(AO$10:AO10),-ROUNDDOWN($K11*AO$5/100,0)),0) -> 0 | AP11: =IF(AND($A11>=AP$8,$A11<=AP$9),IF(SUM(AP$10:AP10)-ROUNDDOWN($K11*AP$5/100,0)<-AP$6,-AP$6-SUM(AP$10:AP10),-ROUNDDOWN($K11*AP$5/100,0)),0) -> 0 | AQ11: =IF(AND($A11>=AQ$8,$A11<=AQ$9),IF(SUM(AQ$10:AQ10)-ROUNDDOWN($K11*AQ$5/100,0)<-AQ$6,-AQ$6-SUM(AQ$10:AQ10),-ROUNDDOWN($K11*AQ$5/100,0)),0) -> 0 | AR11: =IF(AND($A11>=AR$8,$A11<=AR$9),IF(SUM(AR$10:AR10)-ROUNDDOWN($K11*AR$5/100,0)<-AR$6,-AR$6-SUM(AR$10:AR10),-ROUNDDOWN($K11*AR$5/100,0)),0) -> 0 | AS11: =IF(SUMIFS(AS$10:AS10,$A$10:$A10,$A11)-ROUNDDOWN($K11*$S11/100,0)<-$S11*1000,-$S11*1000-SUMIFS(AS$10:AS10,$A$10:$A10,$A11),-ROUNDDOWN($K11*$S11/100,0)) -> 0 | AT11: =IF(AND(X11="○",$A11>=AT$8,$A11<=AT$9,K11>=3980),IF(SUM(AT$10:AT10)-ROUNDDOWN($K11*AT$5/100,0)<-AT$6,-AT$6-SUM(AT$10:AT10),-ROUNDDOWN($K11*AT$5/100,0)),0) -> 0 | AU11: =IF(O11="○",IF(SUM(AU$10:AU10)-ROUNDDOWN($K11*AU$5/100,0)<-AU$6,-AU$6-SUM(AU$10:AU10),-ROUNDDOWN($K11*AU$5/100,0)),0) -> 0 | AV11: =IF(P11="○",IF(SUM(AV$10:AV10)-ROUNDDOWN($K11*AV$5/100,0)<-AV$6,-AV$6-SUM(AV$10:AV10),-ROUNDDOWN($K11*AV$5/100,0)),0) -> 0 | AW11: =IF(Q11="○",IF(SUM(AW$10:AW10)-ROUNDDOWN($K11*AW$5/100,0)<-AW$6,-AW$6-SUM(AW$10:AW10),-ROUNDDOWN($K11*AW$5/100,0)),0) -> 0 | AX11: =IF(R11="○",IF(SUM(AX$10:AX10)-ROUNDDOWN($K11*AX$5/100,0)<-AX$6,-AX$6-SUM(AX$10:AX10),-ROUNDDOWN($K11*AX$5/100,0)),0) -> 0 | AY11: 0 | AZ11: =-ROUNDDOWN($K11*AY11/100,0) -> 0 | BA11: =-ROUNDDOWN($K11*AI11/100,0) -> 0 | BC11: =-ROUNDDOWN($K11*BB11/100,0) -> 0 | BD11: 0 | BE11: =-ROUNDDOWN($K11*BD11/100,0) -> 0 | BF11: 0 | BG11: =-ROUNDDOWN($K11*BF11/100,0) -> 0 | BH11: 0 | BI11: =-ROUNDDOWN($K11*BH11/100,0) -> 0 | BJ11: =IF(AND(BJ$7="○",$A11>=BJ$8,$A11<=BJ$9),IF(SUM(BJ$10:BJ10)-ROUNDDOWN($M11*BJ$5/100,0)<-BJ$6,-BJ$6-SUM(BJ$10:BJ10),-ROUNDDOWN($M11*BJ$5/100,0)),0) -> 0 | BK11: =IF(AND(BK$7="○",$A11>=BK$8,$A11<=BK$9),IF(SUM(BK$10:BK10)-ROUNDDOWN($L11*BK$5/100,0)<-BK$6,-BK$6-SUM(BK$10:BK10),-ROUNDDOWN($L11*BK$5/100,0)),0) -> 0 | BL11: =IF(AND(BL$7="○",$A11>=BL$8,$A11<=BL$9),IF(SUM(BL$10:BL10)-ROUNDDOWN($L11*BL$5/100,0)<-BL$6,-BL$6-SUM(BL$10:BL10),-ROUNDDOWN($L11*BL$5/100,0)),0) -> 0 | BM11: =IF(AND(BM$7="○",$A11>=BM$8,$A11<=BM$9),IF(SUM(BM$10:BM10)-ROUNDDOWN($M11*BM$5/100,0)<-BM$6,-BM$6-SUM(BM$10:BM10),-ROUNDDOWN($M11*BM$5/100,0)),0) -> 0 | BN11: =IF(AND(BN$7="○",$A11>=BN$8,$A11<=BN$9),IF(SUM(BN$10:BN10)-ROUNDDOWN($M11*BN$5/100,0)<-BN$6,-BN$6-SUM(BN$10:BN10),-ROUNDDOWN($M11*BN$5/100,0)),0) -> 0 | BO11: =IF(AND(BO$7="○",$A11>=BO$8,$A11<=BO$9),IF(SUM(BO$10:BO10)-ROUNDDOWN($M11*BO$5/100,0)<-BO$6,-BO$6-SUM(BO$10:BO10),-ROUNDDOWN($M11*BO$5/100,0)),0) -> 0 | BP11: =IF(AND(BP$7="○",$A11>=BP$8,$A11<=BP$9),IF(SUM(BP$10:BP10)-ROUNDDOWN($M11*BP$5/100,0)<-BP$6,-BP$6-SUM(BP$10:BP10),-ROUNDDOWN($M11*BP$5/100,0)),0) -> 0 | BQ11: =IF(AND(BQ$7="○",$A11>=BQ$8,$A11<=BQ$9),IF(SUM(BQ$10:BQ10)-ROUNDDOWN($L11*BQ$5/100,0)<-BQ$6,-BQ$6-SUM(BQ$10:BQ10),-ROUNDDOWN($L11*BQ$5/100,0)),0) -> 0 | BR11: =IF(AND(BR$7="○",$A11>=BR$8,$A11<=BR$9),IF(SUM(BR$10:BR10)-ROUNDDOWN($M11*BR$5/100,0)<-BR$6,-BR$6-SUM(BR$10:BR10),-ROUNDDOWN($M11*BR$5/100,0)),0) -> 0 | BS11: =IF(AND(BS$7="○",$A11>=BS$8,$A11<=BS$9),IF(SUM(BS$10:BS10)-ROUNDDOWN($M11*BS$5/100,0)<-BS$6,-BS$6-SUM(BS$10:BS10),-ROUNDDOWN($M11*BS$5/100,0)),0) -> 0 | BT11: =IF(AND(BT$7="○",$A11>=BT$8,$A11<=BT$9),IF(SUM(BT$10:BT10)-ROUNDDOWN($M11*BT$5/100,0)<-BT$6,-BT$6-SUM(BT$10:BT10),-ROUNDDOWN($M11*BT$5/100,0)),0) -> 0 | BU11: =IF(AND(BU$7="○",$A11>=BU$8,$A11<=BU$9),IF(SUM(BU$10:BU10)-ROUNDDOWN($M11*BU$5/100,0)<-BU$6,-BU$6-SUM(BU$10:BU10),-ROUNDDOWN($M11*BU$5/100,0)),0) -> 0 | BV11: =IF(AND(BV$7="○",$A11>=BV$8,$A11<=BV$9),IF(SUM(BV$10:BV10)-ROUNDDOWN($M11*BV$5/100,0)<-BV$6,-BV$6-SUM(BV$10:BV10),-ROUNDDOWN($M11*BV$5/100,0)),0) -> 0 | BW11: =IF(AND(BW$7="○",$A11>=BW$8,$A11<=BW$9),IF(SUM(BW$10:BW10)-ROUNDDOWN($M11*BW$5/100,0)<-BW$6,-BW$6-SUM(BW$10:BW10),-ROUNDDOWN($M11*BW$5/100,0)),0) -> 0 | BX11: =IF(AND(T11="○",$A11>=BX$8,$A11<=BX$9),IF(SUM(BX$10:BX10)-ROUNDDOWN($K11*BX$5/100,0)<-BX$6,-BX$6-SUM(BX$10:BX10),-ROUNDDOWN($K11*BX$5/100,0)),0) -> 0 | BY11: =IF(AND(U11="○",$A11>=BY$8,$A11<=BY$9),IF(SUM(BY$10:BY10)-ROUNDDOWN($K11*BY$5/100,0)<-BY$6,-BY$6-SUM(BY$10:BY10),-ROUNDDOWN($K11*BY$5/100,0)),0) -> 0 | BZ11: =IF(AND(V11="○",$A11>=BZ$8,$A11<=BZ$9),IF(SUM(BZ$10:BZ10)-ROUNDDOWN($K11*BZ$5/100,0)<-BZ$6,-BZ$6-SUM(BZ$10:BZ10),-ROUNDDOWN($K11*BZ$5/100,0)),0) -> 0 | CA11: =IF(AND(W11="○",$A11>=CA$8,$A11<=CA$9),IF(SUM(CA$10:CA10)-ROUNDDOWN($K11*CA$5/100,0)<-CA$6,-CA$6-SUM(CA$10:CA10),-ROUNDDOWN($K11*CA$5/100,0)),0) -> 0 | CG11: =+SUM(AJ11:CF11,BC11,BE11,AZ11,BA11,BG11,BI11) -> 0 | CH11: =+CG11+N11 -> 0 | CI11: =IFERROR(ROUNDDOWN((CH11/G11),0),0) -> 0 | CO11: =IFERROR(CN11-CI11,0) -> 0 | CP11: =IFERROR(CN11/CI11,0) -> 0 | CR11: =+CO11*G11 -> 0 | CT11: =INDEX([2]マスタ!$A:$A,MATCH(D11,[2]マスタ!$C:$C,0)) -> #N/A | CU11: =IFERROR(TEXT(TODAY(),"yyyymmdd")&"_"&ROUNDDOWN(H11+I11,0)&"-"&ROUNDDOWN(CI11,0),"") -> 20260620_0-0
G12: 1 | H12: =+F12*G12 -> 0 | K12: =+ROUNDDOWN((H12+I12)/100,0)*100 -> 0 | L12: =+ROUNDDOWN((H12+I12)/1.1/100,0)*100 -> 0 | M12: =+ROUNDDOWN((H12+I12)/1.1/200,0)*200 -> 0 | N12: =+H12+I12+J12 -> 0 | O12: =IF(OR(WEEKDAY($A12,2)=2,WEEKDAY($A12,2)=4),"○","✕") -> ✕ | P12: =+IF(MOD(TEXT($A12,"DD"),5)=0,"○","✕") -> ○ | Q12: =+IF((TEXT($A12,"DD")+0)=1,"○","✕") -> ✕ | R12: =+IF((TEXT($A12,"DD")+0)=18,"○","✕") -> ✕ | S12: 0 | T12: ✕ | U12: ✕ | V12: ✕ | W12: ✕ | X12: ○ | Y12: ✕ | Z12: ✕ | AA12: ✕ | AB12: ✕ | AC12: ✕ | AD12: =+IF(ISERROR(VLOOKUP($B12,AD$10:AD11,1,0)),IF(AND($N12>=1000,$A12>=AO$8,$A12<=AO$9),$B12,""),"") | AE12: =+IF(ISERROR(VLOOKUP($B12,AE$10:AE11,1,0)),IF(AND($N12>=1000,$A12>=AP$8,$A12<=AP$9),$B12,""),"") | AF12: =+IF(ISERROR(VLOOKUP($B12,AF$10:AF11,1,0)),IF(AND($N12>=1000,$A12>=AQ$8,$A12<=AQ$9),$B12,""),"") | AG12: =+IF(ISERROR(VLOOKUP($B12,AG$10:AG11,1,0)),IF(AND($N12>=1000,$A12>=AR$8,$A12<=AR$9),$B12,""),"") | AI12: 0 | AJ12: =IF(AND(AJ$7="○",$A12>=AJ$8,$A12<=AJ$9),IF(SUM(AJ$10:AJ11)-ROUNDDOWN($K12*AJ$5/100,0)<-AJ$6,-AJ$6-SUM(AJ$10:AJ11),-ROUNDDOWN($K12*AJ$5/100,0)),0) -> 0 | AK12: =IF(AND(AK$7="○",$A12>=AK$8,$A12<=AK$9),IF(SUM(AK$10:AK11)-ROUNDDOWN($L12*AK$5/100,0)<-AK$6,-AK$6-SUM(AK$10:AK11),-ROUNDDOWN($L12*AK$5/100,0)),0) -> 0 | AL12: =IF(AND(AL$7="○",$A12>=AL$8,$A12<=AL$9),IF(SUM(AL$10:AL11)-ROUNDDOWN($N12*AL$5/100,0)<-AL$6,-AL$6-SUM(AL$10:AL11),-ROUNDDOWN($N12*AL$5/100,0)),0) -> 0 | AM12: =IF(AND(AM$7="○",$A12>=AM$8,$A12<=AM$9),IF(SUM(AM$10:AM11)-ROUNDDOWN($L12*AM$5/100,0)<-AM$6,-AM$6-SUM(AM$10:AM11),-ROUNDDOWN($L12*AM$5/100,0)),0) -> 0 | AN12: =IF(AND(AN$7="○",$A12>=AN$8,$A12<=AN$9),IF(SUM(AN$10:AN11)-ROUNDDOWN($M12*AN$5/100,0)<-AN$6,-AN$6-SUM(AN$10:AN11),-ROUNDDOWN($M12*AN$5/100,0)),0) -> 0 | AO12: =IF(AND($A12>=AO$8,$A12<=AO$9),IF(SUM(AO$10:AO11)-ROUNDDOWN($K12*AO$5/100,0)<-AO$6,-AO$6-SUM(AO$10:AO11),-ROUNDDOWN($K12*AO$5/100,0)),0) -> 0 | AP12: =IF(AND($A12>=AP$8,$A12<=AP$9),IF(SUM(AP$10:AP11)-ROUNDDOWN($K12*AP$5/100,0)<-AP$6,-AP$6-SUM(AP$10:AP11),-ROUNDDOWN($K12*AP$5/100,0)),0) -> 0 | AQ12: =IF(AND($A12>=AQ$8,$A12<=AQ$9),IF(SUM(AQ$10:AQ11)-ROUNDDOWN($K12*AQ$5/100,0)<-AQ$6,-AQ$6-SUM(AQ$10:AQ11),-ROUNDDOWN($K12*AQ$5/100,0)),0) -> 0 | AR12: =IF(AND($A12>=AR$8,$A12<=AR$9),IF(SUM(AR$10:AR11)-ROUNDDOWN($K12*AR$5/100,0)<-AR$6,-AR$6-SUM(AR$10:AR11),-ROUNDDOWN($K12*AR$5/100,0)),0) -> 0 | AS12: =IF(SUMIFS(AS$10:AS11,$A$10:$A11,$A12)-ROUNDDOWN($K12*$S12/100,0)<-$S12*1000,-$S12*1000-SUMIFS(AS$10:AS11,$A$10:$A11,$A12),-ROUNDDOWN($K12*$S12/100,0)) -> 0 | AT12: =IF(AND(X12="○",$A12>=AT$8,$A12<=AT$9,K12>=3980),IF(SUM(AT$10:AT11)-ROUNDDOWN($K12*AT$5/100,0)<-AT$6,-AT$6-SUM(AT$10:AT11),-ROUNDDOWN($K12*AT$5/100,0)),0) -> 0 | AU12: =IF(O12="○",IF(SUM(AU$10:AU11)-ROUNDDOWN($K12*AU$5/100,0)<-AU$6,-AU$6-SUM(AU$10:AU11),-ROUNDDOWN($K12*AU$5/100,0)),0) -> 0 | AV12: =IF(P12="○",IF(SUM(AV$10:AV11)-ROUNDDOWN($K12*AV$5/100,0)<-AV$6,-AV$6-SUM(AV$10:AV11),-ROUNDDOWN($K12*AV$5/100,0)),0) -> 0 | AW12: =IF(Q12="○",IF(SUM(AW$10:AW11)-ROUNDDOWN($K12*AW$5/100,0)<-AW$6,-AW$6-SUM(AW$10:AW11),-ROUNDDOWN($K12*AW$5/100,0)),0) -> 0 | AX12: =IF(R12="○",IF(SUM(AX$10:AX11)-ROUNDDOWN($K12*AX$5/100,0)<-AX$6,-AX$6-SUM(AX$10:AX11),-ROUNDDOWN($K12*AX$5/100,0)),0) -> 0 | AY12: 0 | AZ12: =-ROUNDDOWN($K12*AY12/100,0) -> 0 | BA12: =-ROUNDDOWN($K12*AI12/100,0) -> 0 | BC12: =-ROUNDDOWN($K12*BB12/100,0) -> 0 | BD12: 0 | BE12: =-ROUNDDOWN($K12*BD12/100,0) -> 0 | BF12: 0 | BG12: =-ROUNDDOWN($K12*BF12/100,0) -> 0 | BH12: 0 | BI12: =-ROUNDDOWN($K12*BH12/100,0) -> 0 | BJ12: =IF(AND(BJ$7="○",$A12>=BJ$8,$A12<=BJ$9),IF(SUM(BJ$10:BJ11)-ROUNDDOWN($M12*BJ$5/100,0)<-BJ$6,-BJ$6-SUM(BJ$10:BJ11),-ROUNDDOWN($M12*BJ$5/100,0)),0) -> 0 | BK12: =IF(AND(BK$7="○",$A12>=BK$8,$A12<=BK$9),IF(SUM(BK$10:BK11)-ROUNDDOWN($L12*BK$5/100,0)<-BK$6,-BK$6-SUM(BK$10:BK11),-ROUNDDOWN($L12*BK$5/100,0)),0) -> 0 | BL12: =IF(AND(BL$7="○",$A12>=BL$8,$A12<=BL$9),IF(SUM(BL$10:BL11)-ROUNDDOWN($L12*BL$5/100,0)<-BL$6,-BL$6-SUM(BL$10:BL11),-ROUNDDOWN($L12*BL$5/100,0)),0) -> 0 | BM12: =IF(AND(BM$7="○",$A12>=BM$8,$A12<=BM$9),IF(SUM(BM$10:BM11)-ROUNDDOWN($M12*BM$5/100,0)<-BM$6,-BM$6-SUM(BM$10:BM11),-ROUNDDOWN($M12*BM$5/100,0)),0) -> 0 | BN12: =IF(AND(BN$7="○",$A12>=BN$8,$A12<=BN$9),IF(SUM(BN$10:BN11)-ROUNDDOWN($M12*BN$5/100,0)<-BN$6,-BN$6-SUM(BN$10:BN11),-ROUNDDOWN($M12*BN$5/100,0)),0) -> 0 | BO12: =IF(AND(BO$7="○",$A12>=BO$8,$A12<=BO$9),IF(SUM(BO$10:BO11)-ROUNDDOWN($M12*BO$5/100,0)<-BO$6,-BO$6-SUM(BO$10:BO11),-ROUNDDOWN($M12*BO$5/100,0)),0) -> 0 | BP12: =IF(AND(BP$7="○",$A12>=BP$8,$A12<=BP$9),IF(SUM(BP$10:BP11)-ROUNDDOWN($M12*BP$5/100,0)<-BP$6,-BP$6-SUM(BP$10:BP11),-ROUNDDOWN($M12*BP$5/100,0)),0) -> 0 | BQ12: =IF(AND(BQ$7="○",$A12>=BQ$8,$A12<=BQ$9),IF(SUM(BQ$10:BQ11)-ROUNDDOWN($L12*BQ$5/100,0)<-BQ$6,-BQ$6-SUM(BQ$10:BQ11),-ROUNDDOWN($L12*BQ$5/100,0)),0) -> 0 | BR12: =IF(AND(BR$7="○",$A12>=BR$8,$A12<=BR$9),IF(SUM(BR$10:BR11)-ROUNDDOWN($M12*BR$5/100,0)<-BR$6,-BR$6-SUM(BR$10:BR11),-ROUNDDOWN($M12*BR$5/100,0)),0) -> 0 | BS12: =IF(AND(BS$7="○",$A12>=BS$8,$A12<=BS$9),IF(SUM(BS$10:BS11)-ROUNDDOWN($M12*BS$5/100,0)<-BS$6,-BS$6-SUM(BS$10:BS11),-ROUNDDOWN($M12*BS$5/100,0)),0) -> 0 | BT12: =IF(AND(BT$7="○",$A12>=BT$8,$A12<=BT$9),IF(SUM(BT$10:BT11)-ROUNDDOWN($M12*BT$5/100,0)<-BT$6,-BT$6-SUM(BT$10:BT11),-ROUNDDOWN($M12*BT$5/100,0)),0) -> 0 | BU12: =IF(AND(BU$7="○",$A12>=BU$8,$A12<=BU$9),IF(SUM(BU$10:BU11)-ROUNDDOWN($M12*BU$5/100,0)<-BU$6,-BU$6-SUM(BU$10:BU11),-ROUNDDOWN($M12*BU$5/100,0)),0) -> 0 | BV12: =IF(AND(BV$7="○",$A12>=BV$8,$A12<=BV$9),IF(SUM(BV$10:BV11)-ROUNDDOWN($M12*BV$5/100,0)<-BV$6,-BV$6-SUM(BV$10:BV11),-ROUNDDOWN($M12*BV$5/100,0)),0) -> 0 | BW12: =IF(AND(BW$7="○",$A12>=BW$8,$A12<=BW$9),IF(SUM(BW$10:BW11)-ROUNDDOWN($M12*BW$5/100,0)<-BW$6,-BW$6-SUM(BW$10:BW11),-ROUNDDOWN($M12*BW$5/100,0)),0) -> 0 | BX12: =IF(AND(T12="○",$A12>=BX$8,$A12<=BX$9),IF(SUM(BX$10:BX11)-ROUNDDOWN($K12*BX$5/100,0)<-BX$6,-BX$6-SUM(BX$10:BX11),-ROUNDDOWN($K12*BX$5/100,0)),0) -> 0 | BY12: =IF(AND(U12="○",$A12>=BY$8,$A12<=BY$9),IF(SUM(BY$10:BY11)-ROUNDDOWN($K12*BY$5/100,0)<-BY$6,-BY$6-SUM(BY$10:BY11),-ROUNDDOWN($K12*BY$5/100,0)),0) -> 0 | BZ12: =IF(AND(V12="○",$A12>=BZ$8,$A12<=BZ$9),IF(SUM(BZ$10:BZ11)-ROUNDDOWN($K12*BZ$5/100,0)<-BZ$6,-BZ$6-SUM(BZ$10:BZ11),-ROUNDDOWN($K12*BZ$5/100,0)),0) -> 0 | CA12: =IF(AND(W12="○",$A12>=CA$8,$A12<=CA$9),IF(SUM(CA$10:CA11)-ROUNDDOWN($K12*CA$5/100,0)<-CA$6,-CA$6-SUM(CA$10:CA11),-ROUNDDOWN($K12*CA$5/100,0)),0) -> 0 | CG12: =+SUM(AJ12:CF12,BC12,BE12,AZ12,BA12,BG12,BI12) -> 0 | CH12: =+CG12+N12 -> 0 | CI12: =IFERROR(ROUNDDOWN((CH12/G12),0),0) -> 0 | CO12: =IFERROR(CN12-CI12,0) -> 0 | CP12: =IFERROR(CN12/CI12,0) -> 0 | CR12: =+CO12*G12 -> 0 | CT12: =INDEX([2]マスタ!$A:$A,MATCH(D12,[2]マスタ!$C:$C,0)) -> #N/A | CU12: =IFERROR(TEXT(TODAY(),"yyyymmdd")&"_"&ROUNDDOWN(H12+I12,0)&"-"&ROUNDDOWN(CI12,0),"") -> 20260620_0-0
G13: 1 | H13: =+F13*G13 -> 0 | K13: =+ROUNDDOWN((H13+I13)/100,0)*100 -> 0 | L13: =+ROUNDDOWN((H13+I13)/1.1/100,0)*100 -> 0 | M13: =+ROUNDDOWN((H13+I13)/1.1/200,0)*200 -> 0 | N13: =+H13+I13+J13 -> 0 | O13: =IF(OR(WEEKDAY($A13,2)=2,WEEKDAY($A13,2)=4),"○","✕") -> ✕ | P13: =+IF(MOD(TEXT($A13,"DD"),5)=0,"○","✕") -> ○ | Q13: =+IF((TEXT($A13,"DD")+0)=1,"○","✕") -> ✕ | R13: =+IF((TEXT($A13,"DD")+0)=18,"○","✕") -> ✕ | S13: 0 | T13: ✕ | U13: ✕ | V13: ✕ | W13: ✕ | X13: ○ | Y13: ✕ | Z13: ✕ | AA13: ✕ | AB13: ✕ | AC13: ✕ | AD13: =+IF(ISERROR(VLOOKUP($B13,AD$10:AD12,1,0)),IF(AND($N13>=1000,$A13>=AO$8,$A13<=AO$9),$B13,""),"") | AE13: =+IF(ISERROR(VLOOKUP($B13,AE$10:AE12,1,0)),IF(AND($N13>=1000,$A13>=AP$8,$A13<=AP$9),$B13,""),"") | AF13: =+IF(ISERROR(VLOOKUP($B13,AF$10:AF12,1,0)),IF(AND($N13>=1000,$A13>=AQ$8,$A13<=AQ$9),$B13,""),"") | AG13: =+IF(ISERROR(VLOOKUP($B13,AG$10:AG12,1,0)),IF(AND($N13>=1000,$A13>=AR$8,$A13<=AR$9),$B13,""),"") | AI13: 0 | AJ13: =IF(AND(AJ$7="○",$A13>=AJ$8,$A13<=AJ$9),IF(SUM(AJ$10:AJ12)-ROUNDDOWN($K13*AJ$5/100,0)<-AJ$6,-AJ$6-SUM(AJ$10:AJ12),-ROUNDDOWN($K13*AJ$5/100,0)),0) -> 0 | AK13: =IF(AND(AK$7="○",$A13>=AK$8,$A13<=AK$9),IF(SUM(AK$10:AK12)-ROUNDDOWN($L13*AK$5/100,0)<-AK$6,-AK$6-SUM(AK$10:AK12),-ROUNDDOWN($L13*AK$5/100,0)),0) -> 0 | AL13: =IF(AND(AL$7="○",$A13>=AL$8,$A13<=AL$9),IF(SUM(AL$10:AL12)-ROUNDDOWN($N13*AL$5/100,0)<-AL$6,-AL$6-SUM(AL$10:AL12),-ROUNDDOWN($N13*AL$5/100,0)),0) -> 0 | AM13: =IF(AND(AM$7="○",$A13>=AM$8,$A13<=AM$9),IF(SUM(AM$10:AM12)-ROUNDDOWN($L13*AM$5/100,0)<-AM$6,-AM$6-SUM(AM$10:AM12),-ROUNDDOWN($L13*AM$5/100,0)),0) -> 0 | AN13: =IF(AND(AN$7="○",$A13>=AN$8,$A13<=AN$9),IF(SUM(AN$10:AN12)-ROUNDDOWN($M13*AN$5/100,0)<-AN$6,-AN$6-SUM(AN$10:AN12),-ROUNDDOWN($M13*AN$5/100,0)),0) -> 0 | AO13: =IF(AND($A13>=AO$8,$A13<=AO$9),IF(SUM(AO$10:AO12)-ROUNDDOWN($K13*AO$5/100,0)<-AO$6,-AO$6-SUM(AO$10:AO12),-ROUNDDOWN($K13*AO$5/100,0)),0) -> 0 | AP13: =IF(AND($A13>=AP$8,$A13<=AP$9),IF(SUM(AP$10:AP12)-ROUNDDOWN($K13*AP$5/100,0)<-AP$6,-AP$6-SUM(AP$10:AP12),-ROUNDDOWN($K13*AP$5/100,0)),0) -> 0 | AQ13: =IF(AND($A13>=AQ$8,$A13<=AQ$9),IF(SUM(AQ$10:AQ12)-ROUNDDOWN($K13*AQ$5/100,0)<-AQ$6,-AQ$6-SUM(AQ$10:AQ12),-ROUNDDOWN($K13*AQ$5/100,0)),0) -> 0 | AR13: =IF(AND($A13>=AR$8,$A13<=AR$9),IF(SUM(AR$10:AR12)-ROUNDDOWN($K13*AR$5/100,0)<-AR$6,-AR$6-SUM(AR$10:AR12),-ROUNDDOWN($K13*AR$5/100,0)),0) -> 0 | AS13: =IF(SUMIFS(AS$10:AS12,$A$10:$A12,$A13)-ROUNDDOWN($K13*$S13/100,0)<-$S13*1000,-$S13*1000-SUMIFS(AS$10:AS12,$A$10:$A12,$A13),-ROUNDDOWN($K13*$S13/100,0)) -> 0 | AT13: =IF(AND(X13="○",$A13>=AT$8,$A13<=AT$9,K13>=3980),IF(SUM(AT$10:AT12)-ROUNDDOWN($K13*AT$5/100,0)<-AT$6,-AT$6-SUM(AT$10:AT12),-ROUNDDOWN($K13*AT$5/100,0)),0) -> 0 | AU13: =IF(O13="○",IF(SUM(AU$10:AU12)-ROUNDDOWN($K13*AU$5/100,0)<-AU$6,-AU$6-SUM(AU$10:AU12),-ROUNDDOWN($K13*AU$5/100,0)),0) -> 0 | AV13: =IF(P13="○",IF(SUM(AV$10:AV12)-ROUNDDOWN($K13*AV$5/100,0)<-AV$6,-AV$6-SUM(AV$10:AV12),-ROUNDDOWN($K13*AV$5/100,0)),0) -> 0 | AW13: =IF(Q13="○",IF(SUM(AW$10:AW12)-ROUNDDOWN($K13*AW$5/100,0)<-AW$6,-AW$6-SUM(AW$10:AW12),-ROUNDDOWN($K13*AW$5/100,0)),0) -> 0 | AX13: =IF(R13="○",IF(SUM(AX$10:AX12)-ROUNDDOWN($K13*AX$5/100,0)<-AX$6,-AX$6-SUM(AX$10:AX12),-ROUNDDOWN($K13*AX$5/100,0)),0) -> 0 | AY13: 0 | AZ13: =-ROUNDDOWN($K13*AY13/100,0) -> 0 | BA13: =-ROUNDDOWN($K13*AI13/100,0) -> 0 | BC13: =-ROUNDDOWN($K13*BB13/100,0) -> 0 | BD13: 0 | BE13: =-ROUNDDOWN($K13*BD13/100,0) -> 0 | BF13: 0 | BG13: =-ROUNDDOWN($K13*BF13/100,0) -> 0 | BH13: 0 | BI13: =-ROUNDDOWN($K13*BH13/100,0) -> 0 | BJ13: =IF(AND(BJ$7="○",$A13>=BJ$8,$A13<=BJ$9),IF(SUM(BJ$10:BJ12)-ROUNDDOWN($M13*BJ$5/100,0)<-BJ$6,-BJ$6-SUM(BJ$10:BJ12),-ROUNDDOWN($M13*BJ$5/100,0)),0) -> 0 | BK13: =IF(AND(BK$7="○",$A13>=BK$8,$A13<=BK$9),IF(SUM(BK$10:BK12)-ROUNDDOWN($L13*BK$5/100,0)<-BK$6,-BK$6-SUM(BK$10:BK12),-ROUNDDOWN($L13*BK$5/100,0)),0) -> 0 | BL13: =IF(AND(BL$7="○",$A13>=BL$8,$A13<=BL$9),IF(SUM(BL$10:BL12)-ROUNDDOWN($L13*BL$5/100,0)<-BL$6,-BL$6-SUM(BL$10:BL12),-ROUNDDOWN($L13*BL$5/100,0)),0) -> 0 | BM13: =IF(AND(BM$7="○",$A13>=BM$8,$A13<=BM$9),IF(SUM(BM$10:BM12)-ROUNDDOWN($M13*BM$5/100,0)<-BM$6,-BM$6-SUM(BM$10:BM12),-ROUNDDOWN($M13*BM$5/100,0)),0) -> 0 | BN13: =IF(AND(BN$7="○",$A13>=BN$8,$A13<=BN$9),IF(SUM(BN$10:BN12)-ROUNDDOWN($M13*BN$5/100,0)<-BN$6,-BN$6-SUM(BN$10:BN12),-ROUNDDOWN($M13*BN$5/100,0)),0) -> 0 | BO13: =IF(AND(BO$7="○",$A13>=BO$8,$A13<=BO$9),IF(SUM(BO$10:BO12)-ROUNDDOWN($M13*BO$5/100,0)<-BO$6,-BO$6-SUM(BO$10:BO12),-ROUNDDOWN($M13*BO$5/100,0)),0) -> 0 | BP13: =IF(AND(BP$7="○",$A13>=BP$8,$A13<=BP$9),IF(SUM(BP$10:BP12)-ROUNDDOWN($M13*BP$5/100,0)<-BP$6,-BP$6-SUM(BP$10:BP12),-ROUNDDOWN($M13*BP$5/100,0)),0) -> 0 | BQ13: =IF(AND(BQ$7="○",$A13>=BQ$8,$A13<=BQ$9),IF(SUM(BQ$10:BQ12)-ROUNDDOWN($L13*BQ$5/100,0)<-BQ$6,-BQ$6-SUM(BQ$10:BQ12),-ROUNDDOWN($L13*BQ$5/100,0)),0) -> 0 | BR13: =IF(AND(BR$7="○",$A13>=BR$8,$A13<=BR$9),IF(SUM(BR$10:BR12)-ROUNDDOWN($M13*BR$5/100,0)<-BR$6,-BR$6-SUM(BR$10:BR12),-ROUNDDOWN($M13*BR$5/100,0)),0) -> 0 | BS13: =IF(AND(BS$7="○",$A13>=BS$8,$A13<=BS$9),IF(SUM(BS$10:BS12)-ROUNDDOWN($M13*BS$5/100,0)<-BS$6,-BS$6-SUM(BS$10:BS12),-ROUNDDOWN($M13*BS$5/100,0)),0) -> 0 | BT13: =IF(AND(BT$7="○",$A13>=BT$8,$A13<=BT$9),IF(SUM(BT$10:BT12)-ROUNDDOWN($M13*BT$5/100,0)<-BT$6,-BT$6-SUM(BT$10:BT12),-ROUNDDOWN($M13*BT$5/100,0)),0) -> 0 | BU13: =IF(AND(BU$7="○",$A13>=BU$8,$A13<=BU$9),IF(SUM(BU$10:BU12)-ROUNDDOWN($M13*BU$5/100,0)<-BU$6,-BU$6-SUM(BU$10:BU12),-ROUNDDOWN($M13*BU$5/100,0)),0) -> 0 | BV13: =IF(AND(BV$7="○",$A13>=BV$8,$A13<=BV$9),IF(SUM(BV$10:BV12)-ROUNDDOWN($M13*BV$5/100,0)<-BV$6,-BV$6-SUM(BV$10:BV12),-ROUNDDOWN($M13*BV$5/100,0)),0) -> 0 | BW13: =IF(AND(BW$7="○",$A13>=BW$8,$A13<=BW$9),IF(SUM(BW$10:BW12)-ROUNDDOWN($M13*BW$5/100,0)<-BW$6,-BW$6-SUM(BW$10:BW12),-ROUNDDOWN($M13*BW$5/100,0)),0) -> 0 | BX13: =IF(AND(T13="○",$A13>=BX$8,$A13<=BX$9),IF(SUM(BX$10:BX12)-ROUNDDOWN($K13*BX$5/100,0)<-BX$6,-BX$6-SUM(BX$10:BX12),-ROUNDDOWN($K13*BX$5/100,0)),0) -> 0 | BY13: =IF(AND(U13="○",$A13>=BY$8,$A13<=BY$9),IF(SUM(BY$10:BY12)-ROUNDDOWN($K13*BY$5/100,0)<-BY$6,-BY$6-SUM(BY$10:BY12),-ROUNDDOWN($K13*BY$5/100,0)),0) -> 0 | BZ13: =IF(AND(V13="○",$A13>=BZ$8,$A13<=BZ$9),IF(SUM(BZ$10:BZ12)-ROUNDDOWN($K13*BZ$5/100,0)<-BZ$6,-BZ$6-SUM(BZ$10:BZ12),-ROUNDDOWN($K13*BZ$5/100,0)),0) -> 0 | CA13: =IF(AND(W13="○",$A13>=CA$8,$A13<=CA$9),IF(SUM(CA$10:CA12)-ROUNDDOWN($K13*CA$5/100,0)<-CA$6,-CA$6-SUM(CA$10:CA12),-ROUNDDOWN($K13*CA$5/100,0)),0) -> 0 | CG13: =+SUM(AJ13:CF13,BC13,BE13,AZ13,BA13,BG13,BI13) -> 0 | CH13: =+CG13+N13 -> 0 | CI13: =IFERROR(ROUNDDOWN((CH13/G13),0),0) -> 0 | CO13: =IFERROR(CN13-CI13,0) -> 0 | CP13: =IFERROR(CN13/CI13,0) -> 0 | CR13: =+CO13*G13 -> 0 | CT13: =INDEX([2]マスタ!$A:$A,MATCH(D13,[2]マスタ!$C:$C,0)) -> #N/A | CU13: =IFERROR(TEXT(TODAY(),"yyyymmdd")&"_"&ROUNDDOWN(H13+I13,0)&"-"&ROUNDDOWN(CI13,0),"") -> 20260620_0-0
G14: 1 | H14: =+F14*G14 -> 0 | K14: =+ROUNDDOWN((H14+I14)/100,0)*100 -> 0 | L14: =+ROUNDDOWN((H14+I14)/1.1/100,0)*100 -> 0 | M14: =+ROUNDDOWN((H14+I14)/1.1/200,0)*200 -> 0 | N14: =+H14+I14+J14 -> 0 | O14: =IF(OR(WEEKDAY($A14,2)=2,WEEKDAY($A14,2)=4),"○","✕") -> ✕ | P14: =+IF(MOD(TEXT($A14,"DD"),5)=0,"○","✕") -> ○ | Q14: =+IF((TEXT($A14,"DD")+0)=1,"○","✕") -> ✕ | R14: =+IF((TEXT($A14,"DD")+0)=18,"○","✕") -> ✕ | S14: 0 | T14: ✕ | U14: ✕ | V14: ✕ | W14: ✕ | X14: ○ | Y14: ✕ | Z14: ✕ | AA14: ✕ | AB14: ✕ | AC14: ✕ | AD14: =+IF(ISERROR(VLOOKUP($B14,AD$10:AD13,1,0)),IF(AND($N14>=1000,$A14>=AO$8,$A14<=AO$9),$B14,""),"") | AE14: =+IF(ISERROR(VLOOKUP($B14,AE$10:AE13,1,0)),IF(AND($N14>=1000,$A14>=AP$8,$A14<=AP$9),$B14,""),"") | AF14: =+IF(ISERROR(VLOOKUP($B14,AF$10:AF13,1,0)),IF(AND($N14>=1000,$A14>=AQ$8,$A14<=AQ$9),$B14,""),"") | AG14: =+IF(ISERROR(VLOOKUP($B14,AG$10:AG13,1,0)),IF(AND($N14>=1000,$A14>=AR$8,$A14<=AR$9),$B14,""),"") | AI14: 0 | AJ14: =IF(AND(AJ$7="○",$A14>=AJ$8,$A14<=AJ$9),IF(SUM(AJ$10:AJ13)-ROUNDDOWN($K14*AJ$5/100,0)<-AJ$6,-AJ$6-SUM(AJ$10:AJ13),-ROUNDDOWN($K14*AJ$5/100,0)),0) -> 0 | AK14: =IF(AND(AK$7="○",$A14>=AK$8,$A14<=AK$9),IF(SUM(AK$10:AK13)-ROUNDDOWN($L14*AK$5/100,0)<-AK$6,-AK$6-SUM(AK$10:AK13),-ROUNDDOWN($L14*AK$5/100,0)),0) -> 0 | AL14: =IF(AND(AL$7="○",$A14>=AL$8,$A14<=AL$9),IF(SUM(AL$10:AL13)-ROUNDDOWN($N14*AL$5/100,0)<-AL$6,-AL$6-SUM(AL$10:AL13),-ROUNDDOWN($N14*AL$5/100,0)),0) -> 0 | AM14: =IF(AND(AM$7="○",$A14>=AM$8,$A14<=AM$9),IF(SUM(AM$10:AM13)-ROUNDDOWN($L14*AM$5/100,0)<-AM$6,-AM$6-SUM(AM$10:AM13),-ROUNDDOWN($L14*AM$5/100,0)),0) -> 0 | AN14: =IF(AND(AN$7="○",$A14>=AN$8,$A14<=AN$9),IF(SUM(AN$10:AN13)-ROUNDDOWN($M14*AN$5/100,0)<-AN$6,-AN$6-SUM(AN$10:AN13),-ROUNDDOWN($M14*AN$5/100,0)),0) -> 0 | AO14: =IF(AND($A14>=AO$8,$A14<=AO$9),IF(SUM(AO$10:AO13)-ROUNDDOWN($K14*AO$5/100,0)<-AO$6,-AO$6-SUM(AO$10:AO13),-ROUNDDOWN($K14*AO$5/100,0)),0) -> 0 | AP14: =IF(AND($A14>=AP$8,$A14<=AP$9),IF(SUM(AP$10:AP13)-ROUNDDOWN($K14*AP$5/100,0)<-AP$6,-AP$6-SUM(AP$10:AP13),-ROUNDDOWN($K14*AP$5/100,0)),0) -> 0 | AQ14: =IF(AND($A14>=AQ$8,$A14<=AQ$9),IF(SUM(AQ$10:AQ13)-ROUNDDOWN($K14*AQ$5/100,0)<-AQ$6,-AQ$6-SUM(AQ$10:AQ13),-ROUNDDOWN($K14*AQ$5/100,0)),0) -> 0 | AR14: =IF(AND($A14>=AR$8,$A14<=AR$9),IF(SUM(AR$10:AR13)-ROUNDDOWN($K14*AR$5/100,0)<-AR$6,-AR$6-SUM(AR$10:AR13),-ROUNDDOWN($K14*AR$5/100,0)),0) -> 0 | AS14: =IF(SUMIFS(AS$10:AS13,$A$10:$A13,$A14)-ROUNDDOWN($K14*$S14/100,0)<-$S14*1000,-$S14*1000-SUMIFS(AS$10:AS13,$A$10:$A13,$A14),-ROUNDDOWN($K14*$S14/100,0)) -> 0 | AT14: =IF(AND(X14="○",$A14>=AT$8,$A14<=AT$9,K14>=3980),IF(SUM(AT$10:AT13)-ROUNDDOWN($K14*AT$5/100,0)<-AT$6,-AT$6-SUM(AT$10:AT13),-ROUNDDOWN($K14*AT$5/100,0)),0) -> 0 | AU14: =IF(O14="○",IF(SUM(AU$10:AU13)-ROUNDDOWN($K14*AU$5/100,0)<-AU$6,-AU$6-SUM(AU$10:AU13),-ROUNDDOWN($K14*AU$5/100,0)),0) -> 0 | AV14: =IF(P14="○",IF(SUM(AV$10:AV13)-ROUNDDOWN($K14*AV$5/100,0)<-AV$6,-AV$6-SUM(AV$10:AV13),-ROUNDDOWN($K14*AV$5/100,0)),0) -> 0 | AW14: =IF(Q14="○",IF(SUM(AW$10:AW13)-ROUNDDOWN($K14*AW$5/100,0)<-AW$6,-AW$6-SUM(AW$10:AW13),-ROUNDDOWN($K14*AW$5/100,0)),0) -> 0 | AX14: =IF(R14="○",IF(SUM(AX$10:AX13)-ROUNDDOWN($K14*AX$5/100,0)<-AX$6,-AX$6-SUM(AX$10:AX13),-ROUNDDOWN($K14*AX$5/100,0)),0) -> 0 | AY14: 0 | AZ14: =-ROUNDDOWN($K14*AY14/100,0) -> 0 | BA14: =-ROUNDDOWN($K14*AI14/100,0) -> 0 | BC14: =-ROUNDDOWN($K14*BB14/100,0) -> 0 | BD14: 0 | BE14: =-ROUNDDOWN($K14*BD14/100,0) -> 0 | BF14: 0 | BG14: =-ROUNDDOWN($K14*BF14/100,0) -> 0 | BH14: 0 | BI14: =-ROUNDDOWN($K14*BH14/100,0) -> 0 | BJ14: =IF(AND(BJ$7="○",$A14>=BJ$8,$A14<=BJ$9),IF(SUM(BJ$10:BJ13)-ROUNDDOWN($M14*BJ$5/100,0)<-BJ$6,-BJ$6-SUM(BJ$10:BJ13),-ROUNDDOWN($M14*BJ$5/100,0)),0) -> 0 | BK14: =IF(AND(BK$7="○",$A14>=BK$8,$A14<=BK$9),IF(SUM(BK$10:BK13)-ROUNDDOWN($L14*BK$5/100,0)<-BK$6,-BK$6-SUM(BK$10:BK13),-ROUNDDOWN($L14*BK$5/100,0)),0) -> 0 | BL14: =IF(AND(BL$7="○",$A14>=BL$8,$A14<=BL$9),IF(SUM(BL$10:BL13)-ROUNDDOWN($L14*BL$5/100,0)<-BL$6,-BL$6-SUM(BL$10:BL13),-ROUNDDOWN($L14*BL$5/100,0)),0) -> 0 | BM14: =IF(AND(BM$7="○",$A14>=BM$8,$A14<=BM$9),IF(SUM(BM$10:BM13)-ROUNDDOWN($M14*BM$5/100,0)<-BM$6,-BM$6-SUM(BM$10:BM13),-ROUNDDOWN($M14*BM$5/100,0)),0) -> 0 | BN14: =IF(AND(BN$7="○",$A14>=BN$8,$A14<=BN$9),IF(SUM(BN$10:BN13)-ROUNDDOWN($M14*BN$5/100,0)<-BN$6,-BN$6-SUM(BN$10:BN13),-ROUNDDOWN($M14*BN$5/100,0)),0) -> 0 | BO14: =IF(AND(BO$7="○",$A14>=BO$8,$A14<=BO$9),IF(SUM(BO$10:BO13)-ROUNDDOWN($M14*BO$5/100,0)<-BO$6,-BO$6-SUM(BO$10:BO13),-ROUNDDOWN($M14*BO$5/100,0)),0) -> 0 | BP14: =IF(AND(BP$7="○",$A14>=BP$8,$A14<=BP$9),IF(SUM(BP$10:BP13)-ROUNDDOWN($M14*BP$5/100,0)<-BP$6,-BP$6-SUM(BP$10:BP13),-ROUNDDOWN($M14*BP$5/100,0)),0) -> 0 | BQ14: =IF(AND(BQ$7="○",$A14>=BQ$8,$A14<=BQ$9),IF(SUM(BQ$10:BQ13)-ROUNDDOWN($L14*BQ$5/100,0)<-BQ$6,-BQ$6-SUM(BQ$10:BQ13),-ROUNDDOWN($L14*BQ$5/100,0)),0) -> 0 | BR14: =IF(AND(BR$7="○",$A14>=BR$8,$A14<=BR$9),IF(SUM(BR$10:BR13)-ROUNDDOWN($M14*BR$5/100,0)<-BR$6,-BR$6-SUM(BR$10:BR13),-ROUNDDOWN($M14*BR$5/100,0)),0) -> 0 | BS14: =IF(AND(BS$7="○",$A14>=BS$8,$A14<=BS$9),IF(SUM(BS$10:BS13)-ROUNDDOWN($M14*BS$5/100,0)<-BS$6,-BS$6-SUM(BS$10:BS13),-ROUNDDOWN($M14*BS$5/100,0)),0) -> 0 | BT14: =IF(AND(BT$7="○",$A14>=BT$8,$A14<=BT$9),IF(SUM(BT$10:BT13)-ROUNDDOWN($M14*BT$5/100,0)<-BT$6,-BT$6-SUM(BT$10:BT13),-ROUNDDOWN($M14*BT$5/100,0)),0) -> 0 | BU14: =IF(AND(BU$7="○",$A14>=BU$8,$A14<=BU$9),IF(SUM(BU$10:BU13)-ROUNDDOWN($M14*BU$5/100,0)<-BU$6,-BU$6-SUM(BU$10:BU13),-ROUNDDOWN($M14*BU$5/100,0)),0) -> 0 | BV14: =IF(AND(BV$7="○",$A14>=BV$8,$A14<=BV$9),IF(SUM(BV$10:BV13)-ROUNDDOWN($M14*BV$5/100,0)<-BV$6,-BV$6-SUM(BV$10:BV13),-ROUNDDOWN($M14*BV$5/100,0)),0) -> 0 | BW14: =IF(AND(BW$7="○",$A14>=BW$8,$A14<=BW$9),IF(SUM(BW$10:BW13)-ROUNDDOWN($M14*BW$5/100,0)<-BW$6,-BW$6-SUM(BW$10:BW13),-ROUNDDOWN($M14*BW$5/100,0)),0) -> 0 | BX14: =IF(AND(T14="○",$A14>=BX$8,$A14<=BX$9),IF(SUM(BX$10:BX13)-ROUNDDOWN($K14*BX$5/100,0)<-BX$6,-BX$6-SUM(BX$10:BX13),-ROUNDDOWN($K14*BX$5/100,0)),0) -> 0 | BY14: =IF(AND(U14="○",$A14>=BY$8,$A14<=BY$9),IF(SUM(BY$10:BY13)-ROUNDDOWN($K14*BY$5/100,0)<-BY$6,-BY$6-SUM(BY$10:BY13),-ROUNDDOWN($K14*BY$5/100,0)),0) -> 0 | BZ14: =IF(AND(V14="○",$A14>=BZ$8,$A14<=BZ$9),IF(SUM(BZ$10:BZ13)-ROUNDDOWN($K14*BZ$5/100,0)<-BZ$6,-BZ$6-SUM(BZ$10:BZ13),-ROUNDDOWN($K14*BZ$5/100,0)),0) -> 0 | CA14: =IF(AND(W14="○",$A14>=CA$8,$A14<=CA$9),IF(SUM(CA$10:CA13)-ROUNDDOWN($K14*CA$5/100,0)<-CA$6,-CA$6-SUM(CA$10:CA13),-ROUNDDOWN($K14*CA$5/100,0)),0) -> 0 | CG14: =+SUM(AJ14:CF14,BC14,BE14,AZ14,BA14,BG14,BI14) -> 0 | CH14: =+CG14+N14 -> 0 | CI14: =IFERROR(ROUNDDOWN((CH14/G14),0),0) -> 0 | CO14: =IFERROR(CN14-CI14,0) -> 0 | CP14: =IFERROR(CN14/CI14,0) -> 0 | CR14: =+CO14*G14 -> 0 | CT14: =INDEX([2]マスタ!$A:$A,MATCH(D14,[2]マスタ!$C:$C,0)) -> #N/A | CU14: =IFERROR(TEXT(TODAY(),"yyyymmdd")&"_"&ROUNDDOWN(H14+I14,0)&"-"&ROUNDDOWN(CI14,0),"") -> 20260620_0-0
G15: 1 | H15: =+F15*G15 -> 0 | K15: =+ROUNDDOWN((H15+I15)/100,0)*100 -> 0 | L15: =+ROUNDDOWN((H15+I15)/1.1/100,0)*100 -> 0 | M15: =+ROUNDDOWN((H15+I15)/1.1/200,0)*200 -> 0 | N15: =+H15+I15+J15 -> 0 | O15: =IF(OR(WEEKDAY($A15,2)=2,WEEKDAY($A15,2)=4),"○","✕") -> ✕ | P15: =+IF(MOD(TEXT($A15,"DD"),5)=0,"○","✕") -> ○ | Q15: =+IF((TEXT($A15,"DD")+0)=1,"○","✕") -> ✕ | R15: =+IF((TEXT($A15,"DD")+0)=18,"○","✕") -> ✕ | S15: 0 | T15: ✕ | U15: ✕ | V15: ✕ | W15: ✕ | X15: ○ | Y15: ✕ | Z15: ✕ | AA15: ✕ | AB15: ✕ | AC15: ✕ | AD15: =+IF(ISERROR(VLOOKUP($B15,AD$10:AD14,1,0)),IF(AND($N15>=1000,$A15>=AO$8,$A15<=AO$9),$B15,""),"") | AE15: =+IF(ISERROR(VLOOKUP($B15,AE$10:AE14,1,0)),IF(AND($N15>=1000,$A15>=AP$8,$A15<=AP$9),$B15,""),"") | AF15: =+IF(ISERROR(VLOOKUP($B15,AF$10:AF14,1,0)),IF(AND($N15>=1000,$A15>=AQ$8,$A15<=AQ$9),$B15,""),"") | AG15: =+IF(ISERROR(VLOOKUP($B15,AG$10:AG14,1,0)),IF(AND($N15>=1000,$A15>=AR$8,$A15<=AR$9),$B15,""),"") | AI15: 0 | AJ15: =IF(AND(AJ$7="○",$A15>=AJ$8,$A15<=AJ$9),IF(SUM(AJ$10:AJ14)-ROUNDDOWN($K15*AJ$5/100,0)<-AJ$6,-AJ$6-SUM(AJ$10:AJ14),-ROUNDDOWN($K15*AJ$5/100,0)),0) -> 0 | AK15: =IF(AND(AK$7="○",$A15>=AK$8,$A15<=AK$9),IF(SUM(AK$10:AK14)-ROUNDDOWN($L15*AK$5/100,0)<-AK$6,-AK$6-SUM(AK$10:AK14),-ROUNDDOWN($L15*AK$5/100,0)),0) -> 0 | AL15: =IF(AND(AL$7="○",$A15>=AL$8,$A15<=AL$9),IF(SUM(AL$10:AL14)-ROUNDDOWN($N15*AL$5/100,0)<-AL$6,-AL$6-SUM(AL$10:AL14),-ROUNDDOWN($N15*AL$5/100,0)),0) -> 0 | AM15: =IF(AND(AM$7="○",$A15>=AM$8,$A15<=AM$9),IF(SUM(AM$10:AM14)-ROUNDDOWN($L15*AM$5/100,0)<-AM$6,-AM$6-SUM(AM$10:AM14),-ROUNDDOWN($L15*AM$5/100,0)),0) -> 0 | AN15: =IF(AND(AN$7="○",$A15>=AN$8,$A15<=AN$9),IF(SUM(AN$10:AN14)-ROUNDDOWN($M15*AN$5/100,0)<-AN$6,-AN$6-SUM(AN$10:AN14),-ROUNDDOWN($M15*AN$5/100,0)),0) -> 0 | AO15: =IF(AND($A15>=AO$8,$A15<=AO$9),IF(SUM(AO$10:AO14)-ROUNDDOWN($K15*AO$5/100,0)<-AO$6,-AO$6-SUM(AO$10:AO14),-ROUNDDOWN($K15*AO$5/100,0)),0) -> 0 | AP15: =IF(AND($A15>=AP$8,$A15<=AP$9),IF(SUM(AP$10:AP14)-ROUNDDOWN($K15*AP$5/100,0)<-AP$6,-AP$6-SUM(AP$10:AP14),-ROUNDDOWN($K15*AP$5/100,0)),0) -> 0 | AQ15: =IF(AND($A15>=AQ$8,$A15<=AQ$9),IF(SUM(AQ$10:AQ14)-ROUNDDOWN($K15*AQ$5/100,0)<-AQ$6,-AQ$6-SUM(AQ$10:AQ14),-ROUNDDOWN($K15*AQ$5/100,0)),0) -> 0 | AR15: =IF(AND($A15>=AR$8,$A15<=AR$9),IF(SUM(AR$10:AR14)-ROUNDDOWN($K15*AR$5/100,0)<-AR$6,-AR$6-SUM(AR$10:AR14),-ROUNDDOWN($K15*AR$5/100,0)),0) -> 0 | AS15: =IF(SUMIFS(AS$10:AS14,$A$10:$A14,$A15)-ROUNDDOWN($K15*$S15/100,0)<-$S15*1000,-$S15*1000-SUMIFS(AS$10:AS14,$A$10:$A14,$A15),-ROUNDDOWN($K15*$S15/100,0)) -> 0 | AT15: =IF(AND(X15="○",$A15>=AT$8,$A15<=AT$9,K15>=3980),IF(SUM(AT$10:AT14)-ROUNDDOWN($K15*AT$5/100,0)<-AT$6,-AT$6-SUM(AT$10:AT14),-ROUNDDOWN($K15*AT$5/100,0)),0) -> 0 | AU15: =IF(O15="○",IF(SUM(AU$10:AU14)-ROUNDDOWN($K15*AU$5/100,0)<-AU$6,-AU$6-SUM(AU$10:AU14),-ROUNDDOWN($K15*AU$5/100,0)),0) -> 0 | AV15: =IF(P15="○",IF(SUM(AV$10:AV14)-ROUNDDOWN($K15*AV$5/100,0)<-AV$6,-AV$6-SUM(AV$10:AV14),-ROUNDDOWN($K15*AV$5/100,0)),0) -> 0 | AW15: =IF(Q15="○",IF(SUM(AW$10:AW14)-ROUNDDOWN($K15*AW$5/100,0)<-AW$6,-AW$6-SUM(AW$10:AW14),-ROUNDDOWN($K15*AW$5/100,0)),0) -> 0 | AX15: =IF(R15="○",IF(SUM(AX$10:AX14)-ROUNDDOWN($K15*AX$5/100,0)<-AX$6,-AX$6-SUM(AX$10:AX14),-ROUNDDOWN($K15*AX$5/100,0)),0) -> 0 | AY15: 0 | AZ15: =-ROUNDDOWN($K15*AY15/100,0) -> 0 | BA15: =-ROUNDDOWN($K15*AI15/100,0) -> 0 | BC15: =-ROUNDDOWN($K15*BB15/100,0) -> 0 | BD15: 0 | BE15: =-ROUNDDOWN($K15*BD15/100,0) -> 0 | BF15: 0 | BG15: =-ROUNDDOWN($K15*BF15/100,0) -> 0 | BH15: 0 | BI15: =-ROUNDDOWN($K15*BH15/100,0) -> 0 | BJ15: =IF(AND(BJ$7="○",$A15>=BJ$8,$A15<=BJ$9),IF(SUM(BJ$10:BJ14)-ROUNDDOWN($M15*BJ$5/100,0)<-BJ$6,-BJ$6-SUM(BJ$10:BJ14),-ROUNDDOWN($M15*BJ$5/100,0)),0) -> 0 | BK15: =IF(AND(BK$7="○",$A15>=BK$8,$A15<=BK$9),IF(SUM(BK$10:BK14)-ROUNDDOWN($L15*BK$5/100,0)<-BK$6,-BK$6-SUM(BK$10:BK14),-ROUNDDOWN($L15*BK$5/100,0)),0) -> 0 | BL15: =IF(AND(BL$7="○",$A15>=BL$8,$A15<=BL$9),IF(SUM(BL$10:BL14)-ROUNDDOWN($L15*BL$5/100,0)<-BL$6,-BL$6-SUM(BL$10:BL14),-ROUNDDOWN($L15*BL$5/100,0)),0) -> 0 | BM15: =IF(AND(BM$7="○",$A15>=BM$8,$A15<=BM$9),IF(SUM(BM$10:BM14)-ROUNDDOWN($M15*BM$5/100,0)<-BM$6,-BM$6-SUM(BM$10:BM14),-ROUNDDOWN($M15*BM$5/100,0)),0) -> 0 | BN15: =IF(AND(BN$7="○",$A15>=BN$8,$A15<=BN$9),IF(SUM(BN$10:BN14)-ROUNDDOWN($M15*BN$5/100,0)<-BN$6,-BN$6-SUM(BN$10:BN14),-ROUNDDOWN($M15*BN$5/100,0)),0) -> 0 | BO15: =IF(AND(BO$7="○",$A15>=BO$8,$A15<=BO$9),IF(SUM(BO$10:BO14)-ROUNDDOWN($M15*BO$5/100,0)<-BO$6,-BO$6-SUM(BO$10:BO14),-ROUNDDOWN($M15*BO$5/100,0)),0) -> 0 | BP15: =IF(AND(BP$7="○",$A15>=BP$8,$A15<=BP$9),IF(SUM(BP$10:BP14)-ROUNDDOWN($M15*BP$5/100,0)<-BP$6,-BP$6-SUM(BP$10:BP14),-ROUNDDOWN($M15*BP$5/100,0)),0) -> 0 | BQ15: =IF(AND(BQ$7="○",$A15>=BQ$8,$A15<=BQ$9),IF(SUM(BQ$10:BQ14)-ROUNDDOWN($L15*BQ$5/100,0)<-BQ$6,-BQ$6-SUM(BQ$10:BQ14),-ROUNDDOWN($L15*BQ$5/100,0)),0) -> 0 | BR15: =IF(AND(BR$7="○",$A15>=BR$8,$A15<=BR$9),IF(SUM(BR$10:BR14)-ROUNDDOWN($M15*BR$5/100,0)<-BR$6,-BR$6-SUM(BR$10:BR14),-ROUNDDOWN($M15*BR$5/100,0)),0) -> 0 | BS15: =IF(AND(BS$7="○",$A15>=BS$8,$A15<=BS$9),IF(SUM(BS$10:BS14)-ROUNDDOWN($M15*BS$5/100,0)<-BS$6,-BS$6-SUM(BS$10:BS14),-ROUNDDOWN($M15*BS$5/100,0)),0) -> 0 | BT15: =IF(AND(BT$7="○",$A15>=BT$8,$A15<=BT$9),IF(SUM(BT$10:BT14)-ROUNDDOWN($M15*BT$5/100,0)<-BT$6,-BT$6-SUM(BT$10:BT14),-ROUNDDOWN($M15*BT$5/100,0)),0) -> 0 | BU15: =IF(AND(BU$7="○",$A15>=BU$8,$A15<=BU$9),IF(SUM(BU$10:BU14)-ROUNDDOWN($M15*BU$5/100,0)<-BU$6,-BU$6-SUM(BU$10:BU14),-ROUNDDOWN($M15*BU$5/100,0)),0) -> 0 | BV15: =IF(AND(BV$7="○",$A15>=BV$8,$A15<=BV$9),IF(SUM(BV$10:BV14)-ROUNDDOWN($M15*BV$5/100,0)<-BV$6,-BV$6-SUM(BV$10:BV14),-ROUNDDOWN($M15*BV$5/100,0)),0) -> 0 | BW15: =IF(AND(BW$7="○",$A15>=BW$8,$A15<=BW$9),IF(SUM(BW$10:BW14)-ROUNDDOWN($M15*BW$5/100,0)<-BW$6,-BW$6-SUM(BW$10:BW14),-ROUNDDOWN($M15*BW$5/100,0)),0) -> 0 | BX15: =IF(AND(T15="○",$A15>=BX$8,$A15<=BX$9),IF(SUM(BX$10:BX14)-ROUNDDOWN($K15*BX$5/100,0)<-BX$6,-BX$6-SUM(BX$10:BX14),-ROUNDDOWN($K15*BX$5/100,0)),0) -> 0 | BY15: =IF(AND(U15="○",$A15>=BY$8,$A15<=BY$9),IF(SUM(BY$10:BY14)-ROUNDDOWN($K15*BY$5/100,0)<-BY$6,-BY$6-SUM(BY$10:BY14),-ROUNDDOWN($K15*BY$5/100,0)),0) -> 0 | BZ15: =IF(AND(V15="○",$A15>=BZ$8,$A15<=BZ$9),IF(SUM(BZ$10:BZ14)-ROUNDDOWN($K15*BZ$5/100,0)<-BZ$6,-BZ$6-SUM(BZ$10:BZ14),-ROUNDDOWN($K15*BZ$5/100,0)),0) -> 0 | CA15: =IF(AND(W15="○",$A15>=CA$8,$A15<=CA$9),IF(SUM(CA$10:CA14)-ROUNDDOWN($K15*CA$5/100,0)<-CA$6,-CA$6-SUM(CA$10:CA14),-ROUNDDOWN($K15*CA$5/100,0)),0) -> 0 | CG15: =+SUM(AJ15:CF15,BC15,BE15,AZ15,BA15,BG15,BI15) -> 0 | CH15: =+CG15+N15 -> 0 | CI15: =IFERROR(ROUNDDOWN((CH15/G15),0),0) -> 0 | CO15: =IFERROR(CN15-CI15,0) -> 0 | CP15: =IFERROR(CN15/CI15,0) -> 0 | CR15: =+CO15*G15 -> 0 | CT15: =INDEX([2]マスタ!$A:$A,MATCH(D15,[2]マスタ!$C:$C,0)) -> #N/A | CU15: =IFERROR(TEXT(TODAY(),"yyyymmdd")&"_"&ROUNDDOWN(H15+I15,0)&"-"&ROUNDDOWN(CI15,0),"") -> 20260620_0-0
G16: 1 | H16: =+F16*G16 -> 0 | K16: =+ROUNDDOWN((H16+I16)/100,0)*100 -> 0 | L16: =+ROUNDDOWN((H16+I16)/1.1/100,0)*100 -> 0 | M16: =+ROUNDDOWN((H16+I16)/1.1/200,0)*200 -> 0 | N16: =+H16+I16+J16 -> 0 | O16: =IF(OR(WEEKDAY($A16,2)=2,WEEKDAY($A16,2)=4),"○","✕") -> ✕ | P16: =+IF(MOD(TEXT($A16,"DD"),5)=0,"○","✕") -> ○ | Q16: =+IF((TEXT($A16,"DD")+0)=1,"○","✕") -> ✕ | R16: =+IF((TEXT($A16,"DD")+0)=18,"○","✕") -> ✕ | S16: 0 | T16: ✕ | U16: ✕ | V16: ✕ | W16: ✕ | X16: ○ | Y16: ✕ | Z16: ✕ | AA16: ✕ | AB16: ✕ | AC16: ✕ | AD16: =+IF(ISERROR(VLOOKUP($B16,AD$10:AD15,1,0)),IF(AND($N16>=1000,$A16>=AO$8,$A16<=AO$9),$B16,""),"") | AE16: =+IF(ISERROR(VLOOKUP($B16,AE$10:AE15,1,0)),IF(AND($N16>=1000,$A16>=AP$8,$A16<=AP$9),$B16,""),"") | AF16: =+IF(ISERROR(VLOOKUP($B16,AF$10:AF15,1,0)),IF(AND($N16>=1000,$A16>=AQ$8,$A16<=AQ$9),$B16,""),"") | AG16: =+IF(ISERROR(VLOOKUP($B16,AG$10:AG15,1,0)),IF(AND($N16>=1000,$A16>=AR$8,$A16<=AR$9),$B16,""),"") | AI16: 0 | AJ16: =IF(AND(AJ$7="○",$A16>=AJ$8,$A16<=AJ$9),IF(SUM(AJ$10:AJ15)-ROUNDDOWN($K16*AJ$5/100,0)<-AJ$6,-AJ$6-SUM(AJ$10:AJ15),-ROUNDDOWN($K16*AJ$5/100,0)),0) -> 0 | AK16: =IF(AND(AK$7="○",$A16>=AK$8,$A16<=AK$9),IF(SUM(AK$10:AK15)-ROUNDDOWN($L16*AK$5/100,0)<-AK$6,-AK$6-SUM(AK$10:AK15),-ROUNDDOWN($L16*AK$5/100,0)),0) -> 0 | AL16: =IF(AND(AL$7="○",$A16>=AL$8,$A16<=AL$9),IF(SUM(AL$10:AL15)-ROUNDDOWN($N16*AL$5/100,0)<-AL$6,-AL$6-SUM(AL$10:AL15),-ROUNDDOWN($N16*AL$5/100,0)),0) -> 0 | AM16: =IF(AND(AM$7="○",$A16>=AM$8,$A16<=AM$9),IF(SUM(AM$10:AM15)-ROUNDDOWN($L16*AM$5/100,0)<-AM$6,-AM$6-SUM(AM$10:AM15),-ROUNDDOWN($L16*AM$5/100,0)),0) -> 0 | AN16: =IF(AND(AN$7="○",$A16>=AN$8,$A16<=AN$9),IF(SUM(AN$10:AN15)-ROUNDDOWN($M16*AN$5/100,0)<-AN$6,-AN$6-SUM(AN$10:AN15),-ROUNDDOWN($M16*AN$5/100,0)),0) -> 0 | AO16: =IF(AND($A16>=AO$8,$A16<=AO$9),IF(SUM(AO$10:AO15)-ROUNDDOWN($K16*AO$5/100,0)<-AO$6,-AO$6-SUM(AO$10:AO15),-ROUNDDOWN($K16*AO$5/100,0)),0) -> 0 | AP16: =IF(AND($A16>=AP$8,$A16<=AP$9),IF(SUM(AP$10:AP15)-ROUNDDOWN($K16*AP$5/100,0)<-AP$6,-AP$6-SUM(AP$10:AP15),-ROUNDDOWN($K16*AP$5/100,0)),0) -> 0 | AQ16: =IF(AND($A16>=AQ$8,$A16<=AQ$9),IF(SUM(AQ$10:AQ15)-ROUNDDOWN($K16*AQ$5/100,0)<-AQ$6,-AQ$6-SUM(AQ$10:AQ15),-ROUNDDOWN($K16*AQ$5/100,0)),0) -> 0 | AR16: =IF(AND($A16>=AR$8,$A16<=AR$9),IF(SUM(AR$10:AR15)-ROUNDDOWN($K16*AR$5/100,0)<-AR$6,-AR$6-SUM(AR$10:AR15),-ROUNDDOWN($K16*AR$5/100,0)),0) -> 0 | AS16: =IF(SUMIFS(AS$10:AS15,$A$10:$A15,$A16)-ROUNDDOWN($K16*$S16/100,0)<-$S16*1000,-$S16*1000-SUMIFS(AS$10:AS15,$A$10:$A15,$A16),-ROUNDDOWN($K16*$S16/100,0)) -> 0 | AT16: =IF(AND(X16="○",$A16>=AT$8,$A16<=AT$9,K16>=3980),IF(SUM(AT$10:AT15)-ROUNDDOWN($K16*AT$5/100,0)<-AT$6,-AT$6-SUM(AT$10:AT15),-ROUNDDOWN($K16*AT$5/100,0)),0) -> 0 | AU16: =IF(O16="○",IF(SUM(AU$10:AU15)-ROUNDDOWN($K16*AU$5/100,0)<-AU$6,-AU$6-SUM(AU$10:AU15),-ROUNDDOWN($K16*AU$5/100,0)),0) -> 0 | AV16: =IF(P16="○",IF(SUM(AV$10:AV15)-ROUNDDOWN($K16*AV$5/100,0)<-AV$6,-AV$6-SUM(AV$10:AV15),-ROUNDDOWN($K16*AV$5/100,0)),0) -> 0 | AW16: =IF(Q16="○",IF(SUM(AW$10:AW15)-ROUNDDOWN($K16*AW$5/100,0)<-AW$6,-AW$6-SUM(AW$10:AW15),-ROUNDDOWN($K16*AW$5/100,0)),0) -> 0 | AX16: =IF(R16="○",IF(SUM(AX$10:AX15)-ROUNDDOWN($K16*AX$5/100,0)<-AX$6,-AX$6-SUM(AX$10:AX15),-ROUNDDOWN($K16*AX$5/100,0)),0) -> 0 | AY16: 0 | AZ16: =-ROUNDDOWN($K16*AY16/100,0) -> 0 | BA16: =-ROUNDDOWN($K16*AI16/100,0) -> 0 | BC16: =-ROUNDDOWN($K16*BB16/100,0) -> 0 | BD16: 0 | BE16: =-ROUNDDOWN($K16*BD16/100,0) -> 0 | BF16: 0 | BG16: =-ROUNDDOWN($K16*BF16/100,0) -> 0 | BH16: 0 | BI16: =-ROUNDDOWN($K16*BH16/100,0) -> 0 | BJ16: =IF(AND(BJ$7="○",$A16>=BJ$8,$A16<=BJ$9),IF(SUM(BJ$10:BJ15)-ROUNDDOWN($M16*BJ$5/100,0)<-BJ$6,-BJ$6-SUM(BJ$10:BJ15),-ROUNDDOWN($M16*BJ$5/100,0)),0) -> 0 | BK16: =IF(AND(BK$7="○",$A16>=BK$8,$A16<=BK$9),IF(SUM(BK$10:BK15)-ROUNDDOWN($L16*BK$5/100,0)<-BK$6,-BK$6-SUM(BK$10:BK15),-ROUNDDOWN($L16*BK$5/100,0)),0) -> 0 | BL16: =IF(AND(BL$7="○",$A16>=BL$8,$A16<=BL$9),IF(SUM(BL$10:BL15)-ROUNDDOWN($L16*BL$5/100,0)<-BL$6,-BL$6-SUM(BL$10:BL15),-ROUNDDOWN($L16*BL$5/100,0)),0) -> 0 | BM16: =IF(AND(BM$7="○",$A16>=BM$8,$A16<=BM$9),IF(SUM(BM$10:BM15)-ROUNDDOWN($M16*BM$5/100,0)<-BM$6,-BM$6-SUM(BM$10:BM15),-ROUNDDOWN($M16*BM$5/100,0)),0) -> 0 | BN16: =IF(AND(BN$7="○",$A16>=BN$8,$A16<=BN$9),IF(SUM(BN$10:BN15)-ROUNDDOWN($M16*BN$5/100,0)<-BN$6,-BN$6-SUM(BN$10:BN15),-ROUNDDOWN($M16*BN$5/100,0)),0) -> 0 | BO16: =IF(AND(BO$7="○",$A16>=BO$8,$A16<=BO$9),IF(SUM(BO$10:BO15)-ROUNDDOWN($M16*BO$5/100,0)<-BO$6,-BO$6-SUM(BO$10:BO15),-ROUNDDOWN($M16*BO$5/100,0)),0) -> 0 | BP16: =IF(AND(BP$7="○",$A16>=BP$8,$A16<=BP$9),IF(SUM(BP$10:BP15)-ROUNDDOWN($M16*BP$5/100,0)<-BP$6,-BP$6-SUM(BP$10:BP15),-ROUNDDOWN($M16*BP$5/100,0)),0) -> 0 | BQ16: =IF(AND(BQ$7="○",$A16>=BQ$8,$A16<=BQ$9),IF(SUM(BQ$10:BQ15)-ROUNDDOWN($L16*BQ$5/100,0)<-BQ$6,-BQ$6-SUM(BQ$10:BQ15),-ROUNDDOWN($L16*BQ$5/100,0)),0) -> 0 | BR16: =IF(AND(BR$7="○",$A16>=BR$8,$A16<=BR$9),IF(SUM(BR$10:BR15)-ROUNDDOWN($M16*BR$5/100,0)<-BR$6,-BR$6-SUM(BR$10:BR15),-ROUNDDOWN($M16*BR$5/100,0)),0) -> 0 | BS16: =IF(AND(BS$7="○",$A16>=BS$8,$A16<=BS$9),IF(SUM(BS$10:BS15)-ROUNDDOWN($M16*BS$5/100,0)<-BS$6,-BS$6-SUM(BS$10:BS15),-ROUNDDOWN($M16*BS$5/100,0)),0) -> 0 | BT16: =IF(AND(BT$7="○",$A16>=BT$8,$A16<=BT$9),IF(SUM(BT$10:BT15)-ROUNDDOWN($M16*BT$5/100,0)<-BT$6,-BT$6-SUM(BT$10:BT15),-ROUNDDOWN($M16*BT$5/100,0)),0) -> 0 | BU16: =IF(AND(BU$7="○",$A16>=BU$8,$A16<=BU$9),IF(SUM(BU$10:BU15)-ROUNDDOWN($M16*BU$5/100,0)<-BU$6,-BU$6-SUM(BU$10:BU15),-ROUNDDOWN($M16*BU$5/100,0)),0) -> 0 | BV16: =IF(AND(BV$7="○",$A16>=BV$8,$A16<=BV$9),IF(SUM(BV$10:BV15)-ROUNDDOWN($M16*BV$5/100,0)<-BV$6,-BV$6-SUM(BV$10:BV15),-ROUNDDOWN($M16*BV$5/100,0)),0) -> 0 | BW16: =IF(AND(BW$7="○",$A16>=BW$8,$A16<=BW$9),IF(SUM(BW$10:BW15)-ROUNDDOWN($M16*BW$5/100,0)<-BW$6,-BW$6-SUM(BW$10:BW15),-ROUNDDOWN($M16*BW$5/100,0)),0) -> 0 | BX16: =IF(AND(T16="○",$A16>=BX$8,$A16<=BX$9),IF(SUM(BX$10:BX15)-ROUNDDOWN($K16*BX$5/100,0)<-BX$6,-BX$6-SUM(BX$10:BX15),-ROUNDDOWN($K16*BX$5/100,0)),0) -> 0 | BY16: =IF(AND(U16="○",$A16>=BY$8,$A16<=BY$9),IF(SUM(BY$10:BY15)-ROUNDDOWN($K16*BY$5/100,0)<-BY$6,-BY$6-SUM(BY$10:BY15),-ROUNDDOWN($K16*BY$5/100,0)),0) -> 0 | BZ16: =IF(AND(V16="○",$A16>=BZ$8,$A16<=BZ$9),IF(SUM(BZ$10:BZ15)-ROUNDDOWN($K16*BZ$5/100,0)<-BZ$6,-BZ$6-SUM(BZ$10:BZ15),-ROUNDDOWN($K16*BZ$5/100,0)),0) -> 0 | CA16: =IF(AND(W16="○",$A16>=CA$8,$A16<=CA$9),IF(SUM(CA$10:CA15)-ROUNDDOWN($K16*CA$5/100,0)<-CA$6,-CA$6-SUM(CA$10:CA15),-ROUNDDOWN($K16*CA$5/100,0)),0) -> 0 | CG16: =+SUM(AJ16:CF16,BC16,BE16,AZ16,BA16,BG16,BI16) -> 0 | CH16: =+CG16+N16 -> 0 | CI16: =IFERROR(ROUNDDOWN((CH16/G16),0),0) -> 0 | CO16: =IFERROR(CN16-CI16,0) -> 0 | CP16: =IFERROR(CN16/CI16,0) -> 0 | CR16: =+CO16*G16 -> 0 | CT16: =INDEX([2]マスタ!$A:$A,MATCH(D16,[2]マスタ!$C:$C,0)) -> #N/A | CU16: =IFERROR(TEXT(TODAY(),"yyyymmdd")&"_"&ROUNDDOWN(H16+I16,0)&"-"&ROUNDDOWN(CI16,0),"") -> 20260620_0-0
G17: 1 | H17: =+F17*G17 -> 0 | K17: =+ROUNDDOWN((H17+I17)/100,0)*100 -> 0 | L17: =+ROUNDDOWN((H17+I17)/1.1/100,0)*100 -> 0 | M17: =+ROUNDDOWN((H17+I17)/1.1/200,0)*200 -> 0 | N17: =+H17+I17+J17 -> 0 | O17: =IF(OR(WEEKDAY($A17,2)=2,WEEKDAY($A17,2)=4),"○","✕") -> ✕ | P17: =+IF(MOD(TEXT($A17,"DD"),5)=0,"○","✕") -> ○ | Q17: =+IF((TEXT($A17,"DD")+0)=1,"○","✕") -> ✕ | R17: =+IF((TEXT($A17,"DD")+0)=18,"○","✕") -> ✕ | S17: 0 | T17: ✕ | U17: ✕ | V17: ✕ | W17: ✕ | X17: ○ | Y17: ✕ | Z17: ✕ | AA17: ✕ | AB17: ✕ | AC17: ✕ | AD17: =+IF(ISERROR(VLOOKUP($B17,AD$10:AD16,1,0)),IF(AND($N17>=1000,$A17>=AO$8,$A17<=AO$9),$B17,""),"") | AE17: =+IF(ISERROR(VLOOKUP($B17,AE$10:AE16,1,0)),IF(AND($N17>=1000,$A17>=AP$8,$A17<=AP$9),$B17,""),"") | AF17: =+IF(ISERROR(VLOOKUP($B17,AF$10:AF16,1,0)),IF(AND($N17>=1000,$A17>=AQ$8,$A17<=AQ$9),$B17,""),"") | AG17: =+IF(ISERROR(VLOOKUP($B17,AG$10:AG16,1,0)),IF(AND($N17>=1000,$A17>=AR$8,$A17<=AR$9),$B17,""),"") | AI17: 0 | AJ17: =IF(AND(AJ$7="○",$A17>=AJ$8,$A17<=AJ$9),IF(SUM(AJ$10:AJ16)-ROUNDDOWN($K17*AJ$5/100,0)<-AJ$6,-AJ$6-SUM(AJ$10:AJ16),-ROUNDDOWN($K17*AJ$5/100,0)),0) -> 0 | AK17: =IF(AND(AK$7="○",$A17>=AK$8,$A17<=AK$9),IF(SUM(AK$10:AK16)-ROUNDDOWN($L17*AK$5/100,0)<-AK$6,-AK$6-SUM(AK$10:AK16),-ROUNDDOWN($L17*AK$5/100,0)),0) -> 0 | AL17: =IF(AND(AL$7="○",$A17>=AL$8,$A17<=AL$9),IF(SUM(AL$10:AL16)-ROUNDDOWN($N17*AL$5/100,0)<-AL$6,-AL$6-SUM(AL$10:AL16),-ROUNDDOWN($N17*AL$5/100,0)),0) -> 0 | AM17: =IF(AND(AM$7="○",$A17>=AM$8,$A17<=AM$9),IF(SUM(AM$10:AM16)-ROUNDDOWN($L17*AM$5/100,0)<-AM$6,-AM$6-SUM(AM$10:AM16),-ROUNDDOWN($L17*AM$5/100,0)),0) -> 0 | AN17: =IF(AND(AN$7="○",$A17>=AN$8,$A17<=AN$9),IF(SUM(AN$10:AN16)-ROUNDDOWN($M17*AN$5/100,0)<-AN$6,-AN$6-SUM(AN$10:AN16),-ROUNDDOWN($M17*AN$5/100,0)),0) -> 0 | AO17: =IF(AND($A17>=AO$8,$A17<=AO$9),IF(SUM(AO$10:AO16)-ROUNDDOWN($K17*AO$5/100,0)<-AO$6,-AO$6-SUM(AO$10:AO16),-ROUNDDOWN($K17*AO$5/100,0)),0) -> 0 | AP17: =IF(AND($A17>=AP$8,$A17<=AP$9),IF(SUM(AP$10:AP16)-ROUNDDOWN($K17*AP$5/100,0)<-AP$6,-AP$6-SUM(AP$10:AP16),-ROUNDDOWN($K17*AP$5/100,0)),0) -> 0 | AQ17: =IF(AND($A17>=AQ$8,$A17<=AQ$9),IF(SUM(AQ$10:AQ16)-ROUNDDOWN($K17*AQ$5/100,0)<-AQ$6,-AQ$6-SUM(AQ$10:AQ16),-ROUNDDOWN($K17*AQ$5/100,0)),0) -> 0 | AR17: =IF(AND($A17>=AR$8,$A17<=AR$9),IF(SUM(AR$10:AR16)-ROUNDDOWN($K17*AR$5/100,0)<-AR$6,-AR$6-SUM(AR$10:AR16),-ROUNDDOWN($K17*AR$5/100,0)),0) -> 0 | AS17: =IF(SUMIFS(AS$10:AS16,$A$10:$A16,$A17)-ROUNDDOWN($K17*$S17/100,0)<-$S17*1000,-$S17*1000-SUMIFS(AS$10:AS16,$A$10:$A16,$A17),-ROUNDDOWN($K17*$S17/100,0)) -> 0 | AT17: =IF(AND(X17="○",$A17>=AT$8,$A17<=AT$9,K17>=3980),IF(SUM(AT$10:AT16)-ROUNDDOWN($K17*AT$5/100,0)<-AT$6,-AT$6-SUM(AT$10:AT16),-ROUNDDOWN($K17*AT$5/100,0)),0) -> 0 | AU17: =IF(O17="○",IF(SUM(AU$10:AU16)-ROUNDDOWN($K17*AU$5/100,0)<-AU$6,-AU$6-SUM(AU$10:AU16),-ROUNDDOWN($K17*AU$5/100,0)),0) -> 0 | AV17: =IF(P17="○",IF(SUM(AV$10:AV16)-ROUNDDOWN($K17*AV$5/100,0)<-AV$6,-AV$6-SUM(AV$10:AV16),-ROUNDDOWN($K17*AV$5/100,0)),0) -> 0 | AW17: =IF(Q17="○",IF(SUM(AW$10:AW16)-ROUNDDOWN($K17*AW$5/100,0)<-AW$6,-AW$6-SUM(AW$10:AW16),-ROUNDDOWN($K17*AW$5/100,0)),0) -> 0 | AX17: =IF(R17="○",IF(SUM(AX$10:AX16)-ROUNDDOWN($K17*AX$5/100,0)<-AX$6,-AX$6-SUM(AX$10:AX16),-ROUNDDOWN($K17*AX$5/100,0)),0) -> 0 | AY17: 0 | AZ17: =-ROUNDDOWN($K17*AY17/100,0) -> 0 | BA17: =-ROUNDDOWN($K17*AI17/100,0) -> 0 | BC17: =-ROUNDDOWN($K17*BB17/100,0) -> 0 | BD17: 0 | BE17: =-ROUNDDOWN($K17*BD17/100,0) -> 0 | BF17: 0 | BG17: =-ROUNDDOWN($K17*BF17/100,0) -> 0 | BH17: 0 | BI17: =-ROUNDDOWN($K17*BH17/100,0) -> 0 | BJ17: =IF(AND(BJ$7="○",$A17>=BJ$8,$A17<=BJ$9),IF(SUM(BJ$10:BJ16)-ROUNDDOWN($M17*BJ$5/100,0)<-BJ$6,-BJ$6-SUM(BJ$10:BJ16),-ROUNDDOWN($M17*BJ$5/100,0)),0) -> 0 | BK17: =IF(AND(BK$7="○",$A17>=BK$8,$A17<=BK$9),IF(SUM(BK$10:BK16)-ROUNDDOWN($L17*BK$5/100,0)<-BK$6,-BK$6-SUM(BK$10:BK16),-ROUNDDOWN($L17*BK$5/100,0)),0) -> 0 | BL17: =IF(AND(BL$7="○",$A17>=BL$8,$A17<=BL$9),IF(SUM(BL$10:BL16)-ROUNDDOWN($L17*BL$5/100,0)<-BL$6,-BL$6-SUM(BL$10:BL16),-ROUNDDOWN($L17*BL$5/100,0)),0) -> 0 | BM17: =IF(AND(BM$7="○",$A17>=BM$8,$A17<=BM$9),IF(SUM(BM$10:BM16)-ROUNDDOWN($M17*BM$5/100,0)<-BM$6,-BM$6-SUM(BM$10:BM16),-ROUNDDOWN($M17*BM$5/100,0)),0) -> 0 | BN17: =IF(AND(BN$7="○",$A17>=BN$8,$A17<=BN$9),IF(SUM(BN$10:BN16)-ROUNDDOWN($M17*BN$5/100,0)<-BN$6,-BN$6-SUM(BN$10:BN16),-ROUNDDOWN($M17*BN$5/100,0)),0) -> 0 | BO17: =IF(AND(BO$7="○",$A17>=BO$8,$A17<=BO$9),IF(SUM(BO$10:BO16)-ROUNDDOWN($M17*BO$5/100,0)<-BO$6,-BO$6-SUM(BO$10:BO16),-ROUNDDOWN($M17*BO$5/100,0)),0) -> 0 | BP17: =IF(AND(BP$7="○",$A17>=BP$8,$A17<=BP$9),IF(SUM(BP$10:BP16)-ROUNDDOWN($M17*BP$5/100,0)<-BP$6,-BP$6-SUM(BP$10:BP16),-ROUNDDOWN($M17*BP$5/100,0)),0) -> 0 | BQ17: =IF(AND(BQ$7="○",$A17>=BQ$8,$A17<=BQ$9),IF(SUM(BQ$10:BQ16)-ROUNDDOWN($L17*BQ$5/100,0)<-BQ$6,-BQ$6-SUM(BQ$10:BQ16),-ROUNDDOWN($L17*BQ$5/100,0)),0) -> 0 | BR17: =IF(AND(BR$7="○",$A17>=BR$8,$A17<=BR$9),IF(SUM(BR$10:BR16)-ROUNDDOWN($M17*BR$5/100,0)<-BR$6,-BR$6-SUM(BR$10:BR16),-ROUNDDOWN($M17*BR$5/100,0)),0) -> 0 | BS17: =IF(AND(BS$7="○",$A17>=BS$8,$A17<=BS$9),IF(SUM(BS$10:BS16)-ROUNDDOWN($M17*BS$5/100,0)<-BS$6,-BS$6-SUM(BS$10:BS16),-ROUNDDOWN($M17*BS$5/100,0)),0) -> 0 | BT17: =IF(AND(BT$7="○",$A17>=BT$8,$A17<=BT$9),IF(SUM(BT$10:BT16)-ROUNDDOWN($M17*BT$5/100,0)<-BT$6,-BT$6-SUM(BT$10:BT16),-ROUNDDOWN($M17*BT$5/100,0)),0) -> 0 | BU17: =IF(AND(BU$7="○",$A17>=BU$8,$A17<=BU$9),IF(SUM(BU$10:BU16)-ROUNDDOWN($M17*BU$5/100,0)<-BU$6,-BU$6-SUM(BU$10:BU16),-ROUNDDOWN($M17*BU$5/100,0)),0) -> 0 | BV17: =IF(AND(BV$7="○",$A17>=BV$8,$A17<=BV$9),IF(SUM(BV$10:BV16)-ROUNDDOWN($M17*BV$5/100,0)<-BV$6,-BV$6-SUM(BV$10:BV16),-ROUNDDOWN($M17*BV$5/100,0)),0) -> 0 | BW17: =IF(AND(BW$7="○",$A17>=BW$8,$A17<=BW$9),IF(SUM(BW$10:BW16)-ROUNDDOWN($M17*BW$5/100,0)<-BW$6,-BW$6-SUM(BW$10:BW16),-ROUNDDOWN($M17*BW$5/100,0)),0) -> 0 | BX17: =IF(AND(T17="○",$A17>=BX$8,$A17<=BX$9),IF(SUM(BX$10:BX16)-ROUNDDOWN($K17*BX$5/100,0)<-BX$6,-BX$6-SUM(BX$10:BX16),-ROUNDDOWN($K17*BX$5/100,0)),0) -> 0 | BY17: =IF(AND(U17="○",$A17>=BY$8,$A17<=BY$9),IF(SUM(BY$10:BY16)-ROUNDDOWN($K17*BY$5/100,0)<-BY$6,-BY$6-SUM(BY$10:BY16),-ROUNDDOWN($K17*BY$5/100,0)),0) -> 0 | BZ17: =IF(AND(V17="○",$A17>=BZ$8,$A17<=BZ$9),IF(SUM(BZ$10:BZ16)-ROUNDDOWN($K17*BZ$5/100,0)<-BZ$6,-BZ$6-SUM(BZ$10:BZ16),-ROUNDDOWN($K17*BZ$5/100,0)),0) -> 0 | CA17: =IF(AND(W17="○",$A17>=CA$8,$A17<=CA$9),IF(SUM(CA$10:CA16)-ROUNDDOWN($K17*CA$5/100,0)<-CA$6,-CA$6-SUM(CA$10:CA16),-ROUNDDOWN($K17*CA$5/100,0)),0) -> 0 | CG17: =+SUM(AJ17:CF17,BC17,BE17,AZ17,BA17,BG17,BI17) -> 0 | CH17: =+CG17+N17 -> 0 | CI17: =IFERROR(ROUNDDOWN((CH17/G17),0),0) -> 0 | CO17: =IFERROR(CN17-CI17,0) -> 0 | CP17: =IFERROR(CN17/CI17,0) -> 0 | CR17: =+CO17*G17 -> 0 | CT17: =INDEX([2]マスタ!$A:$A,MATCH(D17,[2]マスタ!$C:$C,0)) -> #N/A | CU17: =IFERROR(TEXT(TODAY(),"yyyymmdd")&"_"&ROUNDDOWN(H17+I17,0)&"-"&ROUNDDOWN(CI17,0),"") -> 20260620_0-0
G18: 1 | H18: =+F18*G18 -> 0 | K18: =+ROUNDDOWN((H18+I18)/100,0)*100 -> 0 | L18: =+ROUNDDOWN((H18+I18)/1.1/100,0)*100 -> 0 | M18: =+ROUNDDOWN((H18+I18)/1.1/200,0)*200 -> 0 | N18: =+H18+I18+J18 -> 0 | O18: =IF(OR(WEEKDAY($A18,2)=2,WEEKDAY($A18,2)=4),"○","✕") -> ✕ | P18: =+IF(MOD(TEXT($A18,"DD"),5)=0,"○","✕") -> ○ | Q18: =+IF((TEXT($A18,"DD")+0)=1,"○","✕") -> ✕ | R18: =+IF((TEXT($A18,"DD")+0)=18,"○","✕") -> ✕ | S18: 0 | T18: ✕ | U18: ✕ | V18: ✕ | W18: ✕ | X18: ○ | Y18: ✕ | Z18: ✕ | AA18: ✕ | AB18: ✕ | AC18: ✕ | AD18: =+IF(ISERROR(VLOOKUP($B18,AD$10:AD17,1,0)),IF(AND($N18>=1000,$A18>=AO$8,$A18<=AO$9),$B18,""),"") | AE18: =+IF(ISERROR(VLOOKUP($B18,AE$10:AE17,1,0)),IF(AND($N18>=1000,$A18>=AP$8,$A18<=AP$9),$B18,""),"") | AF18: =+IF(ISERROR(VLOOKUP($B18,AF$10:AF17,1,0)),IF(AND($N18>=1000,$A18>=AQ$8,$A18<=AQ$9),$B18,""),"") | AG18: =+IF(ISERROR(VLOOKUP($B18,AG$10:AG17,1,0)),IF(AND($N18>=1000,$A18>=AR$8,$A18<=AR$9),$B18,""),"") | AI18: 0 | AJ18: =IF(AND(AJ$7="○",$A18>=AJ$8,$A18<=AJ$9),IF(SUM(AJ$10:AJ17)-ROUNDDOWN($K18*AJ$5/100,0)<-AJ$6,-AJ$6-SUM(AJ$10:AJ17),-ROUNDDOWN($K18*AJ$5/100,0)),0) -> 0 | AK18: =IF(AND(AK$7="○",$A18>=AK$8,$A18<=AK$9),IF(SUM(AK$10:AK17)-ROUNDDOWN($L18*AK$5/100,0)<-AK$6,-AK$6-SUM(AK$10:AK17),-ROUNDDOWN($L18*AK$5/100,0)),0) -> 0 | AL18: =IF(AND(AL$7="○",$A18>=AL$8,$A18<=AL$9),IF(SUM(AL$10:AL17)-ROUNDDOWN($N18*AL$5/100,0)<-AL$6,-AL$6-SUM(AL$10:AL17),-ROUNDDOWN($N18*AL$5/100,0)),0) -> 0 | AM18: =IF(AND(AM$7="○",$A18>=AM$8,$A18<=AM$9),IF(SUM(AM$10:AM17)-ROUNDDOWN($L18*AM$5/100,0)<-AM$6,-AM$6-SUM(AM$10:AM17),-ROUNDDOWN($L18*AM$5/100,0)),0) -> 0 | AN18: =IF(AND(AN$7="○",$A18>=AN$8,$A18<=AN$9),IF(SUM(AN$10:AN17)-ROUNDDOWN($M18*AN$5/100,0)<-AN$6,-AN$6-SUM(AN$10:AN17),-ROUNDDOWN($M18*AN$5/100,0)),0) -> 0 | AO18: =IF(AND($A18>=AO$8,$A18<=AO$9),IF(SUM(AO$10:AO17)-ROUNDDOWN($K18*AO$5/100,0)<-AO$6,-AO$6-SUM(AO$10:AO17),-ROUNDDOWN($K18*AO$5/100,0)),0) -> 0 | AP18: =IF(AND($A18>=AP$8,$A18<=AP$9),IF(SUM(AP$10:AP17)-ROUNDDOWN($K18*AP$5/100,0)<-AP$6,-AP$6-SUM(AP$10:AP17),-ROUNDDOWN($K18*AP$5/100,0)),0) -> 0 | AQ18: =IF(AND($A18>=AQ$8,$A18<=AQ$9),IF(SUM(AQ$10:AQ17)-ROUNDDOWN($K18*AQ$5/100,0)<-AQ$6,-AQ$6-SUM(AQ$10:AQ17),-ROUNDDOWN($K18*AQ$5/100,0)),0) -> 0 | AR18: =IF(AND($A18>=AR$8,$A18<=AR$9),IF(SUM(AR$10:AR17)-ROUNDDOWN($K18*AR$5/100,0)<-AR$6,-AR$6-SUM(AR$10:AR17),-ROUNDDOWN($K18*AR$5/100,0)),0) -> 0 | AS18: =IF(SUMIFS(AS$10:AS17,$A$10:$A17,$A18)-ROUNDDOWN($K18*$S18/100,0)<-$S18*1000,-$S18*1000-SUMIFS(AS$10:AS17,$A$10:$A17,$A18),-ROUNDDOWN($K18*$S18/100,0)) -> 0 | AT18: =IF(AND(X18="○",$A18>=AT$8,$A18<=AT$9,K18>=3980),IF(SUM(AT$10:AT17)-ROUNDDOWN($K18*AT$5/100,0)<-AT$6,-AT$6-SUM(AT$10:AT17),-ROUNDDOWN($K18*AT$5/100,0)),0) -> 0 | AU18: =IF(O18="○",IF(SUM(AU$10:AU17)-ROUNDDOWN($K18*AU$5/100,0)<-AU$6,-AU$6-SUM(AU$10:AU17),-ROUNDDOWN($K18*AU$5/100,0)),0) -> 0 | AV18: =IF(P18="○",IF(SUM(AV$10:AV17)-ROUNDDOWN($K18*AV$5/100,0)<-AV$6,-AV$6-SUM(AV$10:AV17),-ROUNDDOWN($K18*AV$5/100,0)),0) -> 0 | AW18: =IF(Q18="○",IF(SUM(AW$10:AW17)-ROUNDDOWN($K18*AW$5/100,0)<-AW$6,-AW$6-SUM(AW$10:AW17),-ROUNDDOWN($K18*AW$5/100,0)),0) -> 0 | AX18: =IF(R18="○",IF(SUM(AX$10:AX17)-ROUNDDOWN($K18*AX$5/100,0)<-AX$6,-AX$6-SUM(AX$10:AX17),-ROUNDDOWN($K18*AX$5/100,0)),0) -> 0 | AY18: 0 | AZ18: =-ROUNDDOWN($K18*AY18/100,0) -> 0 | BA18: =-ROUNDDOWN($K18*AI18/100,0) -> 0 | BC18: =-ROUNDDOWN($K18*BB18/100,0) -> 0 | BD18: 0 | BE18: =-ROUNDDOWN($K18*BD18/100,0) -> 0 | BF18: 0 | BG18: =-ROUNDDOWN($K18*BF18/100,0) -> 0 | BH18: 0 | BI18: =-ROUNDDOWN($K18*BH18/100,0) -> 0 | BJ18: =IF(AND(BJ$7="○",$A18>=BJ$8,$A18<=BJ$9),IF(SUM(BJ$10:BJ17)-ROUNDDOWN($M18*BJ$5/100,0)<-BJ$6,-BJ$6-SUM(BJ$10:BJ17),-ROUNDDOWN($M18*BJ$5/100,0)),0) -> 0 | BK18: =IF(AND(BK$7="○",$A18>=BK$8,$A18<=BK$9),IF(SUM(BK$10:BK17)-ROUNDDOWN($L18*BK$5/100,0)<-BK$6,-BK$6-SUM(BK$10:BK17),-ROUNDDOWN($L18*BK$5/100,0)),0) -> 0 | BL18: =IF(AND(BL$7="○",$A18>=BL$8,$A18<=BL$9),IF(SUM(BL$10:BL17)-ROUNDDOWN($L18*BL$5/100,0)<-BL$6,-BL$6-SUM(BL$10:BL17),-ROUNDDOWN($L18*BL$5/100,0)),0) -> 0 | BM18: =IF(AND(BM$7="○",$A18>=BM$8,$A18<=BM$9),IF(SUM(BM$10:BM17)-ROUNDDOWN($M18*BM$5/100,0)<-BM$6,-BM$6-SUM(BM$10:BM17),-ROUNDDOWN($M18*BM$5/100,0)),0) -> 0 | BN18: =IF(AND(BN$7="○",$A18>=BN$8,$A18<=BN$9),IF(SUM(BN$10:BN17)-ROUNDDOWN($M18*BN$5/100,0)<-BN$6,-BN$6-SUM(BN$10:BN17),-ROUNDDOWN($M18*BN$5/100,0)),0) -> 0 | BO18: =IF(AND(BO$7="○",$A18>=BO$8,$A18<=BO$9),IF(SUM(BO$10:BO17)-ROUNDDOWN($M18*BO$5/100,0)<-BO$6,-BO$6-SUM(BO$10:BO17),-ROUNDDOWN($M18*BO$5/100,0)),0) -> 0 | BP18: =IF(AND(BP$7="○",$A18>=BP$8,$A18<=BP$9),IF(SUM(BP$10:BP17)-ROUNDDOWN($M18*BP$5/100,0)<-BP$6,-BP$6-SUM(BP$10:BP17),-ROUNDDOWN($M18*BP$5/100,0)),0) -> 0 | BQ18: =IF(AND(BQ$7="○",$A18>=BQ$8,$A18<=BQ$9),IF(SUM(BQ$10:BQ17)-ROUNDDOWN($L18*BQ$5/100,0)<-BQ$6,-BQ$6-SUM(BQ$10:BQ17),-ROUNDDOWN($L18*BQ$5/100,0)),0) -> 0 | BR18: =IF(AND(BR$7="○",$A18>=BR$8,$A18<=BR$9),IF(SUM(BR$10:BR17)-ROUNDDOWN($M18*BR$5/100,0)<-BR$6,-BR$6-SUM(BR$10:BR17),-ROUNDDOWN($M18*BR$5/100,0)),0) -> 0 | BS18: =IF(AND(BS$7="○",$A18>=BS$8,$A18<=BS$9),IF(SUM(BS$10:BS17)-ROUNDDOWN($M18*BS$5/100,0)<-BS$6,-BS$6-SUM(BS$10:BS17),-ROUNDDOWN($M18*BS$5/100,0)),0) -> 0 | BT18: =IF(AND(BT$7="○",$A18>=BT$8,$A18<=BT$9),IF(SUM(BT$10:BT17)-ROUNDDOWN($M18*BT$5/100,0)<-BT$6,-BT$6-SUM(BT$10:BT17),-ROUNDDOWN($M18*BT$5/100,0)),0) -> 0 | BU18: =IF(AND(BU$7="○",$A18>=BU$8,$A18<=BU$9),IF(SUM(BU$10:BU17)-ROUNDDOWN($M18*BU$5/100,0)<-BU$6,-BU$6-SUM(BU$10:BU17),-ROUNDDOWN($M18*BU$5/100,0)),0) -> 0 | BV18: =IF(AND(BV$7="○",$A18>=BV$8,$A18<=BV$9),IF(SUM(BV$10:BV17)-ROUNDDOWN($M18*BV$5/100,0)<-BV$6,-BV$6-SUM(BV$10:BV17),-ROUNDDOWN($M18*BV$5/100,0)),0) -> 0 | BW18: =IF(AND(BW$7="○",$A18>=BW$8,$A18<=BW$9),IF(SUM(BW$10:BW17)-ROUNDDOWN($M18*BW$5/100,0)<-BW$6,-BW$6-SUM(BW$10:BW17),-ROUNDDOWN($M18*BW$5/100,0)),0) -> 0 | BX18: =IF(AND(T18="○",$A18>=BX$8,$A18<=BX$9),IF(SUM(BX$10:BX17)-ROUNDDOWN($K18*BX$5/100,0)<-BX$6,-BX$6-SUM(BX$10:BX17),-ROUNDDOWN($K18*BX$5/100,0)),0) -> 0 | BY18: =IF(AND(U18="○",$A18>=BY$8,$A18<=BY$9),IF(SUM(BY$10:BY17)-ROUNDDOWN($K18*BY$5/100,0)<-BY$6,-BY$6-SUM(BY$10:BY17),-ROUNDDOWN($K18*BY$5/100,0)),0) -> 0 | BZ18: =IF(AND(V18="○",$A18>=BZ$8,$A18<=BZ$9),IF(SUM(BZ$10:BZ17)-ROUNDDOWN($K18*BZ$5/100,0)<-BZ$6,-BZ$6-SUM(BZ$10:BZ17),-ROUNDDOWN($K18*BZ$5/100,0)),0) -> 0 | CA18: =IF(AND(W18="○",$A18>=CA$8,$A18<=CA$9),IF(SUM(CA$10:CA17)-ROUNDDOWN($K18*CA$5/100,0)<-CA$6,-CA$6-SUM(CA$10:CA17),-ROUNDDOWN($K18*CA$5/100,0)),0) -> 0 | CG18: =+SUM(AJ18:CF18,BC18,BE18,AZ18,BA18,BG18,BI18) -> 0 | CH18: =+CG18+N18 -> 0 | CI18: =IFERROR(ROUNDDOWN((CH18/G18),0),0) -> 0 | CO18: =IFERROR(CN18-CI18,0) -> 0 | CP18: =IFERROR(CN18/CI18,0) -> 0 | CR18: =+CO18*G18 -> 0 | CT18: =INDEX([2]マスタ!$A:$A,MATCH(D18,[2]マスタ!$C:$C,0)) -> #N/A | CU18: =IFERROR(TEXT(TODAY(),"yyyymmdd")&"_"&ROUNDDOWN(H18+I18,0)&"-"&ROUNDDOWN(CI18,0),"") -> 20260620_0-0
G19: 1 | H19: =+F19*G19 -> 0 | K19: =+ROUNDDOWN((H19+I19)/100,0)*100 -> 0 | L19: =+ROUNDDOWN((H19+I19)/1.1/100,0)*100 -> 0 | M19: =+ROUNDDOWN((H19+I19)/1.1/200,0)*200 -> 0 | N19: =+H19+I19+J19 -> 0 | O19: =IF(OR(WEEKDAY($A19,2)=2,WEEKDAY($A19,2)=4),"○","✕") -> ✕ | P19: =+IF(MOD(TEXT($A19,"DD"),5)=0,"○","✕") -> ○ | Q19: =+IF((TEXT($A19,"DD")+0)=1,"○","✕") -> ✕ | R19: =+IF((TEXT($A19,"DD")+0)=18,"○","✕") -> ✕ | S19: 0 | T19: ✕ | U19: ✕ | V19: ✕ | W19: ✕ | X19: ○ | Y19: ✕ | Z19: ✕ | AA19: ✕ | AB19: ✕ | AC19: ✕ | AD19: =+IF(ISERROR(VLOOKUP($B19,AD$10:AD18,1,0)),IF(AND($N19>=1000,$A19>=AO$8,$A19<=AO$9),$B19,""),"") | AE19: =+IF(ISERROR(VLOOKUP($B19,AE$10:AE18,1,0)),IF(AND($N19>=1000,$A19>=AP$8,$A19<=AP$9),$B19,""),"") | AF19: =+IF(ISERROR(VLOOKUP($B19,AF$10:AF18,1,0)),IF(AND($N19>=1000,$A19>=AQ$8,$A19<=AQ$9),$B19,""),"") | AG19: =+IF(ISERROR(VLOOKUP($B19,AG$10:AG18,1,0)),IF(AND($N19>=1000,$A19>=AR$8,$A19<=AR$9),$B19,""),"") | AI19: 0 | AJ19: =IF(AND(AJ$7="○",$A19>=AJ$8,$A19<=AJ$9),IF(SUM(AJ$10:AJ18)-ROUNDDOWN($K19*AJ$5/100,0)<-AJ$6,-AJ$6-SUM(AJ$10:AJ18),-ROUNDDOWN($K19*AJ$5/100,0)),0) -> 0 | AK19: =IF(AND(AK$7="○",$A19>=AK$8,$A19<=AK$9),IF(SUM(AK$10:AK18)-ROUNDDOWN($L19*AK$5/100,0)<-AK$6,-AK$6-SUM(AK$10:AK18),-ROUNDDOWN($L19*AK$5/100,0)),0) -> 0 | AL19: =IF(AND(AL$7="○",$A19>=AL$8,$A19<=AL$9),IF(SUM(AL$10:AL18)-ROUNDDOWN($N19*AL$5/100,0)<-AL$6,-AL$6-SUM(AL$10:AL18),-ROUNDDOWN($N19*AL$5/100,0)),0) -> 0 | AM19: =IF(AND(AM$7="○",$A19>=AM$8,$A19<=AM$9),IF(SUM(AM$10:AM18)-ROUNDDOWN($L19*AM$5/100,0)<-AM$6,-AM$6-SUM(AM$10:AM18),-ROUNDDOWN($L19*AM$5/100,0)),0) -> 0 | AN19: =IF(AND(AN$7="○",$A19>=AN$8,$A19<=AN$9),IF(SUM(AN$10:AN18)-ROUNDDOWN($M19*AN$5/100,0)<-AN$6,-AN$6-SUM(AN$10:AN18),-ROUNDDOWN($M19*AN$5/100,0)),0) -> 0 | AO19: =IF(AND($A19>=AO$8,$A19<=AO$9),IF(SUM(AO$10:AO18)-ROUNDDOWN($K19*AO$5/100,0)<-AO$6,-AO$6-SUM(AO$10:AO18),-ROUNDDOWN($K19*AO$5/100,0)),0) -> 0 | AP19: =IF(AND($A19>=AP$8,$A19<=AP$9),IF(SUM(AP$10:AP18)-ROUNDDOWN($K19*AP$5/100,0)<-AP$6,-AP$6-SUM(AP$10:AP18),-ROUNDDOWN($K19*AP$5/100,0)),0) -> 0 | AQ19: =IF(AND($A19>=AQ$8,$A19<=AQ$9),IF(SUM(AQ$10:AQ18)-ROUNDDOWN($K19*AQ$5/100,0)<-AQ$6,-AQ$6-SUM(AQ$10:AQ18),-ROUNDDOWN($K19*AQ$5/100,0)),0) -> 0 | AR19: =IF(AND($A19>=AR$8,$A19<=AR$9),IF(SUM(AR$10:AR18)-ROUNDDOWN($K19*AR$5/100,0)<-AR$6,-AR$6-SUM(AR$10:AR18),-ROUNDDOWN($K19*AR$5/100,0)),0) -> 0 | AS19: =IF(SUMIFS(AS$10:AS18,$A$10:$A18,$A19)-ROUNDDOWN($K19*$S19/100,0)<-$S19*1000,-$S19*1000-SUMIFS(AS$10:AS18,$A$10:$A18,$A19),-ROUNDDOWN($K19*$S19/100,0)) -> 0 | AT19: =IF(AND(X19="○",$A19>=AT$8,$A19<=AT$9,K19>=3980),IF(SUM(AT$10:AT18)-ROUNDDOWN($K19*AT$5/100,0)<-AT$6,-AT$6-SUM(AT$10:AT18),-ROUNDDOWN($K19*AT$5/100,0)),0) -> 0 | AU19: =IF(O19="○",IF(SUM(AU$10:AU18)-ROUNDDOWN($K19*AU$5/100,0)<-AU$6,-AU$6-SUM(AU$10:AU18),-ROUNDDOWN($K19*AU$5/100,0)),0) -> 0 | AV19: =IF(P19="○",IF(SUM(AV$10:AV18)-ROUNDDOWN($K19*AV$5/100,0)<-AV$6,-AV$6-SUM(AV$10:AV18),-ROUNDDOWN($K19*AV$5/100,0)),0) -> 0 | AW19: =IF(Q19="○",IF(SUM(AW$10:AW18)-ROUNDDOWN($K19*AW$5/100,0)<-AW$6,-AW$6-SUM(AW$10:AW18),-ROUNDDOWN($K19*AW$5/100,0)),0) -> 0 | AX19: =IF(R19="○",IF(SUM(AX$10:AX18)-ROUNDDOWN($K19*AX$5/100,0)<-AX$6,-AX$6-SUM(AX$10:AX18),-ROUNDDOWN($K19*AX$5/100,0)),0) -> 0 | AY19: 0 | AZ19: =-ROUNDDOWN($K19*AY19/100,0) -> 0 | BA19: =-ROUNDDOWN($K19*AI19/100,0) -> 0 | BC19: =-ROUNDDOWN($K19*BB19/100,0) -> 0 | BD19: 0 | BE19: =-ROUNDDOWN($K19*BD19/100,0) -> 0 | BF19: 0 | BG19: =-ROUNDDOWN($K19*BF19/100,0) -> 0 | BH19: 0 | BI19: =-ROUNDDOWN($K19*BH19/100,0) -> 0 | BJ19: =IF(AND(BJ$7="○",$A19>=BJ$8,$A19<=BJ$9),IF(SUM(BJ$10:BJ18)-ROUNDDOWN($M19*BJ$5/100,0)<-BJ$6,-BJ$6-SUM(BJ$10:BJ18),-ROUNDDOWN($M19*BJ$5/100,0)),0) -> 0 | BK19: =IF(AND(BK$7="○",$A19>=BK$8,$A19<=BK$9),IF(SUM(BK$10:BK18)-ROUNDDOWN($L19*BK$5/100,0)<-BK$6,-BK$6-SUM(BK$10:BK18),-ROUNDDOWN($L19*BK$5/100,0)),0) -> 0 | BL19: =IF(AND(BL$7="○",$A19>=BL$8,$A19<=BL$9),IF(SUM(BL$10:BL18)-ROUNDDOWN($L19*BL$5/100,0)<-BL$6,-BL$6-SUM(BL$10:BL18),-ROUNDDOWN($L19*BL$5/100,0)),0) -> 0 | BM19: =IF(AND(BM$7="○",$A19>=BM$8,$A19<=BM$9),IF(SUM(BM$10:BM18)-ROUNDDOWN($M19*BM$5/100,0)<-BM$6,-BM$6-SUM(BM$10:BM18),-ROUNDDOWN($M19*BM$5/100,0)),0) -> 0 | BN19: =IF(AND(BN$7="○",$A19>=BN$8,$A19<=BN$9),IF(SUM(BN$10:BN18)-ROUNDDOWN($M19*BN$5/100,0)<-BN$6,-BN$6-SUM(BN$10:BN18),-ROUNDDOWN($M19*BN$5/100,0)),0) -> 0 | BO19: =IF(AND(BO$7="○",$A19>=BO$8,$A19<=BO$9),IF(SUM(BO$10:BO18)-ROUNDDOWN($M19*BO$5/100,0)<-BO$6,-BO$6-SUM(BO$10:BO18),-ROUNDDOWN($M19*BO$5/100,0)),0) -> 0 | BP19: =IF(AND(BP$7="○",$A19>=BP$8,$A19<=BP$9),IF(SUM(BP$10:BP18)-ROUNDDOWN($M19*BP$5/100,0)<-BP$6,-BP$6-SUM(BP$10:BP18),-ROUNDDOWN($M19*BP$5/100,0)),0) -> 0 | BQ19: =IF(AND(BQ$7="○",$A19>=BQ$8,$A19<=BQ$9),IF(SUM(BQ$10:BQ18)-ROUNDDOWN($L19*BQ$5/100,0)<-BQ$6,-BQ$6-SUM(BQ$10:BQ18),-ROUNDDOWN($L19*BQ$5/100,0)),0) -> 0 | BR19: =IF(AND(BR$7="○",$A19>=BR$8,$A19<=BR$9),IF(SUM(BR$10:BR18)-ROUNDDOWN($M19*BR$5/100,0)<-BR$6,-BR$6-SUM(BR$10:BR18),-ROUNDDOWN($M19*BR$5/100,0)),0) -> 0 | BS19: =IF(AND(BS$7="○",$A19>=BS$8,$A19<=BS$9),IF(SUM(BS$10:BS18)-ROUNDDOWN($M19*BS$5/100,0)<-BS$6,-BS$6-SUM(BS$10:BS18),-ROUNDDOWN($M19*BS$5/100,0)),0) -> 0 | BT19: =IF(AND(BT$7="○",$A19>=BT$8,$A19<=BT$9),IF(SUM(BT$10:BT18)-ROUNDDOWN($M19*BT$5/100,0)<-BT$6,-BT$6-SUM(BT$10:BT18),-ROUNDDOWN($M19*BT$5/100,0)),0) -> 0 | BU19: =IF(AND(BU$7="○",$A19>=BU$8,$A19<=BU$9),IF(SUM(BU$10:BU18)-ROUNDDOWN($M19*BU$5/100,0)<-BU$6,-BU$6-SUM(BU$10:BU18),-ROUNDDOWN($M19*BU$5/100,0)),0) -> 0 | BV19: =IF(AND(BV$7="○",$A19>=BV$8,$A19<=BV$9),IF(SUM(BV$10:BV18)-ROUNDDOWN($M19*BV$5/100,0)<-BV$6,-BV$6-SUM(BV$10:BV18),-ROUNDDOWN($M19*BV$5/100,0)),0) -> 0 | BW19: =IF(AND(BW$7="○",$A19>=BW$8,$A19<=BW$9),IF(SUM(BW$10:BW18)-ROUNDDOWN($M19*BW$5/100,0)<-BW$6,-BW$6-SUM(BW$10:BW18),-ROUNDDOWN($M19*BW$5/100,0)),0) -> 0 | BX19: =IF(AND(T19="○",$A19>=BX$8,$A19<=BX$9),IF(SUM(BX$10:BX18)-ROUNDDOWN($K19*BX$5/100,0)<-BX$6,-BX$6-SUM(BX$10:BX18),-ROUNDDOWN($K19*BX$5/100,0)),0) -> 0 | BY19: =IF(AND(U19="○",$A19>=BY$8,$A19<=BY$9),IF(SUM(BY$10:BY18)-ROUNDDOWN($K19*BY$5/100,0)<-BY$6,-BY$6-SUM(BY$10:BY18),-ROUNDDOWN($K19*BY$5/100,0)),0) -> 0 | BZ19: =IF(AND(V19="○",$A19>=BZ$8,$A19<=BZ$9),IF(SUM(BZ$10:BZ18)-ROUNDDOWN($K19*BZ$5/100,0)<-BZ$6,-BZ$6-SUM(BZ$10:BZ18),-ROUNDDOWN($K19*BZ$5/100,0)),0) -> 0 | CA19: =IF(AND(W19="○",$A19>=CA$8,$A19<=CA$9),IF(SUM(CA$10:CA18)-ROUNDDOWN($K19*CA$5/100,0)<-CA$6,-CA$6-SUM(CA$10:CA18),-ROUNDDOWN($K19*CA$5/100,0)),0) -> 0 | CG19: =+SUM(AJ19:CF19,BC19,BE19,AZ19,BA19,BG19,BI19) -> 0 | CH19: =+CG19+N19 -> 0 | CI19: =IFERROR(ROUNDDOWN((CH19/G19),0),0) -> 0 | CO19: =IFERROR(CN19-CI19,0) -> 0 | CP19: =IFERROR(CN19/CI19,0) -> 0 | CR19: =+CO19*G19 -> 0 | CT19: =INDEX([2]マスタ!$A:$A,MATCH(D19,[2]マスタ!$C:$C,0)) -> #N/A | CU19: =IFERROR(TEXT(TODAY(),"yyyymmdd")&"_"&ROUNDDOWN(H19+I19,0)&"-"&ROUNDDOWN(CI19,0),"") -> 20260620_0-0
G20: 1 | H20: =+F20*G20 -> 0 | K20: =+ROUNDDOWN((H20+I20)/100,0)*100 -> 0 | L20: =+ROUNDDOWN((H20+I20)/1.1/100,0)*100 -> 0 | M20: =+ROUNDDOWN((H20+I20)/1.1/200,0)*200 -> 0 | N20: =+H20+I20+J20 -> 0 | O20: =IF(OR(WEEKDAY($A20,2)=2,WEEKDAY($A20,2)=4),"○","✕") -> ✕ | P20: =+IF(MOD(TEXT($A20,"DD"),5)=0,"○","✕") -> ○ | Q20: =+IF((TEXT($A20,"DD")+0)=1,"○","✕") -> ✕ | R20: =+IF((TEXT($A20,"DD")+0)=18,"○","✕") -> ✕ | S20: 0 | T20: ✕ | U20: ✕ | V20: ✕ | W20: ✕ | X20: ○ | Y20: ✕ | Z20: ✕ | AA20: ✕ | AB20: ✕ | AC20: ✕ | AD20: =+IF(ISERROR(VLOOKUP($B20,AD$10:AD19,1,0)),IF(AND($N20>=1000,$A20>=AO$8,$A20<=AO$9),$B20,""),"") | AE20: =+IF(ISERROR(VLOOKUP($B20,AE$10:AE19,1,0)),IF(AND($N20>=1000,$A20>=AP$8,$A20<=AP$9),$B20,""),"") | AF20: =+IF(ISERROR(VLOOKUP($B20,AF$10:AF19,1,0)),IF(AND($N20>=1000,$A20>=AQ$8,$A20<=AQ$9),$B20,""),"") | AG20: =+IF(ISERROR(VLOOKUP($B20,AG$10:AG19,1,0)),IF(AND($N20>=1000,$A20>=AR$8,$A20<=AR$9),$B20,""),"") | AI20: 0 | AJ20: =IF(AND(AJ$7="○",$A20>=AJ$8,$A20<=AJ$9),IF(SUM(AJ$10:AJ19)-ROUNDDOWN($K20*AJ$5/100,0)<-AJ$6,-AJ$6-SUM(AJ$10:AJ19),-ROUNDDOWN($K20*AJ$5/100,0)),0) -> 0 | AK20: =IF(AND(AK$7="○",$A20>=AK$8,$A20<=AK$9),IF(SUM(AK$10:AK19)-ROUNDDOWN($L20*AK$5/100,0)<-AK$6,-AK$6-SUM(AK$10:AK19),-ROUNDDOWN($L20*AK$5/100,0)),0) -> 0 | AL20: =IF(AND(AL$7="○",$A20>=AL$8,$A20<=AL$9),IF(SUM(AL$10:AL19)-ROUNDDOWN($N20*AL$5/100,0)<-AL$6,-AL$6-SUM(AL$10:AL19),-ROUNDDOWN($N20*AL$5/100,0)),0) -> 0 | AM20: =IF(AND(AM$7="○",$A20>=AM$8,$A20<=AM$9),IF(SUM(AM$10:AM19)-ROUNDDOWN($L20*AM$5/100,0)<-AM$6,-AM$6-SUM(AM$10:AM19),-ROUNDDOWN($L20*AM$5/100,0)),0) -> 0 | AN20: =IF(AND(AN$7="○",$A20>=AN$8,$A20<=AN$9),IF(SUM(AN$10:AN19)-ROUNDDOWN($M20*AN$5/100,0)<-AN$6,-AN$6-SUM(AN$10:AN19),-ROUNDDOWN($M20*AN$5/100,0)),0) -> 0 | AO20: =IF(AND($A20>=AO$8,$A20<=AO$9),IF(SUM(AO$10:AO19)-ROUNDDOWN($K20*AO$5/100,0)<-AO$6,-AO$6-SUM(AO$10:AO19),-ROUNDDOWN($K20*AO$5/100,0)),0) -> 0 | AP20: =IF(AND($A20>=AP$8,$A20<=AP$9),IF(SUM(AP$10:AP19)-ROUNDDOWN($K20*AP$5/100,0)<-AP$6,-AP$6-SUM(AP$10:AP19),-ROUNDDOWN($K20*AP$5/100,0)),0) -> 0 | AQ20: =IF(AND($A20>=AQ$8,$A20<=AQ$9),IF(SUM(AQ$10:AQ19)-ROUNDDOWN($K20*AQ$5/100,0)<-AQ$6,-AQ$6-SUM(AQ$10:AQ19),-ROUNDDOWN($K20*AQ$5/100,0)),0) -> 0 | AR20: =IF(AND($A20>=AR$8,$A20<=AR$9),IF(SUM(AR$10:AR19)-ROUNDDOWN($K20*AR$5/100,0)<-AR$6,-AR$6-SUM(AR$10:AR19),-ROUNDDOWN($K20*AR$5/100,0)),0) -> 0 | AS20: =IF(SUMIFS(AS$10:AS19,$A$10:$A19,$A20)-ROUNDDOWN($K20*$S20/100,0)<-$S20*1000,-$S20*1000-SUMIFS(AS$10:AS19,$A$10:$A19,$A20),-ROUNDDOWN($K20*$S20/100,0)) -> 0 | AT20: =IF(AND(X20="○",$A20>=AT$8,$A20<=AT$9,K20>=3980),IF(SUM(AT$10:AT19)-ROUNDDOWN($K20*AT$5/100,0)<-AT$6,-AT$6-SUM(AT$10:AT19),-ROUNDDOWN($K20*AT$5/100,0)),0) -> 0 | AU20: =IF(O20="○",IF(SUM(AU$10:AU19)-ROUNDDOWN($K20*AU$5/100,0)<-AU$6,-AU$6-SUM(AU$10:AU19),-ROUNDDOWN($K20*AU$5/100,0)),0) -> 0 | AV20: =IF(P20="○",IF(SUM(AV$10:AV19)-ROUNDDOWN($K20*AV$5/100,0)<-AV$6,-AV$6-SUM(AV$10:AV19),-ROUNDDOWN($K20*AV$5/100,0)),0) -> 0 | AW20: =IF(Q20="○",IF(SUM(AW$10:AW19)-ROUNDDOWN($K20*AW$5/100,0)<-AW$6,-AW$6-SUM(AW$10:AW19),-ROUNDDOWN($K20*AW$5/100,0)),0) -> 0 | AX20: =IF(R20="○",IF(SUM(AX$10:AX19)-ROUNDDOWN($K20*AX$5/100,0)<-AX$6,-AX$6-SUM(AX$10:AX19),-ROUNDDOWN($K20*AX$5/100,0)),0) -> 0 | AY20: 0 | AZ20: =-ROUNDDOWN($K20*AY20/100,0) -> 0 | BA20: =-ROUNDDOWN($K20*AI20/100,0) -> 0 | BC20: =-ROUNDDOWN($K20*BB20/100,0) -> 0 | BD20: 0 | BE20: =-ROUNDDOWN($K20*BD20/100,0) -> 0 | BF20: 0 | BG20: =-ROUNDDOWN($K20*BF20/100,0) -> 0 | BH20: 0 | BI20: =-ROUNDDOWN($K20*BH20/100,0) -> 0 | BJ20: =IF(AND(BJ$7="○",$A20>=BJ$8,$A20<=BJ$9),IF(SUM(BJ$10:BJ19)-ROUNDDOWN($M20*BJ$5/100,0)<-BJ$6,-BJ$6-SUM(BJ$10:BJ19),-ROUNDDOWN($M20*BJ$5/100,0)),0) -> 0 | BK20: =IF(AND(BK$7="○",$A20>=BK$8,$A20<=BK$9),IF(SUM(BK$10:BK19)-ROUNDDOWN($L20*BK$5/100,0)<-BK$6,-BK$6-SUM(BK$10:BK19),-ROUNDDOWN($L20*BK$5/100,0)),0) -> 0 | BL20: =IF(AND(BL$7="○",$A20>=BL$8,$A20<=BL$9),IF(SUM(BL$10:BL19)-ROUNDDOWN($L20*BL$5/100,0)<-BL$6,-BL$6-SUM(BL$10:BL19),-ROUNDDOWN($L20*BL$5/100,0)),0) -> 0 | BM20: =IF(AND(BM$7="○",$A20>=BM$8,$A20<=BM$9),IF(SUM(BM$10:BM19)-ROUNDDOWN($M20*BM$5/100,0)<-BM$6,-BM$6-SUM(BM$10:BM19),-ROUNDDOWN($M20*BM$5/100,0)),0) -> 0 | BN20: =IF(AND(BN$7="○",$A20>=BN$8,$A20<=BN$9),IF(SUM(BN$10:BN19)-ROUNDDOWN($M20*BN$5/100,0)<-BN$6,-BN$6-SUM(BN$10:BN19),-ROUNDDOWN($M20*BN$5/100,0)),0) -> 0 | BO20: =IF(AND(BO$7="○",$A20>=BO$8,$A20<=BO$9),IF(SUM(BO$10:BO19)-ROUNDDOWN($M20*BO$5/100,0)<-BO$6,-BO$6-SUM(BO$10:BO19),-ROUNDDOWN($M20*BO$5/100,0)),0) -> 0 | BP20: =IF(AND(BP$7="○",$A20>=BP$8,$A20<=BP$9),IF(SUM(BP$10:BP19)-ROUNDDOWN($M20*BP$5/100,0)<-BP$6,-BP$6-SUM(BP$10:BP19),-ROUNDDOWN($M20*BP$5/100,0)),0) -> 0 | BQ20: =IF(AND(BQ$7="○",$A20>=BQ$8,$A20<=BQ$9),IF(SUM(BQ$10:BQ19)-ROUNDDOWN($L20*BQ$5/100,0)<-BQ$6,-BQ$6-SUM(BQ$10:BQ19),-ROUNDDOWN($L20*BQ$5/100,0)),0) -> 0 | BR20: =IF(AND(BR$7="○",$A20>=BR$8,$A20<=BR$9),IF(SUM(BR$10:BR19)-ROUNDDOWN($M20*BR$5/100,0)<-BR$6,-BR$6-SUM(BR$10:BR19),-ROUNDDOWN($M20*BR$5/100,0)),0) -> 0 | BS20: =IF(AND(BS$7="○",$A20>=BS$8,$A20<=BS$9),IF(SUM(BS$10:BS19)-ROUNDDOWN($M20*BS$5/100,0)<-BS$6,-BS$6-SUM(BS$10:BS19),-ROUNDDOWN($M20*BS$5/100,0)),0) -> 0 | BT20: =IF(AND(BT$7="○",$A20>=BT$8,$A20<=BT$9),IF(SUM(BT$10:BT19)-ROUNDDOWN($M20*BT$5/100,0)<-BT$6,-BT$6-SUM(BT$10:BT19),-ROUNDDOWN($M20*BT$5/100,0)),0) -> 0 | BU20: =IF(AND(BU$7="○",$A20>=BU$8,$A20<=BU$9),IF(SUM(BU$10:BU19)-ROUNDDOWN($M20*BU$5/100,0)<-BU$6,-BU$6-SUM(BU$10:BU19),-ROUNDDOWN($M20*BU$5/100,0)),0) -> 0 | BV20: =IF(AND(BV$7="○",$A20>=BV$8,$A20<=BV$9),IF(SUM(BV$10:BV19)-ROUNDDOWN($M20*BV$5/100,0)<-BV$6,-BV$6-SUM(BV$10:BV19),-ROUNDDOWN($M20*BV$5/100,0)),0) -> 0 | BW20: =IF(AND(BW$7="○",$A20>=BW$8,$A20<=BW$9),IF(SUM(BW$10:BW19)-ROUNDDOWN($M20*BW$5/100,0)<-BW$6,-BW$6-SUM(BW$10:BW19),-ROUNDDOWN($M20*BW$5/100,0)),0) -> 0 | BX20: =IF(AND(T20="○",$A20>=BX$8,$A20<=BX$9),IF(SUM(BX$10:BX19)-ROUNDDOWN($K20*BX$5/100,0)<-BX$6,-BX$6-SUM(BX$10:BX19),-ROUNDDOWN($K20*BX$5/100,0)),0) -> 0 | BY20: =IF(AND(U20="○",$A20>=BY$8,$A20<=BY$9),IF(SUM(BY$10:BY19)-ROUNDDOWN($K20*BY$5/100,0)<-BY$6,-BY$6-SUM(BY$10:BY19),-ROUNDDOWN($K20*BY$5/100,0)),0) -> 0 | BZ20: =IF(AND(V20="○",$A20>=BZ$8,$A20<=BZ$9),IF(SUM(BZ$10:BZ19)-ROUNDDOWN($K20*BZ$5/100,0)<-BZ$6,-BZ$6-SUM(BZ$10:BZ19),-ROUNDDOWN($K20*BZ$5/100,0)),0) -> 0 | CA20: =IF(AND(W20="○",$A20>=CA$8,$A20<=CA$9),IF(SUM(CA$10:CA19)-ROUNDDOWN($K20*CA$5/100,0)<-CA$6,-CA$6-SUM(CA$10:CA19),-ROUNDDOWN($K20*CA$5/100,0)),0) -> 0 | CG20: =+SUM(AJ20:CF20,BC20,BE20,AZ20,BA20,BG20,BI20) -> 0 | CH20: =+CG20+N20 -> 0 | CI20: =IFERROR(ROUNDDOWN((CH20/G20),0),0) -> 0 | CO20: =IFERROR(CN20-CI20,0) -> 0 | CP20: =IFERROR(CN20/CI20,0) -> 0 | CR20: =+CO20*G20 -> 0 | CT20: =INDEX([2]マスタ!$A:$A,MATCH(D20,[2]マスタ!$C:$C,0)) -> #N/A | CU20: =IFERROR(TEXT(TODAY(),"yyyymmdd")&"_"&ROUNDDOWN(H20+I20,0)&"-"&ROUNDDOWN(CI20,0),"") -> 20260620_0-0
G21: 1 | H21: =+F21*G21 -> 0 | K21: =+ROUNDDOWN((H21+I21)/100,0)*100 -> 0 | L21: =+ROUNDDOWN((H21+I21)/1.1/100,0)*100 -> 0 | M21: =+ROUNDDOWN((H21+I21)/1.1/200,0)*200 -> 0 | N21: =+H21+I21+J21 -> 0 | O21: =IF(OR(WEEKDAY($A21,2)=2,WEEKDAY($A21,2)=4),"○","✕") -> ✕ | P21: =+IF(MOD(TEXT($A21,"DD"),5)=0,"○","✕") -> ○ | Q21: =+IF((TEXT($A21,"DD")+0)=1,"○","✕") -> ✕ | R21: =+IF((TEXT($A21,"DD")+0)=18,"○","✕") -> ✕ | S21: 0 | T21: ✕ | U21: ✕ | V21: ✕ | W21: ✕ | X21: ○ | Y21: ✕ | Z21: ✕ | AA21: ✕ | AB21: ✕ | AC21: ✕ | AD21: =+IF(ISERROR(VLOOKUP($B21,AD$10:AD20,1,0)),IF(AND($N21>=1000,$A21>=AO$8,$A21<=AO$9),$B21,""),"") | AE21: =+IF(ISERROR(VLOOKUP($B21,AE$10:AE20,1,0)),IF(AND($N21>=1000,$A21>=AP$8,$A21<=AP$9),$B21,""),"") | AF21: =+IF(ISERROR(VLOOKUP($B21,AF$10:AF20,1,0)),IF(AND($N21>=1000,$A21>=AQ$8,$A21<=AQ$9),$B21,""),"") | AG21: =+IF(ISERROR(VLOOKUP($B21,AG$10:AG20,1,0)),IF(AND($N21>=1000,$A21>=AR$8,$A21<=AR$9),$B21,""),"") | AI21: 0 | AJ21: =IF(AND(AJ$7="○",$A21>=AJ$8,$A21<=AJ$9),IF(SUM(AJ$10:AJ20)-ROUNDDOWN($K21*AJ$5/100,0)<-AJ$6,-AJ$6-SUM(AJ$10:AJ20),-ROUNDDOWN($K21*AJ$5/100,0)),0) -> 0 | AK21: =IF(AND(AK$7="○",$A21>=AK$8,$A21<=AK$9),IF(SUM(AK$10:AK20)-ROUNDDOWN($L21*AK$5/100,0)<-AK$6,-AK$6-SUM(AK$10:AK20),-ROUNDDOWN($L21*AK$5/100,0)),0) -> 0 | AL21: =IF(AND(AL$7="○",$A21>=AL$8,$A21<=AL$9),IF(SUM(AL$10:AL20)-ROUNDDOWN($N21*AL$5/100,0)<-AL$6,-AL$6-SUM(AL$10:AL20),-ROUNDDOWN($N21*AL$5/100,0)),0) -> 0 | AM21: =IF(AND(AM$7="○",$A21>=AM$8,$A21<=AM$9),IF(SUM(AM$10:AM20)-ROUNDDOWN($L21*AM$5/100,0)<-AM$6,-AM$6-SUM(AM$10:AM20),-ROUNDDOWN($L21*AM$5/100,0)),0) -> 0 | AN21: =IF(AND(AN$7="○",$A21>=AN$8,$A21<=AN$9),IF(SUM(AN$10:AN20)-ROUNDDOWN($M21*AN$5/100,0)<-AN$6,-AN$6-SUM(AN$10:AN20),-ROUNDDOWN($M21*AN$5/100,0)),0) -> 0 | AO21: =IF(AND($A21>=AO$8,$A21<=AO$9),IF(SUM(AO$10:AO20)-ROUNDDOWN($K21*AO$5/100,0)<-AO$6,-AO$6-SUM(AO$10:AO20),-ROUNDDOWN($K21*AO$5/100,0)),0) -> 0 | AP21: =IF(AND($A21>=AP$8,$A21<=AP$9),IF(SUM(AP$10:AP20)-ROUNDDOWN($K21*AP$5/100,0)<-AP$6,-AP$6-SUM(AP$10:AP20),-ROUNDDOWN($K21*AP$5/100,0)),0) -> 0 | AQ21: =IF(AND($A21>=AQ$8,$A21<=AQ$9),IF(SUM(AQ$10:AQ20)-ROUNDDOWN($K21*AQ$5/100,0)<-AQ$6,-AQ$6-SUM(AQ$10:AQ20),-ROUNDDOWN($K21*AQ$5/100,0)),0) -> 0 | AR21: =IF(AND($A21>=AR$8,$A21<=AR$9),IF(SUM(AR$10:AR20)-ROUNDDOWN($K21*AR$5/100,0)<-AR$6,-AR$6-SUM(AR$10:AR20),-ROUNDDOWN($K21*AR$5/100,0)),0) -> 0 | AS21: =IF(SUMIFS(AS$10:AS20,$A$10:$A20,$A21)-ROUNDDOWN($K21*$S21/100,0)<-$S21*1000,-$S21*1000-SUMIFS(AS$10:AS20,$A$10:$A20,$A21),-ROUNDDOWN($K21*$S21/100,0)) -> 0 | AT21: =IF(AND(X21="○",$A21>=AT$8,$A21<=AT$9,K21>=3980),IF(SUM(AT$10:AT20)-ROUNDDOWN($K21*AT$5/100,0)<-AT$6,-AT$6-SUM(AT$10:AT20),-ROUNDDOWN($K21*AT$5/100,0)),0) -> 0 | AU21: =IF(O21="○",IF(SUM(AU$10:AU20)-ROUNDDOWN($K21*AU$5/100,0)<-AU$6,-AU$6-SUM(AU$10:AU20),-ROUNDDOWN($K21*AU$5/100,0)),0) -> 0 | AV21: =IF(P21="○",IF(SUM(AV$10:AV20)-ROUNDDOWN($K21*AV$5/100,0)<-AV$6,-AV$6-SUM(AV$10:AV20),-ROUNDDOWN($K21*AV$5/100,0)),0) -> 0 | AW21: =IF(Q21="○",IF(SUM(AW$10:AW20)-ROUNDDOWN($K21*AW$5/100,0)<-AW$6,-AW$6-SUM(AW$10:AW20),-ROUNDDOWN($K21*AW$5/100,0)),0) -> 0 | AX21: =IF(R21="○",IF(SUM(AX$10:AX20)-ROUNDDOWN($K21*AX$5/100,0)<-AX$6,-AX$6-SUM(AX$10:AX20),-ROUNDDOWN($K21*AX$5/100,0)),0) -> 0 | AY21: 0 | AZ21: =-ROUNDDOWN($K21*AY21/100,0) -> 0 | BA21: =-ROUNDDOWN($K21*AI21/100,0) -> 0 | BC21: =-ROUNDDOWN($K21*BB21/100,0) -> 0 | BD21: 0 | BE21: =-ROUNDDOWN($K21*BD21/100,0) -> 0 | BF21: 0 | BG21: =-ROUNDDOWN($K21*BF21/100,0) -> 0 | BH21: 0 | BI21: =-ROUNDDOWN($K21*BH21/100,0) -> 0 | BJ21: =IF(AND(BJ$7="○",$A21>=BJ$8,$A21<=BJ$9),IF(SUM(BJ$10:BJ20)-ROUNDDOWN($M21*BJ$5/100,0)<-BJ$6,-BJ$6-SUM(BJ$10:BJ20),-ROUNDDOWN($M21*BJ$5/100,0)),0) -> 0 | BK21: =IF(AND(BK$7="○",$A21>=BK$8,$A21<=BK$9),IF(SUM(BK$10:BK20)-ROUNDDOWN($L21*BK$5/100,0)<-BK$6,-BK$6-SUM(BK$10:BK20),-ROUNDDOWN($L21*BK$5/100,0)),0) -> 0 | BL21: =IF(AND(BL$7="○",$A21>=BL$8,$A21<=BL$9),IF(SUM(BL$10:BL20)-ROUNDDOWN($L21*BL$5/100,0)<-BL$6,-BL$6-SUM(BL$10:BL20),-ROUNDDOWN($L21*BL$5/100,0)),0) -> 0 | BM21: =IF(AND(BM$7="○",$A21>=BM$8,$A21<=BM$9),IF(SUM(BM$10:BM20)-ROUNDDOWN($M21*BM$5/100,0)<-BM$6,-BM$6-SUM(BM$10:BM20),-ROUNDDOWN($M21*BM$5/100,0)),0) -> 0 | BN21: =IF(AND(BN$7="○",$A21>=BN$8,$A21<=BN$9),IF(SUM(BN$10:BN20)-ROUNDDOWN($M21*BN$5/100,0)<-BN$6,-BN$6-SUM(BN$10:BN20),-ROUNDDOWN($M21*BN$5/100,0)),0) -> 0 | BO21: =IF(AND(BO$7="○",$A21>=BO$8,$A21<=BO$9),IF(SUM(BO$10:BO20)-ROUNDDOWN($M21*BO$5/100,0)<-BO$6,-BO$6-SUM(BO$10:BO20),-ROUNDDOWN($M21*BO$5/100,0)),0) -> 0 | BP21: =IF(AND(BP$7="○",$A21>=BP$8,$A21<=BP$9),IF(SUM(BP$10:BP20)-ROUNDDOWN($M21*BP$5/100,0)<-BP$6,-BP$6-SUM(BP$10:BP20),-ROUNDDOWN($M21*BP$5/100,0)),0) -> 0 | BQ21: =IF(AND(BQ$7="○",$A21>=BQ$8,$A21<=BQ$9),IF(SUM(BQ$10:BQ20)-ROUNDDOWN($L21*BQ$5/100,0)<-BQ$6,-BQ$6-SUM(BQ$10:BQ20),-ROUNDDOWN($L21*BQ$5/100,0)),0) -> 0 | BR21: =IF(AND(BR$7="○",$A21>=BR$8,$A21<=BR$9),IF(SUM(BR$10:BR20)-ROUNDDOWN($M21*BR$5/100,0)<-BR$6,-BR$6-SUM(BR$10:BR20),-ROUNDDOWN($M21*BR$5/100,0)),0) -> 0 | BS21: =IF(AND(BS$7="○",$A21>=BS$8,$A21<=BS$9),IF(SUM(BS$10:BS20)-ROUNDDOWN($M21*BS$5/100,0)<-BS$6,-BS$6-SUM(BS$10:BS20),-ROUNDDOWN($M21*BS$5/100,0)),0) -> 0 | BT21: =IF(AND(BT$7="○",$A21>=BT$8,$A21<=BT$9),IF(SUM(BT$10:BT20)-ROUNDDOWN($M21*BT$5/100,0)<-BT$6,-BT$6-SUM(BT$10:BT20),-ROUNDDOWN($M21*BT$5/100,0)),0) -> 0 | BU21: =IF(AND(BU$7="○",$A21>=BU$8,$A21<=BU$9),IF(SUM(BU$10:BU20)-ROUNDDOWN($M21*BU$5/100,0)<-BU$6,-BU$6-SUM(BU$10:BU20),-ROUNDDOWN($M21*BU$5/100,0)),0) -> 0 | BV21: =IF(AND(BV$7="○",$A21>=BV$8,$A21<=BV$9),IF(SUM(BV$10:BV20)-ROUNDDOWN($M21*BV$5/100,0)<-BV$6,-BV$6-SUM(BV$10:BV20),-ROUNDDOWN($M21*BV$5/100,0)),0) -> 0 | BW21: =IF(AND(BW$7="○",$A21>=BW$8,$A21<=BW$9),IF(SUM(BW$10:BW20)-ROUNDDOWN($M21*BW$5/100,0)<-BW$6,-BW$6-SUM(BW$10:BW20),-ROUNDDOWN($M21*BW$5/100,0)),0) -> 0 | BX21: =IF(AND(T21="○",$A21>=BX$8,$A21<=BX$9),IF(SUM(BX$10:BX20)-ROUNDDOWN($K21*BX$5/100,0)<-BX$6,-BX$6-SUM(BX$10:BX20),-ROUNDDOWN($K21*BX$5/100,0)),0) -> 0 | BY21: =IF(AND(U21="○",$A21>=BY$8,$A21<=BY$9),IF(SUM(BY$10:BY20)-ROUNDDOWN($K21*BY$5/100,0)<-BY$6,-BY$6-SUM(BY$10:BY20),-ROUNDDOWN($K21*BY$5/100,0)),0) -> 0 | BZ21: =IF(AND(V21="○",$A21>=BZ$8,$A21<=BZ$9),IF(SUM(BZ$10:BZ20)-ROUNDDOWN($K21*BZ$5/100,0)<-BZ$6,-BZ$6-SUM(BZ$10:BZ20),-ROUNDDOWN($K21*BZ$5/100,0)),0) -> 0 | CA21: =IF(AND(W21="○",$A21>=CA$8,$A21<=CA$9),IF(SUM(CA$10:CA20)-ROUNDDOWN($K21*CA$5/100,0)<-CA$6,-CA$6-SUM(CA$10:CA20),-ROUNDDOWN($K21*CA$5/100,0)),0) -> 0 | CG21: =+SUM(AJ21:CF21,BC21,BE21,AZ21,BA21,BG21,BI21) -> 0 | CH21: =+CG21+N21 -> 0 | CI21: =IFERROR(ROUNDDOWN((CH21/G21),0),0) -> 0 | CO21: =IFERROR(CN21-CI21,0) -> 0 | CP21: =IFERROR(CN21/CI21,0) -> 0 | CR21: =+CO21*G21 -> 0 | CT21: =INDEX([2]マスタ!$A:$A,MATCH(D21,[2]マスタ!$C:$C,0)) -> #N/A | CU21: =IFERROR(TEXT(TODAY(),"yyyymmdd")&"_"&ROUNDDOWN(H21+I21,0)&"-"&ROUNDDOWN(CI21,0),"") -> 20260620_0-0
G22: 1 | H22: =+F22*G22 -> 0 | K22: =+ROUNDDOWN((H22+I22)/100,0)*100 -> 0 | L22: =+ROUNDDOWN((H22+I22)/1.1/100,0)*100 -> 0 | M22: =+ROUNDDOWN((H22+I22)/1.1/200,0)*200 -> 0 | N22: =+H22+I22+J22 -> 0 | O22: =IF(OR(WEEKDAY($A22,2)=2,WEEKDAY($A22,2)=4),"○","✕") -> ✕ | P22: =+IF(MOD(TEXT($A22,"DD"),5)=0,"○","✕") -> ○ | Q22: =+IF((TEXT($A22,"DD")+0)=1,"○","✕") -> ✕ | R22: =+IF((TEXT($A22,"DD")+0)=18,"○","✕") -> ✕ | S22: 0 | T22: ✕ | U22: ✕ | V22: ✕ | W22: ✕ | X22: ○ | Y22: ✕ | Z22: ✕ | AA22: ✕ | AB22: ✕ | AC22: ✕ | AD22: =+IF(ISERROR(VLOOKUP($B22,AD$10:AD21,1,0)),IF(AND($N22>=1000,$A22>=AO$8,$A22<=AO$9),$B22,""),"") | AE22: =+IF(ISERROR(VLOOKUP($B22,AE$10:AE21,1,0)),IF(AND($N22>=1000,$A22>=AP$8,$A22<=AP$9),$B22,""),"") | AF22: =+IF(ISERROR(VLOOKUP($B22,AF$10:AF21,1,0)),IF(AND($N22>=1000,$A22>=AQ$8,$A22<=AQ$9),$B22,""),"") | AG22: =+IF(ISERROR(VLOOKUP($B22,AG$10:AG21,1,0)),IF(AND($N22>=1000,$A22>=AR$8,$A22<=AR$9),$B22,""),"") | AI22: 0 | AJ22: =IF(AND(AJ$7="○",$A22>=AJ$8,$A22<=AJ$9),IF(SUM(AJ$10:AJ21)-ROUNDDOWN($K22*AJ$5/100,0)<-AJ$6,-AJ$6-SUM(AJ$10:AJ21),-ROUNDDOWN($K22*AJ$5/100,0)),0) -> 0 | AK22: =IF(AND(AK$7="○",$A22>=AK$8,$A22<=AK$9),IF(SUM(AK$10:AK21)-ROUNDDOWN($L22*AK$5/100,0)<-AK$6,-AK$6-SUM(AK$10:AK21),-ROUNDDOWN($L22*AK$5/100,0)),0) -> 0 | AL22: =IF(AND(AL$7="○",$A22>=AL$8,$A22<=AL$9),IF(SUM(AL$10:AL21)-ROUNDDOWN($N22*AL$5/100,0)<-AL$6,-AL$6-SUM(AL$10:AL21),-ROUNDDOWN($N22*AL$5/100,0)),0) -> 0 | AM22: =IF(AND(AM$7="○",$A22>=AM$8,$A22<=AM$9),IF(SUM(AM$10:AM21)-ROUNDDOWN($L22*AM$5/100,0)<-AM$6,-AM$6-SUM(AM$10:AM21),-ROUNDDOWN($L22*AM$5/100,0)),0) -> 0 | AN22: =IF(AND(AN$7="○",$A22>=AN$8,$A22<=AN$9),IF(SUM(AN$10:AN21)-ROUNDDOWN($M22*AN$5/100,0)<-AN$6,-AN$6-SUM(AN$10:AN21),-ROUNDDOWN($M22*AN$5/100,0)),0) -> 0 | AO22: =IF(AND($A22>=AO$8,$A22<=AO$9),IF(SUM(AO$10:AO21)-ROUNDDOWN($K22*AO$5/100,0)<-AO$6,-AO$6-SUM(AO$10:AO21),-ROUNDDOWN($K22*AO$5/100,0)),0) -> 0 | AP22: =IF(AND($A22>=AP$8,$A22<=AP$9),IF(SUM(AP$10:AP21)-ROUNDDOWN($K22*AP$5/100,0)<-AP$6,-AP$6-SUM(AP$10:AP21),-ROUNDDOWN($K22*AP$5/100,0)),0) -> 0 | AQ22: =IF(AND($A22>=AQ$8,$A22<=AQ$9),IF(SUM(AQ$10:AQ21)-ROUNDDOWN($K22*AQ$5/100,0)<-AQ$6,-AQ$6-SUM(AQ$10:AQ21),-ROUNDDOWN($K22*AQ$5/100,0)),0) -> 0 | AR22: =IF(AND($A22>=AR$8,$A22<=AR$9),IF(SUM(AR$10:AR21)-ROUNDDOWN($K22*AR$5/100,0)<-AR$6,-AR$6-SUM(AR$10:AR21),-ROUNDDOWN($K22*AR$5/100,0)),0) -> 0 | AS22: =IF(SUMIFS(AS$10:AS21,$A$10:$A21,$A22)-ROUNDDOWN($K22*$S22/100,0)<-$S22*1000,-$S22*1000-SUMIFS(AS$10:AS21,$A$10:$A21,$A22),-ROUNDDOWN($K22*$S22/100,0)) -> 0 | AT22: =IF(AND(X22="○",$A22>=AT$8,$A22<=AT$9,K22>=3980),IF(SUM(AT$10:AT21)-ROUNDDOWN($K22*AT$5/100,0)<-AT$6,-AT$6-SUM(AT$10:AT21),-ROUNDDOWN($K22*AT$5/100,0)),0) -> 0 | AU22: =IF(O22="○",IF(SUM(AU$10:AU21)-ROUNDDOWN($K22*AU$5/100,0)<-AU$6,-AU$6-SUM(AU$10:AU21),-ROUNDDOWN($K22*AU$5/100,0)),0) -> 0 | AV22: =IF(P22="○",IF(SUM(AV$10:AV21)-ROUNDDOWN($K22*AV$5/100,0)<-AV$6,-AV$6-SUM(AV$10:AV21),-ROUNDDOWN($K22*AV$5/100,0)),0) -> 0 | AW22: =IF(Q22="○",IF(SUM(AW$10:AW21)-ROUNDDOWN($K22*AW$5/100,0)<-AW$6,-AW$6-SUM(AW$10:AW21),-ROUNDDOWN($K22*AW$5/100,0)),0) -> 0 | AX22: =IF(R22="○",IF(SUM(AX$10:AX21)-ROUNDDOWN($K22*AX$5/100,0)<-AX$6,-AX$6-SUM(AX$10:AX21),-ROUNDDOWN($K22*AX$5/100,0)),0) -> 0 | AY22: 0 | AZ22: =-ROUNDDOWN($K22*AY22/100,0) -> 0 | BA22: =-ROUNDDOWN($K22*AI22/100,0) -> 0 | BC22: =-ROUNDDOWN($K22*BB22/100,0) -> 0 | BD22: 0 | BE22: =-ROUNDDOWN($K22*BD22/100,0) -> 0 | BF22: 0 | BG22: =-ROUNDDOWN($K22*BF22/100,0) -> 0 | BH22: 0 | BI22: =-ROUNDDOWN($K22*BH22/100,0) -> 0 | BJ22: =IF(AND(BJ$7="○",$A22>=BJ$8,$A22<=BJ$9),IF(SUM(BJ$10:BJ21)-ROUNDDOWN($M22*BJ$5/100,0)<-BJ$6,-BJ$6-SUM(BJ$10:BJ21),-ROUNDDOWN($M22*BJ$5/100,0)),0) -> 0 | BK22: =IF(AND(BK$7="○",$A22>=BK$8,$A22<=BK$9),IF(SUM(BK$10:BK21)-ROUNDDOWN($L22*BK$5/100,0)<-BK$6,-BK$6-SUM(BK$10:BK21),-ROUNDDOWN($L22*BK$5/100,0)),0) -> 0 | BL22: =IF(AND(BL$7="○",$A22>=BL$8,$A22<=BL$9),IF(SUM(BL$10:BL21)-ROUNDDOWN($L22*BL$5/100,0)<-BL$6,-BL$6-SUM(BL$10:BL21),-ROUNDDOWN($L22*BL$5/100,0)),0) -> 0 | BM22: =IF(AND(BM$7="○",$A22>=BM$8,$A22<=BM$9),IF(SUM(BM$10:BM21)-ROUNDDOWN($M22*BM$5/100,0)<-BM$6,-BM$6-SUM(BM$10:BM21),-ROUNDDOWN($M22*BM$5/100,0)),0) -> 0 | BN22: =IF(AND(BN$7="○",$A22>=BN$8,$A22<=BN$9),IF(SUM(BN$10:BN21)-ROUNDDOWN($M22*BN$5/100,0)<-BN$6,-BN$6-SUM(BN$10:BN21),-ROUNDDOWN($M22*BN$5/100,0)),0) -> 0 | BO22: =IF(AND(BO$7="○",$A22>=BO$8,$A22<=BO$9),IF(SUM(BO$10:BO21)-ROUNDDOWN($M22*BO$5/100,0)<-BO$6,-BO$6-SUM(BO$10:BO21),-ROUNDDOWN($M22*BO$5/100,0)),0) -> 0 | BP22: =IF(AND(BP$7="○",$A22>=BP$8,$A22<=BP$9),IF(SUM(BP$10:BP21)-ROUNDDOWN($M22*BP$5/100,0)<-BP$6,-BP$6-SUM(BP$10:BP21),-ROUNDDOWN($M22*BP$5/100,0)),0) -> 0 | BQ22: =IF(AND(BQ$7="○",$A22>=BQ$8,$A22<=BQ$9),IF(SUM(BQ$10:BQ21)-ROUNDDOWN($L22*BQ$5/100,0)<-BQ$6,-BQ$6-SUM(BQ$10:BQ21),-ROUNDDOWN($L22*BQ$5/100,0)),0) -> 0 | BR22: =IF(AND(BR$7="○",$A22>=BR$8,$A22<=BR$9),IF(SUM(BR$10:BR21)-ROUNDDOWN($M22*BR$5/100,0)<-BR$6,-BR$6-SUM(BR$10:BR21),-ROUNDDOWN($M22*BR$5/100,0)),0) -> 0 | BS22: =IF(AND(BS$7="○",$A22>=BS$8,$A22<=BS$9),IF(SUM(BS$10:BS21)-ROUNDDOWN($M22*BS$5/100,0)<-BS$6,-BS$6-SUM(BS$10:BS21),-ROUNDDOWN($M22*BS$5/100,0)),0) -> 0 | BT22: =IF(AND(BT$7="○",$A22>=BT$8,$A22<=BT$9),IF(SUM(BT$10:BT21)-ROUNDDOWN($M22*BT$5/100,0)<-BT$6,-BT$6-SUM(BT$10:BT21),-ROUNDDOWN($M22*BT$5/100,0)),0) -> 0 | BU22: =IF(AND(BU$7="○",$A22>=BU$8,$A22<=BU$9),IF(SUM(BU$10:BU21)-ROUNDDOWN($M22*BU$5/100,0)<-BU$6,-BU$6-SUM(BU$10:BU21),-ROUNDDOWN($M22*BU$5/100,0)),0) -> 0 | BV22: =IF(AND(BV$7="○",$A22>=BV$8,$A22<=BV$9),IF(SUM(BV$10:BV21)-ROUNDDOWN($M22*BV$5/100,0)<-BV$6,-BV$6-SUM(BV$10:BV21),-ROUNDDOWN($M22*BV$5/100,0)),0) -> 0 | BW22: =IF(AND(BW$7="○",$A22>=BW$8,$A22<=BW$9),IF(SUM(BW$10:BW21)-ROUNDDOWN($M22*BW$5/100,0)<-BW$6,-BW$6-SUM(BW$10:BW21),-ROUNDDOWN($M22*BW$5/100,0)),0) -> 0 | BX22: =IF(AND(T22="○",$A22>=BX$8,$A22<=BX$9),IF(SUM(BX$10:BX21)-ROUNDDOWN($K22*BX$5/100,0)<-BX$6,-BX$6-SUM(BX$10:BX21),-ROUNDDOWN($K22*BX$5/100,0)),0) -> 0 | BY22: =IF(AND(U22="○",$A22>=BY$8,$A22<=BY$9),IF(SUM(BY$10:BY21)-ROUNDDOWN($K22*BY$5/100,0)<-BY$6,-BY$6-SUM(BY$10:BY21),-ROUNDDOWN($K22*BY$5/100,0)),0) -> 0 | BZ22: =IF(AND(V22="○",$A22>=BZ$8,$A22<=BZ$9),IF(SUM(BZ$10:BZ21)-ROUNDDOWN($K22*BZ$5/100,0)<-BZ$6,-BZ$6-SUM(BZ$10:BZ21),-ROUNDDOWN($K22*BZ$5/100,0)),0) -> 0 | CA22: =IF(AND(W22="○",$A22>=CA$8,$A22<=CA$9),IF(SUM(CA$10:CA21)-ROUNDDOWN($K22*CA$5/100,0)<-CA$6,-CA$6-SUM(CA$10:CA21),-ROUNDDOWN($K22*CA$5/100,0)),0) -> 0 | CG22: =+SUM(AJ22:CF22,BC22,BE22,AZ22,BA22,BG22,BI22) -> 0 | CH22: =+CG22+N22 -> 0 | CI22: =IFERROR(ROUNDDOWN((CH22/G22),0),0) -> 0 | CO22: =IFERROR(CN22-CI22,0) -> 0 | CP22: =IFERROR(CN22/CI22,0) -> 0 | CR22: =+CO22*G22 -> 0 | CT22: =INDEX([2]マスタ!$A:$A,MATCH(D22,[2]マスタ!$C:$C,0)) -> #N/A | CU22: =IFERROR(TEXT(TODAY(),"yyyymmdd")&"_"&ROUNDDOWN(H22+I22,0)&"-"&ROUNDDOWN(CI22,0),"") -> 20260620_0-0
... G27: 1 | H27: =+F27*G27 -> 0 | K27: =+ROUNDDOWN((H27+I27)/100,0)*100 -> 0 | L27: =+ROUNDDOWN((H27+I27)/1.1/100,0)*100 -> 0 | M27: =+ROUNDDOWN((H27+I27)/1.1/200,0)*200 -> 0 | N27: =+H27+I27+J27 -> 0 | O27: =IF(OR(WEEKDAY($A27,2)=2,WEEKDAY($A27,2)=4),"○","✕") -> ✕ | P27: =+IF(MOD(TEXT($A27,"DD"),5)=0,"○","✕") -> ○ | Q27: =+IF((TEXT($A27,"DD")+0)=1,"○","✕") -> ✕ | R27: =+IF((TEXT($A27,"DD")+0)=18,"○","✕") -> ✕ | S27: 0 | T27: ✕ | U27: ✕ | V27: ✕ | W27: ✕ | X27: ○ | Y27: ✕ | Z27: ✕ | AA27: ✕ | AB27: ✕ | AC27: ✕ | AD27: =+IF(ISERROR(VLOOKUP($B27,AD$10:AD26,1,0)),IF(AND($N27>=1000,$A27>=AO$8,$A27<=AO$9),$B27,""),"") | AE27: =+IF(ISERROR(VLOOKUP($B27,AE$10:AE26,1,0)),IF(AND($N27>=1000,$A27>=AP$8,$A27<=AP$9),$B27,""),"") | AF27: =+IF(ISERROR(VLOOKUP($B27,AF$10:AF26,1,0)),IF(AND($N27>=1000,$A27>=AQ$8,$A27<=AQ$9),$B27,""),"") | AG27: =+IF(ISERROR(VLOOKUP($B27,AG$10:AG26,1,0)),IF(AND($N27>=1000,$A27>=AR$8,$A27<=AR$9),$B27,""),"") | AI27: 0 | AJ27: =IF(AND(AJ$7="○",$A27>=AJ$8,$A27<=AJ$9),IF(SUM(AJ$10:AJ26)-ROUNDDOWN($K27*AJ$5/100,0)<-AJ$6,-AJ$6-SUM(AJ$10:AJ26),-ROUNDDOWN($K27*AJ$5/100,0)),0) -> 0 | AK27: =IF(AND(AK$7="○",$A27>=AK$8,$A27<=AK$9),IF(SUM(AK$10:AK26)-ROUNDDOWN($L27*AK$5/100,0)<-AK$6,-AK$6-SUM(AK$10:AK26),-ROUNDDOWN($L27*AK$5/100,0)),0) -> 0 | AL27: =IF(AND(AL$7="○",$A27>=AL$8,$A27<=AL$9),IF(SUM(AL$10:AL26)-ROUNDDOWN($N27*AL$5/100,0)<-AL$6,-AL$6-SUM(AL$10:AL26),-ROUNDDOWN($N27*AL$5/100,0)),0) -> 0 | AM27: =IF(AND(AM$7="○",$A27>=AM$8,$A27<=AM$9),IF(SUM(AM$10:AM26)-ROUNDDOWN($L27*AM$5/100,0)<-AM$6,-AM$6-SUM(AM$10:AM26),-ROUNDDOWN($L27*AM$5/100,0)),0) -> 0 | AN27: =IF(AND(AN$7="○",$A27>=AN$8,$A27<=AN$9),IF(SUM(AN$10:AN26)-ROUNDDOWN($M27*AN$5/100,0)<-AN$6,-AN$6-SUM(AN$10:AN26),-ROUNDDOWN($M27*AN$5/100,0)),0) -> 0 | AO27: =IF(AND($A27>=AO$8,$A27<=AO$9),IF(SUM(AO$10:AO26)-ROUNDDOWN($K27*AO$5/100,0)<-AO$6,-AO$6-SUM(AO$10:AO26),-ROUNDDOWN($K27*AO$5/100,0)),0) -> 0 | AP27: =IF(AND($A27>=AP$8,$A27<=AP$9),IF(SUM(AP$10:AP26)-ROUNDDOWN($K27*AP$5/100,0)<-AP$6,-AP$6-SUM(AP$10:AP26),-ROUNDDOWN($K27*AP$5/100,0)),0) -> 0 | AQ27: =IF(AND($A27>=AQ$8,$A27<=AQ$9),IF(SUM(AQ$10:AQ26)-ROUNDDOWN($K27*AQ$5/100,0)<-AQ$6,-AQ$6-SUM(AQ$10:AQ26),-ROUNDDOWN($K27*AQ$5/100,0)),0) -> 0 | AR27: =IF(AND($A27>=AR$8,$A27<=AR$9),IF(SUM(AR$10:AR26)-ROUNDDOWN($K27*AR$5/100,0)<-AR$6,-AR$6-SUM(AR$10:AR26),-ROUNDDOWN($K27*AR$5/100,0)),0) -> 0 | AS27: =IF(SUMIFS(AS$10:AS26,$A$10:$A26,$A27)-ROUNDDOWN($K27*$S27/100,0)<-$S27*1000,-$S27*1000-SUMIFS(AS$10:AS26,$A$10:$A26,$A27),-ROUNDDOWN($K27*$S27/100,0)) -> 0 | AT27: =IF(AND(X27="○",$A27>=AT$8,$A27<=AT$9,K27>=3980),IF(SUM(AT$10:AT26)-ROUNDDOWN($K27*AT$5/100,0)<-AT$6,-AT$6-SUM(AT$10:AT26),-ROUNDDOWN($K27*AT$5/100,0)),0) -> 0 | AU27: =IF(O27="○",IF(SUM(AU$10:AU26)-ROUNDDOWN($K27*AU$5/100,0)<-AU$6,-AU$6-SUM(AU$10:AU26),-ROUNDDOWN($K27*AU$5/100,0)),0) -> 0 | AV27: =IF(P27="○",IF(SUM(AV$10:AV26)-ROUNDDOWN($K27*AV$5/100,0)<-AV$6,-AV$6-SUM(AV$10:AV26),-ROUNDDOWN($K27*AV$5/100,0)),0) -> 0 | AW27: =IF(Q27="○",IF(SUM(AW$10:AW26)-ROUNDDOWN($K27*AW$5/100,0)<-AW$6,-AW$6-SUM(AW$10:AW26),-ROUNDDOWN($K27*AW$5/100,0)),0) -> 0 | AX27: =IF(R27="○",IF(SUM(AX$10:AX26)-ROUNDDOWN($K27*AX$5/100,0)<-AX$6,-AX$6-SUM(AX$10:AX26),-ROUNDDOWN($K27*AX$5/100,0)),0) -> 0 | AY27: 0 | AZ27: =-ROUNDDOWN($K27*AY27/100,0) -> 0 | BA27: =-ROUNDDOWN($K27*AI27/100,0) -> 0 | BC27: =-ROUNDDOWN($K27*BB27/100,0) -> 0 | BD27: 0 | BE27: =-ROUNDDOWN($K27*BD27/100,0) -> 0 | BF27: 0 | BG27: =-ROUNDDOWN($K27*BF27/100,0) -> 0 | BH27: 0 | BI27: =-ROUNDDOWN($K27*BH27/100,0) -> 0 | BJ27: =IF(AND(BJ$7="○",$A27>=BJ$8,$A27<=BJ$9),IF(SUM(BJ$10:BJ26)-ROUNDDOWN($M27*BJ$5/100,0)<-BJ$6,-BJ$6-SUM(BJ$10:BJ26),-ROUNDDOWN($M27*BJ$5/100,0)),0) -> 0 | BK27: =IF(AND(BK$7="○",$A27>=BK$8,$A27<=BK$9),IF(SUM(BK$10:BK26)-ROUNDDOWN($L27*BK$5/100,0)<-BK$6,-BK$6-SUM(BK$10:BK26),-ROUNDDOWN($L27*BK$5/100,0)),0) -> 0 | BL27: =IF(AND(BL$7="○",$A27>=BL$8,$A27<=BL$9),IF(SUM(BL$10:BL26)-ROUNDDOWN($L27*BL$5/100,0)<-BL$6,-BL$6-SUM(BL$10:BL26),-ROUNDDOWN($L27*BL$5/100,0)),0) -> 0 | BM27: =IF(AND(BM$7="○",$A27>=BM$8,$A27<=BM$9),IF(SUM(BM$10:BM26)-ROUNDDOWN($M27*BM$5/100,0)<-BM$6,-BM$6-SUM(BM$10:BM26),-ROUNDDOWN($M27*BM$5/100,0)),0) -> 0 | BN27: =IF(AND(BN$7="○",$A27>=BN$8,$A27<=BN$9),IF(SUM(BN$10:BN26)-ROUNDDOWN($M27*BN$5/100,0)<-BN$6,-BN$6-SUM(BN$10:BN26),-ROUNDDOWN($M27*BN$5/100,0)),0) -> 0 | BO27: =IF(AND(BO$7="○",$A27>=BO$8,$A27<=BO$9),IF(SUM(BO$10:BO26)-ROUNDDOWN($M27*BO$5/100,0)<-BO$6,-BO$6-SUM(BO$10:BO26),-ROUNDDOWN($M27*BO$5/100,0)),0) -> 0 | BP27: =IF(AND(BP$7="○",$A27>=BP$8,$A27<=BP$9),IF(SUM(BP$10:BP26)-ROUNDDOWN($M27*BP$5/100,0)<-BP$6,-BP$6-SUM(BP$10:BP26),-ROUNDDOWN($M27*BP$5/100,0)),0) -> 0 | BQ27: =IF(AND(BQ$7="○",$A27>=BQ$8,$A27<=BQ$9),IF(SUM(BQ$10:BQ26)-ROUNDDOWN($L27*BQ$5/100,0)<-BQ$6,-BQ$6-SUM(BQ$10:BQ26),-ROUNDDOWN($L27*BQ$5/100,0)),0) -> 0 | BR27: =IF(AND(BR$7="○",$A27>=BR$8,$A27<=BR$9),IF(SUM(BR$10:BR26)-ROUNDDOWN($M27*BR$5/100,0)<-BR$6,-BR$6-SUM(BR$10:BR26),-ROUNDDOWN($M27*BR$5/100,0)),0) -> 0 | BS27: =IF(AND(BS$7="○",$A27>=BS$8,$A27<=BS$9),IF(SUM(BS$10:BS26)-ROUNDDOWN($M27*BS$5/100,0)<-BS$6,-BS$6-SUM(BS$10:BS26),-ROUNDDOWN($M27*BS$5/100,0)),0) -> 0 | BT27: =IF(AND(BT$7="○",$A27>=BT$8,$A27<=BT$9),IF(SUM(BT$10:BT26)-ROUNDDOWN($M27*BT$5/100,0)<-BT$6,-BT$6-SUM(BT$10:BT26),-ROUNDDOWN($M27*BT$5/100,0)),0) -> 0 | BU27: =IF(AND(BU$7="○",$A27>=BU$8,$A27<=BU$9),IF(SUM(BU$10:BU26)-ROUNDDOWN($M27*BU$5/100,0)<-BU$6,-BU$6-SUM(BU$10:BU26),-ROUNDDOWN($M27*BU$5/100,0)),0) -> 0 | BV27: =IF(AND(BV$7="○",$A27>=BV$8,$A27<=BV$9),IF(SUM(BV$10:BV26)-ROUNDDOWN($M27*BV$5/100,0)<-BV$6,-BV$6-SUM(BV$10:BV26),-ROUNDDOWN($M27*BV$5/100,0)),0) -> 0 | BW27: =IF(AND(BW$7="○",$A27>=BW$8,$A27<=BW$9),IF(SUM(BW$10:BW26)-ROUNDDOWN($M27*BW$5/100,0)<-BW$6,-BW$6-SUM(BW$10:BW26),-ROUNDDOWN($M27*BW$5/100,0)),0) -> 0 | BX27: =IF(AND(T27="○",$A27>=BX$8,$A27<=BX$9),IF(SUM(BX$10:BX26)-ROUNDDOWN($K27*BX$5/100,0)<-BX$6,-BX$6-SUM(BX$10:BX26),-ROUNDDOWN($K27*BX$5/100,0)),0) -> 0 | BY27: =IF(AND(U27="○",$A27>=BY$8,$A27<=BY$9),IF(SUM(BY$10:BY26)-ROUNDDOWN($K27*BY$5/100,0)<-BY$6,-BY$6-SUM(BY$10:BY26),-ROUNDDOWN($K27*BY$5/100,0)),0) -> 0 | BZ27: =IF(AND(V27="○",$A27>=BZ$8,$A27<=BZ$9),IF(SUM(BZ$10:BZ26)-ROUNDDOWN($K27*BZ$5/100,0)<-BZ$6,-BZ$6-SUM(BZ$10:BZ26),-ROUNDDOWN($K27*BZ$5/100,0)),0) -> 0 | CA27: =IF(AND(W27="○",$A27>=CA$8,$A27<=CA$9),IF(SUM(CA$10:CA26)-ROUNDDOWN($K27*CA$5/100,0)<-CA$6,-CA$6-SUM(CA$10:CA26),-ROUNDDOWN($K27*CA$5/100,0)),0) -> 0 | CG27: =+SUM(AJ27:CF27,BC27,BE27,AZ27,BA27,BG27,BI27) -> 0 | CH27: =+CG27+N27 -> 0 | CI27: =IFERROR(ROUNDDOWN((CH27/G27),0),0) -> 0 | CO27: =IFERROR(CN27-CI27,0) -> 0 | CP27: =IFERROR(CN27/CI27,0) -> 0 | CR27: =+CO27*G27 -> 0 | CT27: =INDEX([2]マスタ!$A:$A,MATCH(D27,[2]マスタ!$C:$C,0)) -> #N/A | CU27: =IFERROR(TEXT(TODAY(),"yyyymmdd")&"_"&ROUNDDOWN(H27+I27,0)&"-"&ROUNDDOWN(CI27,0),"") -> 20260620_0-0
G28: 1 | H28: =+F28*G28 -> 0 | K28: =+ROUNDDOWN((H28+I28+J28)/100,0)*100 -> 0 | L28: =+ROUNDDOWN((H28+I28)/1.1/100,0)*100 -> 0 | M28: =+ROUNDDOWN((H28+I28)/1.1/200,0)*200 -> 0 | N28: =+H28+I28+J28 -> 0 | O28: =IF(OR(WEEKDAY($A28,2)=2,WEEKDAY($A28,2)=4),"○","✕") -> ✕ | P28: =+IF(MOD(TEXT($A28,"DD"),5)=0,"○","✕") -> ○ | Q28: =+IF((TEXT(A28,"DD")+0)=1,"○","✕") -> ✕ | R28: =+IF((TEXT($A28,"DD")+0)=18,"○","✕") -> ✕ | S28: 0 | T28: ✕ | U28: ✕ | V28: ✕ | W28: ✕ | X28: ○ | Y28: ✕ | Z28: ✕ | AA28: ✕ | AB28: ✕ | AC28: ✕ | AD28: =+IF(ISERROR(VLOOKUP($B28,AD$10:AD20,1,0)),IF(AND($N28>=1000,$A28>=AO$8,$A28<=AO$9),$B28,""),"") | AE28: =+IF(ISERROR(VLOOKUP($B28,AE$10:AE20,1,0)),IF(AND($N28>=1000,$A28>=AP$8,$A28<=AP$9),$B28,""),"") | AF28: =+IF(ISERROR(VLOOKUP($B28,AF$10:AF20,1,0)),IF(AND($N28>=1000,$A28>=AQ$8,$A28<=AQ$9),$B28,""),"") | AG28: =+IF(ISERROR(VLOOKUP($B28,AG$10:AG20,1,0)),IF(AND($N28>=1000,$A28>=AR$8,$A28<=AR$9),$B28,""),"") | AI28: 0 | AJ28: =IF(AND(AJ$7="○",$A28>=AJ$8,$A28<=AJ$9),IF(SUM(AJ$10:AJ27)-ROUNDDOWN($K28*AJ$5/100,0)<-AJ$6,-AJ$6-SUM(AJ$10:AJ27),-ROUNDDOWN($K28*AJ$5/100,0)),0) -> 0 | AK28: =IF(AND(AK$7="○",$A28>=AK$8,$A28<=AK$9),IF(SUM(AK$10:AK27)-ROUNDDOWN($L28*AK$5/100,0)<-AK$6,-AK$6-SUM(AK$10:AK27),-ROUNDDOWN($L28*AK$5/100,0)),0) -> 0 | AL28: =IF(AND(AL$7="○",$A28>=AL$8,$A28<=AL$9),IF(SUM(AL$10:AL27)-ROUNDDOWN($N28*AL$5/100,0)<-AL$6,-AL$6-SUM(AL$10:AL27),-ROUNDDOWN($N28*AL$5/100,0)),0) -> 0 | AM28: =IF(AND(AM$7="○",$A28>=AM$8,$A28<=AM$9),IF(SUM(AM$10:AM27)-ROUNDDOWN($L28*AM$5/100,0)<-AM$6,-AM$6-SUM(AM$10:AM27),-ROUNDDOWN($L28*AM$5/100,0)),0) -> 0 | AN28: =IF(AND(AN$7="○",$A28>=AN$8,$A28<=AN$9),IF(SUM(AN$10:AN27)-ROUNDDOWN($M28*AN$5/100,0)<-AN$6,-AN$6-SUM(AN$10:AN27),-ROUNDDOWN($M28*AN$5/100,0)),0) -> 0 | AO28: =IF(AND($A28>=AO$8,$A28<=AO$9),IF(SUM(AO$10:AO27)-ROUNDDOWN($K28*AO$5/100,0)<-AO$6,-AO$6-SUM(AO$10:AO27),-ROUNDDOWN($K28*AO$5/100,0)),0) -> 0 | AP28: =IF(AND($A28>=AP$8,$A28<=AP$9),IF(SUM(AP$10:AP27)-ROUNDDOWN($K28*AP$5/100,0)<-AP$6,-AP$6-SUM(AP$10:AP27),-ROUNDDOWN($K28*AP$5/100,0)),0) -> 0 | AQ28: =IF(AND($A28>=AQ$8,$A28<=AQ$9),IF(SUM(AQ$10:AQ27)-ROUNDDOWN($K28*AQ$5/100,0)<-AQ$6,-AQ$6-SUM(AQ$10:AQ27),-ROUNDDOWN($K28*AQ$5/100,0)),0) -> 0 | AR28: =IF(AND($A28>=AR$8,$A28<=AR$9),IF(SUM(AR$10:AR27)-ROUNDDOWN($K28*AR$5/100,0)<-AR$6,-AR$6-SUM(AR$10:AR27),-ROUNDDOWN($K28*AR$5/100,0)),0) -> 0 | AS28: =IF(SUMIFS(AS$10:AS27,$A$10:$A27,$A28)-ROUNDDOWN($K28*$S28/100,0)<-$S28*1000,-$S28*1000-SUMIFS(AS$10:AS27,$A$10:$A27,$A28),-ROUNDDOWN($K28*$S28/100,0)) -> 0 | AT28: =IF(AND(X28="○",$A28>=AT$8,$A28<=AT$9,K28>=3980),IF(SUM(AT$10:AT27)-ROUNDDOWN($K28*AT$5/100,0)<-AT$6,-AT$6-SUM(AT$10:AT27),-ROUNDDOWN($K28*AT$5/100,0)),0) -> 0 | AU28: =IF(O28="○",IF(SUM(AU$10:AU27)-ROUNDDOWN($K28*AU$5/100,0)<-AU$6,-AU$6-SUM(AU$10:AU27),-ROUNDDOWN($K28*AU$5/100,0)),0) -> 0 | AV28: =IF(P28="○",IF(SUM(AV$10:AV27)-ROUNDDOWN($K28*AV$5/100,0)<-AV$6,-AV$6-SUM(AV$10:AV27),-ROUNDDOWN($K28*AV$5/100,0)),0) -> 0 | AW28: =IF(Q28="○",IF(SUM(AW$10:AW27)-ROUNDDOWN($K28*AW$5/100,0)<-AW$6,-AW$6-SUM(AW$10:AW27),-ROUNDDOWN($K28*AW$5/100,0)),0) -> 0 | AX28: =IF(R28="○",IF(SUM(AX$10:AX27)-ROUNDDOWN($K28*AX$5/100,0)<-AX$6,-AX$6-SUM(AX$10:AX27),-ROUNDDOWN($K28*AX$5/100,0)),0) -> 0 | AY28: 0 | AZ28: =-ROUNDDOWN($K28*AY28/100,0) -> 0 | BA28: =-ROUNDDOWN($K28*AI28/100,0) -> 0 | BC28: =-ROUNDDOWN($K28*BB28/100,0) -> 0 | BD28: 0 | BE28: =-ROUNDDOWN($K28*BD28/100,0) -> 0 | BF28: 0 | BG28: =-ROUNDDOWN($K28*BF28/100,0) -> 0 | BH28: 0 | BI28: =-ROUNDDOWN($K28*BH28/100,0) -> 0 | BJ28: =IF(AND(BJ$7="○",$A28>=BJ$8,$A28<=BJ$9),IF(SUM(BJ$10:BJ27)-ROUNDDOWN($M28*BJ$5/100,0)<-BJ$6,-BJ$6-SUM(BJ$10:BJ27),-ROUNDDOWN($M28*BJ$5/100,0)),0) -> 0 | BK28: =IF(AND(BK$7="○",$A28>=BK$8,$A28<=BK$9),IF(SUM(BK$10:BK27)-ROUNDDOWN($L28*BK$5/100,0)<-BK$6,-BK$6-SUM(BK$10:BK27),-ROUNDDOWN($L28*BK$5/100,0)),0) -> 0 | BL28: =IF(AND(BL$7="○",$A28>=BL$8,$A28<=BL$9),IF(SUM(BL$10:BL27)-ROUNDDOWN($L28*BL$5/100,0)<-BL$6,-BL$6-SUM(BL$10:BL27),-ROUNDDOWN($L28*BL$5/100,0)),0) -> 0 | BM28: =IF(AND(BM$7="○",$A28>=BM$8,$A28<=BM$9),IF(SUM(BM$10:BM27)-ROUNDDOWN($M28*BM$5/100,0)<-BM$6,-BM$6-SUM(BM$10:BM27),-ROUNDDOWN($M28*BM$5/100,0)),0) -> 0 | BN28: =IF(AND(BN$7="○",$A28>=BN$8,$A28<=BN$9),IF(SUM(BN$10:BN27)-ROUNDDOWN($M28*BN$5/100,0)<-BN$6,-BN$6-SUM(BN$10:BN27),-ROUNDDOWN($M28*BN$5/100,0)),0) -> 0 | BO28: =IF(AND(BO$7="○",$A28>=BO$8,$A28<=BO$9),IF(SUM(BO$10:BO27)-ROUNDDOWN($M28*BO$5/100,0)<-BO$6,-BO$6-SUM(BO$10:BO27),-ROUNDDOWN($M28*BO$5/100,0)),0) -> 0 | BP28: =IF(AND(BP$7="○",$A28>=BP$8,$A28<=BP$9),IF(SUM(BP$10:BP27)-ROUNDDOWN($M28*BP$5/100,0)<-BP$6,-BP$6-SUM(BP$10:BP27),-ROUNDDOWN($M28*BP$5/100,0)),0) -> 0 | BQ28: =IF(AND(BQ$7="○",$A28>=BQ$8,$A28<=BQ$9),IF(SUM(BQ$10:BQ27)-ROUNDDOWN($L28*BQ$5/100,0)<-BQ$6,-BQ$6-SUM(BQ$10:BQ27),-ROUNDDOWN($L28*BQ$5/100,0)),0) -> 0 | BR28: =IF(AND(BR$7="○",$A28>=BR$8,$A28<=BR$9),IF(SUM(BR$10:BR27)-ROUNDDOWN($M28*BR$5/100,0)<-BR$6,-BR$6-SUM(BR$10:BR27),-ROUNDDOWN($M28*BR$5/100,0)),0) -> 0 | BS28: =IF(AND(BS$7="○",$A28>=BS$8,$A28<=BS$9),IF(SUM(BS$10:BS27)-ROUNDDOWN($M28*BS$5/100,0)<-BS$6,-BS$6-SUM(BS$10:BS27),-ROUNDDOWN($M28*BS$5/100,0)),0) -> 0 | BT28: =IF(AND(BT$7="○",$A28>=BT$8,$A28<=BT$9),IF(SUM(BT$10:BT27)-ROUNDDOWN($M28*BT$5/100,0)<-BT$6,-BT$6-SUM(BT$10:BT27),-ROUNDDOWN($M28*BT$5/100,0)),0) -> 0 | BU28: =IF(AND(BU$7="○",$A28>=BU$8,$A28<=BU$9),IF(SUM(BU$10:BU27)-ROUNDDOWN($M28*BU$5/100,0)<-BU$6,-BU$6-SUM(BU$10:BU27),-ROUNDDOWN($M28*BU$5/100,0)),0) -> 0 | BV28: =IF(AND(BV$7="○",$A28>=BV$8,$A28<=BV$9),IF(SUM(BV$10:BV27)-ROUNDDOWN($M28*BV$5/100,0)<-BV$6,-BV$6-SUM(BV$10:BV27),-ROUNDDOWN($M28*BV$5/100,0)),0) -> 0 | BW28: =IF(AND(BW$7="○",$A28>=BW$8,$A28<=BW$9),IF(SUM(BW$10:BW27)-ROUNDDOWN($M28*BW$5/100,0)<-BW$6,-BW$6-SUM(BW$10:BW27),-ROUNDDOWN($M28*BW$5/100,0)),0) -> 0 | BX28: =IF(AND(T28="○",$A28>=BX$8,$A28<=BX$9),IF(SUM(BX$10:BX27)-ROUNDDOWN($K28*BX$5/100,0)<-BX$6,-BX$6-SUM(BX$10:BX27),-ROUNDDOWN($K28*BX$5/100,0)),0) -> 0 | BY28: =IF(AND(U28="○",$A28>=BY$8,$A28<=BY$9),IF(SUM(BY$10:BY27)-ROUNDDOWN($K28*BY$5/100,0)<-BY$6,-BY$6-SUM(BY$10:BY27),-ROUNDDOWN($K28*BY$5/100,0)),0) -> 0 | BZ28: =IF(AND(V28="○",$A28>=BZ$8,$A28<=BZ$9),IF(SUM(BZ$10:BZ27)-ROUNDDOWN($K28*BZ$5/100,0)<-BZ$6,-BZ$6-SUM(BZ$10:BZ27),-ROUNDDOWN($K28*BZ$5/100,0)),0) -> 0 | CA28: =IF(AND(W28="○",$A28>=CA$8,$A28<=CA$9),IF(SUM(CA$10:CA27)-ROUNDDOWN($K28*CA$5/100,0)<-CA$6,-CA$6-SUM(CA$10:CA27),-ROUNDDOWN($K28*CA$5/100,0)),0) -> 0 | CG28: =+SUM(AJ28:CF28,BC28,BE28,AZ28,BA28,BG28,BI28) -> 0 | CH28: =+CG28+N28 -> 0 | CI28: =IFERROR(ROUNDDOWN((CH28/G28),0),0) -> 0 | CO28: =IFERROR(CN28-CI28,0) -> 0 | CP28: =IFERROR(CN28/CI28,0) -> 0 | CR28: =+CO28*G28 -> 0 | CT28: =INDEX([2]マスタ!$A:$A,MATCH(D28,[2]マスタ!$C:$C,0)) -> #N/A | CU28: =IFERROR(TEXT(TODAY(),"yyyymmdd")&"_"&ROUNDDOWN(H28+I28,0)&"-"&ROUNDDOWN(CI28,0),"") -> 20260620_0-0
G29: 1 | H29: =+F29*G29 -> 0 | K29: =+ROUNDDOWN((H29+I29+J29)/100,0)*100 -> 0 | L29: =+ROUNDDOWN((H29+I29)/1.1/100,0)*100 -> 0 | M29: =+ROUNDDOWN((H29+I29)/1.1/200,0)*200 -> 0 | N29: =+H29+I29+J29 -> 0 | O29: =IF(OR(WEEKDAY($A29,2)=2,WEEKDAY($A29,2)=4),"○","✕") -> ✕ | P29: =+IF(MOD(TEXT($A29,"DD"),5)=0,"○","✕") -> ○ | Q29: =+IF((TEXT(A29,"DD")+0)=1,"○","✕") -> ✕ | R29: =+IF((TEXT($A29,"DD")+0)=18,"○","✕") -> ✕ | S29: 0 | T29: ✕ | U29: ✕ | V29: ✕ | W29: ✕ | X29: ○ | Y29: ✕ | Z29: ✕ | AA29: ✕ | AB29: ✕ | AC29: ✕ | AD29: =+IF(ISERROR(VLOOKUP($B29,AD$10:AD28,1,0)),IF(AND($N29>=1000,$A29>=AO$8,$A29<=AO$9),$B29,""),"") | AE29: =+IF(ISERROR(VLOOKUP($B29,AE$10:AE28,1,0)),IF(AND($N29>=1000,$A29>=AP$8,$A29<=AP$9),$B29,""),"") | AF29: =+IF(ISERROR(VLOOKUP($B29,AF$10:AF28,1,0)),IF(AND($N29>=1000,$A29>=AQ$8,$A29<=AQ$9),$B29,""),"") | AG29: =+IF(ISERROR(VLOOKUP($B29,AG$10:AG28,1,0)),IF(AND($N29>=1000,$A29>=AR$8,$A29<=AR$9),$B29,""),"") | AI29: 0 | AJ29: =IF(AND(AJ$7="○",$A29>=AJ$8,$A29<=AJ$9),IF(SUM(AJ$10:AJ28)-ROUNDDOWN($K29*AJ$5/100,0)<-AJ$6,-AJ$6-SUM(AJ$10:AJ28),-ROUNDDOWN($K29*AJ$5/100,0)),0) -> 0 | AK29: =IF(AND(AK$7="○",$A29>=AK$8,$A29<=AK$9),IF(SUM(AK$10:AK28)-ROUNDDOWN($L29*AK$5/100,0)<-AK$6,-AK$6-SUM(AK$10:AK28),-ROUNDDOWN($L29*AK$5/100,0)),0) -> 0 | AL29: =IF(AND(AL$7="○",$A29>=AL$8,$A29<=AL$9),IF(SUM(AL$10:AL28)-ROUNDDOWN($N29*AL$5/100,0)<-AL$6,-AL$6-SUM(AL$10:AL28),-ROUNDDOWN($N29*AL$5/100,0)),0) -> 0 | AM29: =IF(AND(AM$7="○",$A29>=AM$8,$A29<=AM$9),IF(SUM(AM$10:AM28)-ROUNDDOWN($L29*AM$5/100,0)<-AM$6,-AM$6-SUM(AM$10:AM28),-ROUNDDOWN($L29*AM$5/100,0)),0) -> 0 | AN29: =IF(AND(AN$7="○",$A29>=AN$8,$A29<=AN$9),IF(SUM(AN$10:AN28)-ROUNDDOWN($M29*AN$5/100,0)<-AN$6,-AN$6-SUM(AN$10:AN28),-ROUNDDOWN($M29*AN$5/100,0)),0) -> 0 | AO29: =IF(AND($A29>=AO$8,$A29<=AO$9),IF(SUM(AO$10:AO28)-ROUNDDOWN($K29*AO$5/100,0)<-AO$6,-AO$6-SUM(AO$10:AO28),-ROUNDDOWN($K29*AO$5/100,0)),0) -> 0 | AP29: =IF(AND($A29>=AP$8,$A29<=AP$9),IF(SUM(AP$10:AP28)-ROUNDDOWN($K29*AP$5/100,0)<-AP$6,-AP$6-SUM(AP$10:AP28),-ROUNDDOWN($K29*AP$5/100,0)),0) -> 0 | AQ29: =IF(AND($A29>=AQ$8,$A29<=AQ$9),IF(SUM(AQ$10:AQ28)-ROUNDDOWN($K29*AQ$5/100,0)<-AQ$6,-AQ$6-SUM(AQ$10:AQ28),-ROUNDDOWN($K29*AQ$5/100,0)),0) -> 0 | AR29: =IF(AND($A29>=AR$8,$A29<=AR$9),IF(SUM(AR$10:AR28)-ROUNDDOWN($K29*AR$5/100,0)<-AR$6,-AR$6-SUM(AR$10:AR28),-ROUNDDOWN($K29*AR$5/100,0)),0) -> 0 | AS29: =IF(SUMIFS(AS$10:AS28,$A$10:$A28,$A29)-ROUNDDOWN($K29*$S29/100,0)<-$S29*1000,-$S29*1000-SUMIFS(AS$10:AS28,$A$10:$A28,$A29),-ROUNDDOWN($K29*$S29/100,0)) -> 0 | AT29: =IF(AND(X29="○",$A29>=AT$8,$A29<=AT$9,K29>=3980),IF(SUM(AT$10:AT28)-ROUNDDOWN($K29*AT$5/100,0)<-AT$6,-AT$6-SUM(AT$10:AT28),-ROUNDDOWN($K29*AT$5/100,0)),0) -> 0 | AU29: =IF(O29="○",IF(SUM(AU$10:AU28)-ROUNDDOWN($K29*AU$5/100,0)<-AU$6,-AU$6-SUM(AU$10:AU28),-ROUNDDOWN($K29*AU$5/100,0)),0) -> 0 | AV29: =IF(P29="○",IF(SUM(AV$10:AV28)-ROUNDDOWN($K29*AV$5/100,0)<-AV$6,-AV$6-SUM(AV$10:AV28),-ROUNDDOWN($K29*AV$5/100,0)),0) -> 0 | AW29: =IF(Q29="○",IF(SUM(AW$10:AW28)-ROUNDDOWN($K29*AW$5/100,0)<-AW$6,-AW$6-SUM(AW$10:AW28),-ROUNDDOWN($K29*AW$5/100,0)),0) -> 0 | AX29: =IF(R29="○",IF(SUM(AX$10:AX28)-ROUNDDOWN($K29*AX$5/100,0)<-AX$6,-AX$6-SUM(AX$10:AX28),-ROUNDDOWN($K29*AX$5/100,0)),0) -> 0 | AY29: 0 | AZ29: =-ROUNDDOWN($K29*AY29/100,0) -> 0 | BA29: =-ROUNDDOWN($K29*AI29/100,0) -> 0 | BC29: =-ROUNDDOWN($K29*BB29/100,0) -> 0 | BD29: 0 | BE29: =-ROUNDDOWN($K29*BD29/100,0) -> 0 | BF29: 0 | BG29: =-ROUNDDOWN($K29*BF29/100,0) -> 0 | BH29: 0 | BI29: =-ROUNDDOWN($K29*BH29/100,0) -> 0 | BJ29: =IF(AND(BJ$7="○",$A29>=BJ$8,$A29<=BJ$9),IF(SUM(BJ$10:BJ28)-ROUNDDOWN($M29*BJ$5/100,0)<-BJ$6,-BJ$6-SUM(BJ$10:BJ28),-ROUNDDOWN($M29*BJ$5/100,0)),0) -> 0 | BK29: =IF(AND(BK$7="○",$A29>=BK$8,$A29<=BK$9),IF(SUM(BK$10:BK28)-ROUNDDOWN($L29*BK$5/100,0)<-BK$6,-BK$6-SUM(BK$10:BK28),-ROUNDDOWN($L29*BK$5/100,0)),0) -> 0 | BL29: =IF(AND(BL$7="○",$A29>=BL$8,$A29<=BL$9),IF(SUM(BL$10:BL28)-ROUNDDOWN($L29*BL$5/100,0)<-BL$6,-BL$6-SUM(BL$10:BL28),-ROUNDDOWN($L29*BL$5/100,0)),0) -> 0 | BM29: =IF(AND(BM$7="○",$A29>=BM$8,$A29<=BM$9),IF(SUM(BM$10:BM28)-ROUNDDOWN($M29*BM$5/100,0)<-BM$6,-BM$6-SUM(BM$10:BM28),-ROUNDDOWN($M29*BM$5/100,0)),0) -> 0 | BN29: =IF(AND(BN$7="○",$A29>=BN$8,$A29<=BN$9),IF(SUM(BN$10:BN28)-ROUNDDOWN($M29*BN$5/100,0)<-BN$6,-BN$6-SUM(BN$10:BN28),-ROUNDDOWN($M29*BN$5/100,0)),0) -> 0 | BO29: =IF(AND(BO$7="○",$A29>=BO$8,$A29<=BO$9),IF(SUM(BO$10:BO28)-ROUNDDOWN($M29*BO$5/100,0)<-BO$6,-BO$6-SUM(BO$10:BO28),-ROUNDDOWN($M29*BO$5/100,0)),0) -> 0 | BP29: =IF(AND(BP$7="○",$A29>=BP$8,$A29<=BP$9),IF(SUM(BP$10:BP28)-ROUNDDOWN($M29*BP$5/100,0)<-BP$6,-BP$6-SUM(BP$10:BP28),-ROUNDDOWN($M29*BP$5/100,0)),0) -> 0 | BQ29: =IF(AND(BQ$7="○",$A29>=BQ$8,$A29<=BQ$9),IF(SUM(BQ$10:BQ28)-ROUNDDOWN($L29*BQ$5/100,0)<-BQ$6,-BQ$6-SUM(BQ$10:BQ28),-ROUNDDOWN($L29*BQ$5/100,0)),0) -> 0 | BR29: =IF(AND(BR$7="○",$A29>=BR$8,$A29<=BR$9),IF(SUM(BR$10:BR28)-ROUNDDOWN($M29*BR$5/100,0)<-BR$6,-BR$6-SUM(BR$10:BR28),-ROUNDDOWN($M29*BR$5/100,0)),0) -> 0 | BS29: =IF(AND(BS$7="○",$A29>=BS$8,$A29<=BS$9),IF(SUM(BS$10:BS28)-ROUNDDOWN($M29*BS$5/100,0)<-BS$6,-BS$6-SUM(BS$10:BS28),-ROUNDDOWN($M29*BS$5/100,0)),0) -> 0 | BT29: =IF(AND(BT$7="○",$A29>=BT$8,$A29<=BT$9),IF(SUM(BT$10:BT28)-ROUNDDOWN($M29*BT$5/100,0)<-BT$6,-BT$6-SUM(BT$10:BT28),-ROUNDDOWN($M29*BT$5/100,0)),0) -> 0 | BU29: =IF(AND(BU$7="○",$A29>=BU$8,$A29<=BU$9),IF(SUM(BU$10:BU28)-ROUNDDOWN($M29*BU$5/100,0)<-BU$6,-BU$6-SUM(BU$10:BU28),-ROUNDDOWN($M29*BU$5/100,0)),0) -> 0 | BV29: =IF(AND(BV$7="○",$A29>=BV$8,$A29<=BV$9),IF(SUM(BV$10:BV28)-ROUNDDOWN($M29*BV$5/100,0)<-BV$6,-BV$6-SUM(BV$10:BV28),-ROUNDDOWN($M29*BV$5/100,0)),0) -> 0 | BW29: =IF(AND(BW$7="○",$A29>=BW$8,$A29<=BW$9),IF(SUM(BW$10:BW28)-ROUNDDOWN($M29*BW$5/100,0)<-BW$6,-BW$6-SUM(BW$10:BW28),-ROUNDDOWN($M29*BW$5/100,0)),0) -> 0 | BX29: =IF(AND(T29="○",$A29>=BX$8,$A29<=BX$9),IF(SUM(BX$10:BX28)-ROUNDDOWN($K29*BX$5/100,0)<-BX$6,-BX$6-SUM(BX$10:BX28),-ROUNDDOWN($K29*BX$5/100,0)),0) -> 0 | BY29: =IF(AND(U29="○",$A29>=BY$8,$A29<=BY$9),IF(SUM(BY$10:BY28)-ROUNDDOWN($K29*BY$5/100,0)<-BY$6,-BY$6-SUM(BY$10:BY28),-ROUNDDOWN($K29*BY$5/100,0)),0) -> 0 | BZ29: =IF(AND(V29="○",$A29>=BZ$8,$A29<=BZ$9),IF(SUM(BZ$10:BZ28)-ROUNDDOWN($K29*BZ$5/100,0)<-BZ$6,-BZ$6-SUM(BZ$10:BZ28),-ROUNDDOWN($K29*BZ$5/100,0)),0) -> 0 | CA29: =IF(AND(W29="○",$A29>=CA$8,$A29<=CA$9),IF(SUM(CA$10:CA28)-ROUNDDOWN($K29*CA$5/100,0)<-CA$6,-CA$6-SUM(CA$10:CA28),-ROUNDDOWN($K29*CA$5/100,0)),0) -> 0 | CG29: =+SUM(AJ29:CF29,BC29,BE29,AZ29,BA29,BG29,BI29) -> 0 | CH29: =+CG29+N29 -> 0 | CI29: =IFERROR(ROUNDDOWN((CH29/G29),0),0) -> 0 | CO29: =IFERROR(CN29-CI29,0) -> 0 | CP29: =IFERROR(CN29/CI29,0) -> 0 | CR29: =+CO29*G29 -> 0 | CT29: =INDEX([2]マスタ!$A:$A,MATCH(D29,[2]マスタ!$C:$C,0)) -> #N/A | CU29: =IFERROR(TEXT(TODAY(),"yyyymmdd")&"_"&ROUNDDOWN(H29+I29,0)&"-"&ROUNDDOWN(CI29,0),"") -> 20260620_0-0
G30: 1 | H30: =+F30*G30 -> 0 | K30: =+ROUNDDOWN((H30+I30+J30)/100,0)*100 -> 0 | L30: =+ROUNDDOWN((H30+I30)/1.1/100,0)*100 -> 0 | M30: =+ROUNDDOWN((H30+I30)/1.1/200,0)*200 -> 0 | N30: =+H30+I30+J30 -> 0 | O30: =IF(OR(WEEKDAY($A30,2)=2,WEEKDAY($A30,2)=4),"○","✕") -> ✕ | P30: =+IF(MOD(TEXT($A30,"DD"),5)=0,"○","✕") -> ○ | Q30: =+IF((TEXT(A30,"DD")+0)=1,"○","✕") -> ✕ | R30: =+IF((TEXT($A30,"DD")+0)=18,"○","✕") -> ✕ | S30: 0 | T30: ✕ | U30: ✕ | V30: ✕ | W30: ✕ | X30: ○ | Y30: ✕ | Z30: ✕ | AA30: ✕ | AB30: ✕ | AC30: ✕ | AD30: =+IF(ISERROR(VLOOKUP($B30,AD$10:AD29,1,0)),IF(AND($N30>=1000,$A30>=AO$8,$A30<=AO$9),$B30,""),"") | AE30: =+IF(ISERROR(VLOOKUP($B30,AE$10:AE29,1,0)),IF(AND($N30>=1000,$A30>=AP$8,$A30<=AP$9),$B30,""),"") | AF30: =+IF(ISERROR(VLOOKUP($B30,AF$10:AF29,1,0)),IF(AND($N30>=1000,$A30>=AQ$8,$A30<=AQ$9),$B30,""),"") | AG30: =+IF(ISERROR(VLOOKUP($B30,AG$10:AG29,1,0)),IF(AND($N30>=1000,$A30>=AR$8,$A30<=AR$9),$B30,""),"") | AI30: 0 | AJ30: =IF(AND(AJ$7="○",$A30>=AJ$8,$A30<=AJ$9),IF(SUM(AJ$10:AJ29)-ROUNDDOWN($K30*AJ$5/100,0)<-AJ$6,-AJ$6-SUM(AJ$10:AJ29),-ROUNDDOWN($K30*AJ$5/100,0)),0) -> 0 | AK30: =IF(AND(AK$7="○",$A30>=AK$8,$A30<=AK$9),IF(SUM(AK$10:AK29)-ROUNDDOWN($L30*AK$5/100,0)<-AK$6,-AK$6-SUM(AK$10:AK29),-ROUNDDOWN($L30*AK$5/100,0)),0) -> 0 | AL30: =IF(AND(AL$7="○",$A30>=AL$8,$A30<=AL$9),IF(SUM(AL$10:AL29)-ROUNDDOWN($N30*AL$5/100,0)<-AL$6,-AL$6-SUM(AL$10:AL29),-ROUNDDOWN($N30*AL$5/100,0)),0) -> 0 | AM30: =IF(AND(AM$7="○",$A30>=AM$8,$A30<=AM$9),IF(SUM(AM$10:AM29)-ROUNDDOWN($L30*AM$5/100,0)<-AM$6,-AM$6-SUM(AM$10:AM29),-ROUNDDOWN($L30*AM$5/100,0)),0) -> 0 | AN30: =IF(AND(AN$7="○",$A30>=AN$8,$A30<=AN$9),IF(SUM(AN$10:AN29)-ROUNDDOWN($M30*AN$5/100,0)<-AN$6,-AN$6-SUM(AN$10:AN29),-ROUNDDOWN($M30*AN$5/100,0)),0) -> 0 | AO30: =IF(AND($A30>=AO$8,$A30<=AO$9),IF(SUM(AO$10:AO29)-ROUNDDOWN($K30*AO$5/100,0)<-AO$6,-AO$6-SUM(AO$10:AO29),-ROUNDDOWN($K30*AO$5/100,0)),0) -> 0 | AP30: =IF(AND($A30>=AP$8,$A30<=AP$9),IF(SUM(AP$10:AP29)-ROUNDDOWN($K30*AP$5/100,0)<-AP$6,-AP$6-SUM(AP$10:AP29),-ROUNDDOWN($K30*AP$5/100,0)),0) -> 0 | AQ30: =IF(AND($A30>=AQ$8,$A30<=AQ$9),IF(SUM(AQ$10:AQ29)-ROUNDDOWN($K30*AQ$5/100,0)<-AQ$6,-AQ$6-SUM(AQ$10:AQ29),-ROUNDDOWN($K30*AQ$5/100,0)),0) -> 0 | AR30: =IF(AND($A30>=AR$8,$A30<=AR$9),IF(SUM(AR$10:AR29)-ROUNDDOWN($K30*AR$5/100,0)<-AR$6,-AR$6-SUM(AR$10:AR29),-ROUNDDOWN($K30*AR$5/100,0)),0) -> 0 | AS30: =IF(SUMIFS(AS$10:AS29,$A$10:$A29,$A30)-ROUNDDOWN($K30*$S30/100,0)<-$S30*1000,-$S30*1000-SUMIFS(AS$10:AS29,$A$10:$A29,$A30),-ROUNDDOWN($K30*$S30/100,0)) -> 0 | AT30: =IF(AND(X30="○",$A30>=AT$8,$A30<=AT$9,K30>=3980),IF(SUM(AT$10:AT29)-ROUNDDOWN($K30*AT$5/100,0)<-AT$6,-AT$6-SUM(AT$10:AT29),-ROUNDDOWN($K30*AT$5/100,0)),0) -> 0 | AU30: =IF(O30="○",IF(SUM(AU$10:AU29)-ROUNDDOWN($K30*AU$5/100,0)<-AU$6,-AU$6-SUM(AU$10:AU29),-ROUNDDOWN($K30*AU$5/100,0)),0) -> 0 | AV30: =IF(P30="○",IF(SUM(AV$10:AV29)-ROUNDDOWN($K30*AV$5/100,0)<-AV$6,-AV$6-SUM(AV$10:AV29),-ROUNDDOWN($K30*AV$5/100,0)),0) -> 0 | AW30: =IF(Q30="○",IF(SUM(AW$10:AW29)-ROUNDDOWN($K30*AW$5/100,0)<-AW$6,-AW$6-SUM(AW$10:AW29),-ROUNDDOWN($K30*AW$5/100,0)),0) -> 0 | AX30: =IF(R30="○",IF(SUM(AX$10:AX29)-ROUNDDOWN($K30*AX$5/100,0)<-AX$6,-AX$6-SUM(AX$10:AX29),-ROUNDDOWN($K30*AX$5/100,0)),0) -> 0 | AY30: 0 | AZ30: =-ROUNDDOWN($K30*AY30/100,0) -> 0 | BA30: =-ROUNDDOWN($K30*AI30/100,0) -> 0 | BC30: =-ROUNDDOWN($K30*BB30/100,0) -> 0 | BD30: 0 | BE30: =-ROUNDDOWN($K30*BD30/100,0) -> 0 | BF30: 0 | BG30: =-ROUNDDOWN($K30*BF30/100,0) -> 0 | BH30: 0 | BI30: =-ROUNDDOWN($K30*BH30/100,0) -> 0 | BJ30: =IF(AND(BJ$7="○",$A30>=BJ$8,$A30<=BJ$9),IF(SUM(BJ$10:BJ29)-ROUNDDOWN($M30*BJ$5/100,0)<-BJ$6,-BJ$6-SUM(BJ$10:BJ29),-ROUNDDOWN($M30*BJ$5/100,0)),0) -> 0 | BK30: =IF(AND(BK$7="○",$A30>=BK$8,$A30<=BK$9),IF(SUM(BK$10:BK29)-ROUNDDOWN($L30*BK$5/100,0)<-BK$6,-BK$6-SUM(BK$10:BK29),-ROUNDDOWN($L30*BK$5/100,0)),0) -> 0 | BL30: =IF(AND(BL$7="○",$A30>=BL$8,$A30<=BL$9),IF(SUM(BL$10:BL29)-ROUNDDOWN($L30*BL$5/100,0)<-BL$6,-BL$6-SUM(BL$10:BL29),-ROUNDDOWN($L30*BL$5/100,0)),0) -> 0 | BM30: =IF(AND(BM$7="○",$A30>=BM$8,$A30<=BM$9),IF(SUM(BM$10:BM29)-ROUNDDOWN($M30*BM$5/100,0)<-BM$6,-BM$6-SUM(BM$10:BM29),-ROUNDDOWN($M30*BM$5/100,0)),0) -> 0 | BN30: =IF(AND(BN$7="○",$A30>=BN$8,$A30<=BN$9),IF(SUM(BN$10:BN29)-ROUNDDOWN($M30*BN$5/100,0)<-BN$6,-BN$6-SUM(BN$10:BN29),-ROUNDDOWN($M30*BN$5/100,0)),0) -> 0 | BO30: =IF(AND(BO$7="○",$A30>=BO$8,$A30<=BO$9),IF(SUM(BO$10:BO29)-ROUNDDOWN($M30*BO$5/100,0)<-BO$6,-BO$6-SUM(BO$10:BO29),-ROUNDDOWN($M30*BO$5/100,0)),0) -> 0 | BP30: =IF(AND(BP$7="○",$A30>=BP$8,$A30<=BP$9),IF(SUM(BP$10:BP29)-ROUNDDOWN($M30*BP$5/100,0)<-BP$6,-BP$6-SUM(BP$10:BP29),-ROUNDDOWN($M30*BP$5/100,0)),0) -> 0 | BQ30: =IF(AND(BQ$7="○",$A30>=BQ$8,$A30<=BQ$9),IF(SUM(BQ$10:BQ29)-ROUNDDOWN($L30*BQ$5/100,0)<-BQ$6,-BQ$6-SUM(BQ$10:BQ29),-ROUNDDOWN($L30*BQ$5/100,0)),0) -> 0 | BR30: =IF(AND(BR$7="○",$A30>=BR$8,$A30<=BR$9),IF(SUM(BR$10:BR29)-ROUNDDOWN($M30*BR$5/100,0)<-BR$6,-BR$6-SUM(BR$10:BR29),-ROUNDDOWN($M30*BR$5/100,0)),0) -> 0 | BS30: =IF(AND(BS$7="○",$A30>=BS$8,$A30<=BS$9),IF(SUM(BS$10:BS29)-ROUNDDOWN($M30*BS$5/100,0)<-BS$6,-BS$6-SUM(BS$10:BS29),-ROUNDDOWN($M30*BS$5/100,0)),0) -> 0 | BT30: =IF(AND(BT$7="○",$A30>=BT$8,$A30<=BT$9),IF(SUM(BT$10:BT29)-ROUNDDOWN($M30*BT$5/100,0)<-BT$6,-BT$6-SUM(BT$10:BT29),-ROUNDDOWN($M30*BT$5/100,0)),0) -> 0 | BU30: =IF(AND(BU$7="○",$A30>=BU$8,$A30<=BU$9),IF(SUM(BU$10:BU29)-ROUNDDOWN($M30*BU$5/100,0)<-BU$6,-BU$6-SUM(BU$10:BU29),-ROUNDDOWN($M30*BU$5/100,0)),0) -> 0 | BV30: =IF(AND(BV$7="○",$A30>=BV$8,$A30<=BV$9),IF(SUM(BV$10:BV29)-ROUNDDOWN($M30*BV$5/100,0)<-BV$6,-BV$6-SUM(BV$10:BV29),-ROUNDDOWN($M30*BV$5/100,0)),0) -> 0 | BW30: =IF(AND(BW$7="○",$A30>=BW$8,$A30<=BW$9),IF(SUM(BW$10:BW29)-ROUNDDOWN($M30*BW$5/100,0)<-BW$6,-BW$6-SUM(BW$10:BW29),-ROUNDDOWN($M30*BW$5/100,0)),0) -> 0 | BX30: =IF(AND(T30="○",$A30>=BX$8,$A30<=BX$9),IF(SUM(BX$10:BX29)-ROUNDDOWN($K30*BX$5/100,0)<-BX$6,-BX$6-SUM(BX$10:BX29),-ROUNDDOWN($K30*BX$5/100,0)),0) -> 0 | BY30: =IF(AND(U30="○",$A30>=BY$8,$A30<=BY$9),IF(SUM(BY$10:BY29)-ROUNDDOWN($K30*BY$5/100,0)<-BY$6,-BY$6-SUM(BY$10:BY29),-ROUNDDOWN($K30*BY$5/100,0)),0) -> 0 | BZ30: =IF(AND(V30="○",$A30>=BZ$8,$A30<=BZ$9),IF(SUM(BZ$10:BZ29)-ROUNDDOWN($K30*BZ$5/100,0)<-BZ$6,-BZ$6-SUM(BZ$10:BZ29),-ROUNDDOWN($K30*BZ$5/100,0)),0) -> 0 | CA30: =IF(AND(W30="○",$A30>=CA$8,$A30<=CA$9),IF(SUM(CA$10:CA29)-ROUNDDOWN($K30*CA$5/100,0)<-CA$6,-CA$6-SUM(CA$10:CA29),-ROUNDDOWN($K30*CA$5/100,0)),0) -> 0 | CG30: =+SUM(AJ30:CF30,BC30,BE30,AZ30,BA30,BG30,BI30) -> 0 | CH30: =+CG30+N30 -> 0 | CI30: =IFERROR(ROUNDDOWN((CH30/G30),0),0) -> 0 | CO30: =IFERROR(CN30-CI30,0) -> 0 | CP30: =IFERROR(CN30/CI30,0) -> 0 | CR30: =+CO30*G30 -> 0 | CT30: =INDEX([2]マスタ!$A:$A,MATCH(D30,[2]マスタ!$C:$C,0)) -> #N/A | CU30: =IFERROR(TEXT(TODAY(),"yyyymmdd")&"_"&ROUNDDOWN(H30+I30,0)&"-"&ROUNDDOWN(CI30,0),"") -> 20260620_0-0
G31: 1 | H31: =+F31*G31 -> 0 | K31: =+ROUNDDOWN((H31+I31+J31)/100,0)*100 -> 0 | L31: =+ROUNDDOWN((H31+I31)/1.1/100,0)*100 -> 0 | M31: =+ROUNDDOWN((H31+I31)/1.1/200,0)*200 -> 0 | N31: =+H31+I31+J31 -> 0 | O31: =IF(OR(WEEKDAY($A31,2)=2,WEEKDAY($A31,2)=4),"○","✕") -> ✕ | P31: =+IF(MOD(TEXT($A31,"DD"),5)=0,"○","✕") -> ○ | Q31: =+IF((TEXT(A31,"DD")+0)=1,"○","✕") -> ✕ | R31: =+IF((TEXT($A31,"DD")+0)=18,"○","✕") -> ✕ | S31: 0 | T31: ✕ | U31: ✕ | V31: ✕ | W31: ✕ | X31: ○ | Y31: ✕ | Z31: ✕ | AA31: ✕ | AB31: ✕ | AC31: ✕ | AD31: =+IF(ISERROR(VLOOKUP($B31,AD$10:AD30,1,0)),IF(AND($N31>=1000,$A31>=AO$8,$A31<=AO$9),$B31,""),"") | AE31: =+IF(ISERROR(VLOOKUP($B31,AE$10:AE30,1,0)),IF(AND($N31>=1000,$A31>=AP$8,$A31<=AP$9),$B31,""),"") | AF31: =+IF(ISERROR(VLOOKUP($B31,AF$10:AF30,1,0)),IF(AND($N31>=1000,$A31>=AQ$8,$A31<=AQ$9),$B31,""),"") | AG31: =+IF(ISERROR(VLOOKUP($B31,AG$10:AG30,1,0)),IF(AND($N31>=1000,$A31>=AR$8,$A31<=AR$9),$B31,""),"") | AI31: 0 | AJ31: =IF(AND(AJ$7="○",$A31>=AJ$8,$A31<=AJ$9),IF(SUM(AJ$10:AJ30)-ROUNDDOWN($K31*AJ$5/100,0)<-AJ$6,-AJ$6-SUM(AJ$10:AJ30),-ROUNDDOWN($K31*AJ$5/100,0)),0) -> 0 | AK31: =IF(AND(AK$7="○",$A31>=AK$8,$A31<=AK$9),IF(SUM(AK$10:AK30)-ROUNDDOWN($L31*AK$5/100,0)<-AK$6,-AK$6-SUM(AK$10:AK30),-ROUNDDOWN($L31*AK$5/100,0)),0) -> 0 | AL31: =IF(AND(AL$7="○",$A31>=AL$8,$A31<=AL$9),IF(SUM(AL$10:AL30)-ROUNDDOWN($N31*AL$5/100,0)<-AL$6,-AL$6-SUM(AL$10:AL30),-ROUNDDOWN($N31*AL$5/100,0)),0) -> 0 | AM31: =IF(AND(AM$7="○",$A31>=AM$8,$A31<=AM$9),IF(SUM(AM$10:AM30)-ROUNDDOWN($L31*AM$5/100,0)<-AM$6,-AM$6-SUM(AM$10:AM30),-ROUNDDOWN($L31*AM$5/100,0)),0) -> 0 | AN31: =IF(AND(AN$7="○",$A31>=AN$8,$A31<=AN$9),IF(SUM(AN$10:AN30)-ROUNDDOWN($M31*AN$5/100,0)<-AN$6,-AN$6-SUM(AN$10:AN30),-ROUNDDOWN($M31*AN$5/100,0)),0) -> 0 | AO31: =IF(AND($A31>=AO$8,$A31<=AO$9),IF(SUM(AO$10:AO30)-ROUNDDOWN($K31*AO$5/100,0)<-AO$6,-AO$6-SUM(AO$10:AO30),-ROUNDDOWN($K31*AO$5/100,0)),0) -> 0 | AP31: =IF(AND($A31>=AP$8,$A31<=AP$9),IF(SUM(AP$10:AP30)-ROUNDDOWN($K31*AP$5/100,0)<-AP$6,-AP$6-SUM(AP$10:AP30),-ROUNDDOWN($K31*AP$5/100,0)),0) -> 0 | AQ31: =IF(AND($A31>=AQ$8,$A31<=AQ$9),IF(SUM(AQ$10:AQ30)-ROUNDDOWN($K31*AQ$5/100,0)<-AQ$6,-AQ$6-SUM(AQ$10:AQ30),-ROUNDDOWN($K31*AQ$5/100,0)),0) -> 0 | AR31: =IF(AND($A31>=AR$8,$A31<=AR$9),IF(SUM(AR$10:AR30)-ROUNDDOWN($K31*AR$5/100,0)<-AR$6,-AR$6-SUM(AR$10:AR30),-ROUNDDOWN($K31*AR$5/100,0)),0) -> 0 | AS31: =IF(SUMIFS(AS$10:AS30,$A$10:$A30,$A31)-ROUNDDOWN($K31*$S31/100,0)<-$S31*1000,-$S31*1000-SUMIFS(AS$10:AS30,$A$10:$A30,$A31),-ROUNDDOWN($K31*$S31/100,0)) -> 0 | AT31: =IF(AND(X31="○",$A31>=AT$8,$A31<=AT$9,K31>=3980),IF(SUM(AT$10:AT30)-ROUNDDOWN($K31*AT$5/100,0)<-AT$6,-AT$6-SUM(AT$10:AT30),-ROUNDDOWN($K31*AT$5/100,0)),0) -> 0 | AU31: =IF(O31="○",IF(SUM(AU$10:AU30)-ROUNDDOWN($K31*AU$5/100,0)<-AU$6,-AU$6-SUM(AU$10:AU30),-ROUNDDOWN($K31*AU$5/100,0)),0) -> 0 | AV31: =IF(P31="○",IF(SUM(AV$10:AV30)-ROUNDDOWN($K31*AV$5/100,0)<-AV$6,-AV$6-SUM(AV$10:AV30),-ROUNDDOWN($K31*AV$5/100,0)),0) -> 0 | AW31: =IF(Q31="○",IF(SUM(AW$10:AW30)-ROUNDDOWN($K31*AW$5/100,0)<-AW$6,-AW$6-SUM(AW$10:AW30),-ROUNDDOWN($K31*AW$5/100,0)),0) -> 0 | AX31: =IF(R31="○",IF(SUM(AX$10:AX30)-ROUNDDOWN($K31*AX$5/100,0)<-AX$6,-AX$6-SUM(AX$10:AX30),-ROUNDDOWN($K31*AX$5/100,0)),0) -> 0 | AY31: 0 | AZ31: =-ROUNDDOWN($K31*AY31/100,0) -> 0 | BA31: =-ROUNDDOWN($K31*AI31/100,0) -> 0 | BC31: =-ROUNDDOWN($K31*BB31/100,0) -> 0 | BD31: 0 | BE31: =-ROUNDDOWN($K31*BD31/100,0) -> 0 | BF31: 0 | BG31: =-ROUNDDOWN($K31*BF31/100,0) -> 0 | BH31: 0 | BI31: =-ROUNDDOWN($K31*BH31/100,0) -> 0 | BJ31: =IF(AND(BJ$7="○",$A31>=BJ$8,$A31<=BJ$9),IF(SUM(BJ$10:BJ30)-ROUNDDOWN($M31*BJ$5/100,0)<-BJ$6,-BJ$6-SUM(BJ$10:BJ30),-ROUNDDOWN($M31*BJ$5/100,0)),0) -> 0 | BK31: =IF(AND(BK$7="○",$A31>=BK$8,$A31<=BK$9),IF(SUM(BK$10:BK30)-ROUNDDOWN($L31*BK$5/100,0)<-BK$6,-BK$6-SUM(BK$10:BK30),-ROUNDDOWN($L31*BK$5/100,0)),0) -> 0 | BL31: =IF(AND(BL$7="○",$A31>=BL$8,$A31<=BL$9),IF(SUM(BL$10:BL30)-ROUNDDOWN($L31*BL$5/100,0)<-BL$6,-BL$6-SUM(BL$10:BL30),-ROUNDDOWN($L31*BL$5/100,0)),0) -> 0 | BM31: =IF(AND(BM$7="○",$A31>=BM$8,$A31<=BM$9),IF(SUM(BM$10:BM30)-ROUNDDOWN($M31*BM$5/100,0)<-BM$6,-BM$6-SUM(BM$10:BM30),-ROUNDDOWN($M31*BM$5/100,0)),0) -> 0 | BN31: =IF(AND(BN$7="○",$A31>=BN$8,$A31<=BN$9),IF(SUM(BN$10:BN30)-ROUNDDOWN($M31*BN$5/100,0)<-BN$6,-BN$6-SUM(BN$10:BN30),-ROUNDDOWN($M31*BN$5/100,0)),0) -> 0 | BO31: =IF(AND(BO$7="○",$A31>=BO$8,$A31<=BO$9),IF(SUM(BO$10:BO30)-ROUNDDOWN($M31*BO$5/100,0)<-BO$6,-BO$6-SUM(BO$10:BO30),-ROUNDDOWN($M31*BO$5/100,0)),0) -> 0 | BP31: =IF(AND(BP$7="○",$A31>=BP$8,$A31<=BP$9),IF(SUM(BP$10:BP30)-ROUNDDOWN($M31*BP$5/100,0)<-BP$6,-BP$6-SUM(BP$10:BP30),-ROUNDDOWN($M31*BP$5/100,0)),0) -> 0 | BQ31: =IF(AND(BQ$7="○",$A31>=BQ$8,$A31<=BQ$9),IF(SUM(BQ$10:BQ30)-ROUNDDOWN($L31*BQ$5/100,0)<-BQ$6,-BQ$6-SUM(BQ$10:BQ30),-ROUNDDOWN($L31*BQ$5/100,0)),0) -> 0 | BR31: =IF(AND(BR$7="○",$A31>=BR$8,$A31<=BR$9),IF(SUM(BR$10:BR30)-ROUNDDOWN($M31*BR$5/100,0)<-BR$6,-BR$6-SUM(BR$10:BR30),-ROUNDDOWN($M31*BR$5/100,0)),0) -> 0 | BS31: =IF(AND(BS$7="○",$A31>=BS$8,$A31<=BS$9),IF(SUM(BS$10:BS30)-ROUNDDOWN($M31*BS$5/100,0)<-BS$6,-BS$6-SUM(BS$10:BS30),-ROUNDDOWN($M31*BS$5/100,0)),0) -> 0 | BT31: =IF(AND(BT$7="○",$A31>=BT$8,$A31<=BT$9),IF(SUM(BT$10:BT30)-ROUNDDOWN($M31*BT$5/100,0)<-BT$6,-BT$6-SUM(BT$10:BT30),-ROUNDDOWN($M31*BT$5/100,0)),0) -> 0 | BU31: =IF(AND(BU$7="○",$A31>=BU$8,$A31<=BU$9),IF(SUM(BU$10:BU30)-ROUNDDOWN($M31*BU$5/100,0)<-BU$6,-BU$6-SUM(BU$10:BU30),-ROUNDDOWN($M31*BU$5/100,0)),0) -> 0 | BV31: =IF(AND(BV$7="○",$A31>=BV$8,$A31<=BV$9),IF(SUM(BV$10:BV30)-ROUNDDOWN($M31*BV$5/100,0)<-BV$6,-BV$6-SUM(BV$10:BV30),-ROUNDDOWN($M31*BV$5/100,0)),0) -> 0 | BW31: =IF(AND(BW$7="○",$A31>=BW$8,$A31<=BW$9),IF(SUM(BW$10:BW30)-ROUNDDOWN($M31*BW$5/100,0)<-BW$6,-BW$6-SUM(BW$10:BW30),-ROUNDDOWN($M31*BW$5/100,0)),0) -> 0 | BX31: =IF(AND(T31="○",$A31>=BX$8,$A31<=BX$9),IF(SUM(BX$10:BX30)-ROUNDDOWN($K31*BX$5/100,0)<-BX$6,-BX$6-SUM(BX$10:BX30),-ROUNDDOWN($K31*BX$5/100,0)),0) -> 0 | BY31: =IF(AND(U31="○",$A31>=BY$8,$A31<=BY$9),IF(SUM(BY$10:BY30)-ROUNDDOWN($K31*BY$5/100,0)<-BY$6,-BY$6-SUM(BY$10:BY30),-ROUNDDOWN($K31*BY$5/100,0)),0) -> 0 | BZ31: =IF(AND(V31="○",$A31>=BZ$8,$A31<=BZ$9),IF(SUM(BZ$10:BZ30)-ROUNDDOWN($K31*BZ$5/100,0)<-BZ$6,-BZ$6-SUM(BZ$10:BZ30),-ROUNDDOWN($K31*BZ$5/100,0)),0) -> 0 | CA31: =IF(AND(W31="○",$A31>=CA$8,$A31<=CA$9),IF(SUM(CA$10:CA30)-ROUNDDOWN($K31*CA$5/100,0)<-CA$6,-CA$6-SUM(CA$10:CA30),-ROUNDDOWN($K31*CA$5/100,0)),0) -> 0 | CG31: =+SUM(AJ31:CF31,BC31,BE31,AZ31,BA31,BG31,BI31) -> 0 | CH31: =+CG31+N31 -> 0 | CI31: =IFERROR(ROUNDDOWN((CH31/G31),0),0) -> 0 | CO31: =IFERROR(CN31-CI31,0) -> 0 | CP31: =IFERROR(CN31/CI31,0) -> 0 | CR31: =+CO31*G31 -> 0 | CT31: =INDEX([2]マスタ!$A:$A,MATCH(D31,[2]マスタ!$C:$C,0)) -> #N/A | CU31: =IFERROR(TEXT(TODAY(),"yyyymmdd")&"_"&ROUNDDOWN(H31+I31,0)&"-"&ROUNDDOWN(CI31,0),"") -> 20260620_0-0
G32: 1 | H32: =+F32*G32 -> 0 | K32: =+ROUNDDOWN((H32+I32)/100,0)*100 -> 0 | L32: =+ROUNDDOWN((H32+I32)/1.1/100,0)*100 -> 0 | M32: =+ROUNDDOWN((H32+I32)/1.1/200,0)*200 -> 0 | N32: =+H32+I32+J32 -> 0 | O32: =IF(OR(WEEKDAY($A32,2)=2,WEEKDAY($A32,2)=4),"○","✕") -> ✕ | P32: =+IF(MOD(TEXT($A32,"DD"),5)=0,"○","✕") -> ○ | Q32: =+IF((TEXT($A32,"DD")+0)=1,"○","✕") -> ✕ | R32: =+IF((TEXT($A32,"DD")+0)=18,"○","✕") -> ✕ | S32: 0 | T32: ✕ | U32: ✕ | V32: ✕ | W32: ✕ | X32: ○ | Y32: ✕ | Z32: ✕ | AA32: ✕ | AB32: ✕ | AC32: ✕ | AD32: =+IF(ISERROR(VLOOKUP($B32,AD$10:AD31,1,0)),IF(AND($N32>=1000,$A32>=AO$8,$A32<=AO$9),$B32,""),"") | AE32: =+IF(ISERROR(VLOOKUP($B32,AE$10:AE31,1,0)),IF(AND($N32>=1000,$A32>=AP$8,$A32<=AP$9),$B32,""),"") | AF32: =+IF(ISERROR(VLOOKUP($B32,AF$10:AF31,1,0)),IF(AND($N32>=1000,$A32>=AQ$8,$A32<=AQ$9),$B32,""),"") | AG32: =+IF(ISERROR(VLOOKUP($B32,AG$10:AG31,1,0)),IF(AND($N32>=1000,$A32>=AR$8,$A32<=AR$9),$B32,""),"") | AI32: 0 | AJ32: =IF(AND(AJ$7="○",$A32>=AJ$8,$A32<=AJ$9),IF(SUM(AJ$10:AJ31)-ROUNDDOWN($K32*AJ$5/100,0)<-AJ$6,-AJ$6-SUM(AJ$10:AJ31),-ROUNDDOWN($K32*AJ$5/100,0)),0) -> 0 | AK32: =IF(AND(AK$7="○",$A32>=AK$8,$A32<=AK$9),IF(SUM(AK$10:AK31)-ROUNDDOWN($L32*AK$5/100,0)<-AK$6,-AK$6-SUM(AK$10:AK31),-ROUNDDOWN($L32*AK$5/100,0)),0) -> 0 | AL32: =IF(AND(AL$7="○",$A32>=AL$8,$A32<=AL$9),IF(SUM(AL$10:AL31)-ROUNDDOWN($N32*AL$5/100,0)<-AL$6,-AL$6-SUM(AL$10:AL31),-ROUNDDOWN($N32*AL$5/100,0)),0) -> 0 | AM32: =IF(AND(AM$7="○",$A32>=AM$8,$A32<=AM$9),IF(SUM(AM$10:AM31)-ROUNDDOWN($L32*AM$5/100,0)<-AM$6,-AM$6-SUM(AM$10:AM31),-ROUNDDOWN($L32*AM$5/100,0)),0) -> 0 | AN32: =IF(AND(AN$7="○",$A32>=AN$8,$A32<=AN$9),IF(SUM(AN$10:AN31)-ROUNDDOWN($M32*AN$5/100,0)<-AN$6,-AN$6-SUM(AN$10:AN31),-ROUNDDOWN($M32*AN$5/100,0)),0) -> 0 | AO32: =IF(AND($A32>=AO$8,$A32<=AO$9),IF(SUM(AO$10:AO31)-ROUNDDOWN($K32*AO$5/100,0)<-AO$6,-AO$6-SUM(AO$10:AO31),-ROUNDDOWN($K32*AO$5/100,0)),0) -> 0 | AP32: =IF(AND($A32>=AP$8,$A32<=AP$9),IF(SUM(AP$10:AP31)-ROUNDDOWN($K32*AP$5/100,0)<-AP$6,-AP$6-SUM(AP$10:AP31),-ROUNDDOWN($K32*AP$5/100,0)),0) -> 0 | AQ32: =IF(AND($A32>=AQ$8,$A32<=AQ$9),IF(SUM(AQ$10:AQ31)-ROUNDDOWN($K32*AQ$5/100,0)<-AQ$6,-AQ$6-SUM(AQ$10:AQ31),-ROUNDDOWN($K32*AQ$5/100,0)),0) -> 0 | AR32: =IF(AND($A32>=AR$8,$A32<=AR$9),IF(SUM(AR$10:AR31)-ROUNDDOWN($K32*AR$5/100,0)<-AR$6,-AR$6-SUM(AR$10:AR31),-ROUNDDOWN($K32*AR$5/100,0)),0) -> 0 | AS32: =IF(SUMIFS(AS$10:AS31,$A$10:$A31,$A32)-ROUNDDOWN($K32*$S32/100,0)<-$S32*1000,-$S32*1000-SUMIFS(AS$10:AS31,$A$10:$A31,$A32),-ROUNDDOWN($K32*$S32/100,0)) -> 0 | AT32: =IF(AND(X32="○",$A32>=AT$8,$A32<=AT$9,K32>=3980),IF(SUM(AT$10:AT31)-ROUNDDOWN($K32*AT$5/100,0)<-AT$6,-AT$6-SUM(AT$10:AT31),-ROUNDDOWN($K32*AT$5/100,0)),0) -> 0 | AU32: =IF(O32="○",IF(SUM(AU$10:AU31)-ROUNDDOWN($K32*AU$5/100,0)<-AU$6,-AU$6-SUM(AU$10:AU31),-ROUNDDOWN($K32*AU$5/100,0)),0) -> 0 | AV32: =IF(P32="○",IF(SUM(AV$10:AV31)-ROUNDDOWN($K32*AV$5/100,0)<-AV$6,-AV$6-SUM(AV$10:AV31),-ROUNDDOWN($K32*AV$5/100,0)),0) -> 0 | AW32: =IF(Q32="○",IF(SUM(AW$10:AW31)-ROUNDDOWN($K32*AW$5/100,0)<-AW$6,-AW$6-SUM(AW$10:AW31),-ROUNDDOWN($K32*AW$5/100,0)),0) -> 0 | AX32: =IF(R32="○",IF(SUM(AX$10:AX31)-ROUNDDOWN($K32*AX$5/100,0)<-AX$6,-AX$6-SUM(AX$10:AX31),-ROUNDDOWN($K32*AX$5/100,0)),0) -> 0 | AY32: 0 | AZ32: =-ROUNDDOWN($K32*AY32/100,0) -> 0 | BA32: =-ROUNDDOWN($K32*AI32/100,0) -> 0 | BC32: =-ROUNDDOWN($K32*BB32/100,0) -> 0 | BD32: 0 | BE32: =-ROUNDDOWN($K32*BD32/100,0) -> 0 | BF32: 0 | BG32: =-ROUNDDOWN($K32*BF32/100,0) -> 0 | BH32: 0 | BI32: =-ROUNDDOWN($K32*BH32/100,0) -> 0 | BJ32: =IF(AND(BJ$7="○",$A32>=BJ$8,$A32<=BJ$9),IF(SUM(BJ$10:BJ31)-ROUNDDOWN($M32*BJ$5/100,0)<-BJ$6,-BJ$6-SUM(BJ$10:BJ31),-ROUNDDOWN($M32*BJ$5/100,0)),0) -> 0 | BK32: =IF(AND(BK$7="○",$A32>=BK$8,$A32<=BK$9),IF(SUM(BK$10:BK31)-ROUNDDOWN($L32*BK$5/100,0)<-BK$6,-BK$6-SUM(BK$10:BK31),-ROUNDDOWN($L32*BK$5/100,0)),0) -> 0 | BL32: =IF(AND(BL$7="○",$A32>=BL$8,$A32<=BL$9),IF(SUM(BL$10:BL31)-ROUNDDOWN($L32*BL$5/100,0)<-BL$6,-BL$6-SUM(BL$10:BL31),-ROUNDDOWN($L32*BL$5/100,0)),0) -> 0 | BM32: =IF(AND(BM$7="○",$A32>=BM$8,$A32<=BM$9),IF(SUM(BM$10:BM31)-ROUNDDOWN($M32*BM$5/100,0)<-BM$6,-BM$6-SUM(BM$10:BM31),-ROUNDDOWN($M32*BM$5/100,0)),0) -> 0 | BN32: =IF(AND(BN$7="○",$A32>=BN$8,$A32<=BN$9),IF(SUM(BN$10:BN31)-ROUNDDOWN($M32*BN$5/100,0)<-BN$6,-BN$6-SUM(BN$10:BN31),-ROUNDDOWN($M32*BN$5/100,0)),0) -> 0 | BO32: =IF(AND(BO$7="○",$A32>=BO$8,$A32<=BO$9),IF(SUM(BO$10:BO31)-ROUNDDOWN($M32*BO$5/100,0)<-BO$6,-BO$6-SUM(BO$10:BO31),-ROUNDDOWN($M32*BO$5/100,0)),0) -> 0 | BP32: =IF(AND(BP$7="○",$A32>=BP$8,$A32<=BP$9),IF(SUM(BP$10:BP31)-ROUNDDOWN($M32*BP$5/100,0)<-BP$6,-BP$6-SUM(BP$10:BP31),-ROUNDDOWN($M32*BP$5/100,0)),0) -> 0 | BQ32: =IF(AND(BQ$7="○",$A32>=BQ$8,$A32<=BQ$9),IF(SUM(BQ$10:BQ31)-ROUNDDOWN($L32*BQ$5/100,0)<-BQ$6,-BQ$6-SUM(BQ$10:BQ31),-ROUNDDOWN($L32*BQ$5/100,0)),0) -> 0 | BR32: =IF(AND(BR$7="○",$A32>=BR$8,$A32<=BR$9),IF(SUM(BR$10:BR31)-ROUNDDOWN($M32*BR$5/100,0)<-BR$6,-BR$6-SUM(BR$10:BR31),-ROUNDDOWN($M32*BR$5/100,0)),0) -> 0 | BS32: =IF(AND(BS$7="○",$A32>=BS$8,$A32<=BS$9),IF(SUM(BS$10:BS31)-ROUNDDOWN($M32*BS$5/100,0)<-BS$6,-BS$6-SUM(BS$10:BS31),-ROUNDDOWN($M32*BS$5/100,0)),0) -> 0 | BT32: =IF(AND(BT$7="○",$A32>=BT$8,$A32<=BT$9),IF(SUM(BT$10:BT31)-ROUNDDOWN($M32*BT$5/100,0)<-BT$6,-BT$6-SUM(BT$10:BT31),-ROUNDDOWN($M32*BT$5/100,0)),0) -> 0 | BU32: =IF(AND(BU$7="○",$A32>=BU$8,$A32<=BU$9),IF(SUM(BU$10:BU31)-ROUNDDOWN($M32*BU$5/100,0)<-BU$6,-BU$6-SUM(BU$10:BU31),-ROUNDDOWN($M32*BU$5/100,0)),0) -> 0 | BV32: =IF(AND(BV$7="○",$A32>=BV$8,$A32<=BV$9),IF(SUM(BV$10:BV31)-ROUNDDOWN($M32*BV$5/100,0)<-BV$6,-BV$6-SUM(BV$10:BV31),-ROUNDDOWN($M32*BV$5/100,0)),0) -> 0 | BW32: =IF(AND(BW$7="○",$A32>=BW$8,$A32<=BW$9),IF(SUM(BW$10:BW31)-ROUNDDOWN($M32*BW$5/100,0)<-BW$6,-BW$6-SUM(BW$10:BW31),-ROUNDDOWN($M32*BW$5/100,0)),0) -> 0 | BX32: =IF(AND(T32="○",$A32>=BX$8,$A32<=BX$9),IF(SUM(BX$10:BX31)-ROUNDDOWN($K32*BX$5/100,0)<-BX$6,-BX$6-SUM(BX$10:BX31),-ROUNDDOWN($K32*BX$5/100,0)),0) -> 0 | BY32: =IF(AND(U32="○",$A32>=BY$8,$A32<=BY$9),IF(SUM(BY$10:BY31)-ROUNDDOWN($K32*BY$5/100,0)<-BY$6,-BY$6-SUM(BY$10:BY31),-ROUNDDOWN($K32*BY$5/100,0)),0) -> 0 | BZ32: =IF(AND(V32="○",$A32>=BZ$8,$A32<=BZ$9),IF(SUM(BZ$10:BZ31)-ROUNDDOWN($K32*BZ$5/100,0)<-BZ$6,-BZ$6-SUM(BZ$10:BZ31),-ROUNDDOWN($K32*BZ$5/100,0)),0) -> 0 | CA32: =IF(AND(W32="○",$A32>=CA$8,$A32<=CA$9),IF(SUM(CA$10:CA31)-ROUNDDOWN($K32*CA$5/100,0)<-CA$6,-CA$6-SUM(CA$10:CA31),-ROUNDDOWN($K32*CA$5/100,0)),0) -> 0 | CG32: =+SUM(AJ32:CF32,BC32,BE32,AZ32,BA32,BG32,BI32) -> 0 | CH32: =+CG32+N32 -> 0 | CI32: =IFERROR(ROUNDDOWN((CH32/G32),0),0) -> 0 | CO32: =IFERROR(CN32-CI32,0) -> 0 | CP32: =IFERROR(CN32/CI32,0) -> 0 | CR32: =+CO32*G32 -> 0 | CT32: =INDEX([2]マスタ!$A:$A,MATCH(D32,[2]マスタ!$C:$C,0)) -> #N/A | CU32: =IFERROR(TEXT(TODAY(),"yyyymmdd")&"_"&ROUNDDOWN(H32+I32,0)&"-"&ROUNDDOWN(CI32,0),"") -> 20260620_0-0
G33: 1 | H33: =+F33*G33 -> 0 | K33: =+ROUNDDOWN((H33+I33)/100,0)*100 -> 0 | L33: =+ROUNDDOWN((H33+I33)/1.1/100,0)*100 -> 0 | M33: =+ROUNDDOWN((H33+I33)/1.1/200,0)*200 -> 0 | N33: =+H33+I33+J33 -> 0 | O33: =IF(OR(WEEKDAY($A33,2)=2,WEEKDAY($A33,2)=4),"○","✕") -> ✕ | P33: =+IF(MOD(TEXT($A33,"DD"),5)=0,"○","✕") -> ○ | Q33: =+IF((TEXT($A33,"DD")+0)=1,"○","✕") -> ✕ | R33: =+IF((TEXT($A33,"DD")+0)=18,"○","✕") -> ✕ | S33: 0 | T33: ✕ | U33: ✕ | V33: ✕ | W33: ✕ | X33: ○ | Y33: ✕ | Z33: ✕ | AA33: ✕ | AB33: ✕ | AC33: ✕ | AD33: =+IF(ISERROR(VLOOKUP($B33,AD$10:AD32,1,0)),IF(AND($N33>=1000,$A33>=AO$8,$A33<=AO$9),$B33,""),"") | AE33: =+IF(ISERROR(VLOOKUP($B33,AE$10:AE32,1,0)),IF(AND($N33>=1000,$A33>=AP$8,$A33<=AP$9),$B33,""),"") | AF33: =+IF(ISERROR(VLOOKUP($B33,AF$10:AF32,1,0)),IF(AND($N33>=1000,$A33>=AQ$8,$A33<=AQ$9),$B33,""),"") | AG33: =+IF(ISERROR(VLOOKUP($B33,AG$10:AG32,1,0)),IF(AND($N33>=1000,$A33>=AR$8,$A33<=AR$9),$B33,""),"") | AI33: 0 | AJ33: =IF(AND(AJ$7="○",$A33>=AJ$8,$A33<=AJ$9),IF(SUM(AJ$10:AJ32)-ROUNDDOWN($K33*AJ$5/100,0)<-AJ$6,-AJ$6-SUM(AJ$10:AJ32),-ROUNDDOWN($K33*AJ$5/100,0)),0) -> 0 | AK33: =IF(AND(AK$7="○",$A33>=AK$8,$A33<=AK$9),IF(SUM(AK$10:AK32)-ROUNDDOWN($L33*AK$5/100,0)<-AK$6,-AK$6-SUM(AK$10:AK32),-ROUNDDOWN($L33*AK$5/100,0)),0) -> 0 | AL33: =IF(AND(AL$7="○",$A33>=AL$8,$A33<=AL$9),IF(SUM(AL$10:AL32)-ROUNDDOWN($N33*AL$5/100,0)<-AL$6,-AL$6-SUM(AL$10:AL32),-ROUNDDOWN($N33*AL$5/100,0)),0) -> 0 | AM33: =IF(AND(AM$7="○",$A33>=AM$8,$A33<=AM$9),IF(SUM(AM$10:AM32)-ROUNDDOWN($L33*AM$5/100,0)<-AM$6,-AM$6-SUM(AM$10:AM32),-ROUNDDOWN($L33*AM$5/100,0)),0) -> 0 | AN33: =IF(AND(AN$7="○",$A33>=AN$8,$A33<=AN$9),IF(SUM(AN$10:AN32)-ROUNDDOWN($M33*AN$5/100,0)<-AN$6,-AN$6-SUM(AN$10:AN32),-ROUNDDOWN($M33*AN$5/100,0)),0) -> 0 | AO33: =IF(AND($A33>=AO$8,$A33<=AO$9),IF(SUM(AO$10:AO32)-ROUNDDOWN($K33*AO$5/100,0)<-AO$6,-AO$6-SUM(AO$10:AO32),-ROUNDDOWN($K33*AO$5/100,0)),0) -> 0 | AP33: =IF(AND($A33>=AP$8,$A33<=AP$9),IF(SUM(AP$10:AP32)-ROUNDDOWN($K33*AP$5/100,0)<-AP$6,-AP$6-SUM(AP$10:AP32),-ROUNDDOWN($K33*AP$5/100,0)),0) -> 0 | AQ33: =IF(AND($A33>=AQ$8,$A33<=AQ$9),IF(SUM(AQ$10:AQ32)-ROUNDDOWN($K33*AQ$5/100,0)<-AQ$6,-AQ$6-SUM(AQ$10:AQ32),-ROUNDDOWN($K33*AQ$5/100,0)),0) -> 0 | AR33: =IF(AND($A33>=AR$8,$A33<=AR$9),IF(SUM(AR$10:AR32)-ROUNDDOWN($K33*AR$5/100,0)<-AR$6,-AR$6-SUM(AR$10:AR32),-ROUNDDOWN($K33*AR$5/100,0)),0) -> 0 | AS33: =IF(SUMIFS(AS$10:AS32,$A$10:$A32,$A33)-ROUNDDOWN($K33*$S33/100,0)<-$S33*1000,-$S33*1000-SUMIFS(AS$10:AS32,$A$10:$A32,$A33),-ROUNDDOWN($K33*$S33/100,0)) -> 0 | AT33: =IF(AND(X33="○",$A33>=AT$8,$A33<=AT$9,K33>=3980),IF(SUM(AT$10:AT32)-ROUNDDOWN($K33*AT$5/100,0)<-AT$6,-AT$6-SUM(AT$10:AT32),-ROUNDDOWN($K33*AT$5/100,0)),0) -> 0 | AU33: =IF(O33="○",IF(SUM(AU$10:AU32)-ROUNDDOWN($K33*AU$5/100,0)<-AU$6,-AU$6-SUM(AU$10:AU32),-ROUNDDOWN($K33*AU$5/100,0)),0) -> 0 | AV33: =IF(P33="○",IF(SUM(AV$10:AV32)-ROUNDDOWN($K33*AV$5/100,0)<-AV$6,-AV$6-SUM(AV$10:AV32),-ROUNDDOWN($K33*AV$5/100,0)),0) -> 0 | AW33: =IF(Q33="○",IF(SUM(AW$10:AW32)-ROUNDDOWN($K33*AW$5/100,0)<-AW$6,-AW$6-SUM(AW$10:AW32),-ROUNDDOWN($K33*AW$5/100,0)),0) -> 0 | AX33: =IF(R33="○",IF(SUM(AX$10:AX32)-ROUNDDOWN($K33*AX$5/100,0)<-AX$6,-AX$6-SUM(AX$10:AX32),-ROUNDDOWN($K33*AX$5/100,0)),0) -> 0 | AY33: 0 | AZ33: =-ROUNDDOWN($K33*AY33/100,0) -> 0 | BA33: =-ROUNDDOWN($K33*AI33/100,0) -> 0 | BC33: =-ROUNDDOWN($K33*BB33/100,0) -> 0 | BD33: 0 | BE33: =-ROUNDDOWN($K33*BD33/100,0) -> 0 | BF33: 0 | BG33: =-ROUNDDOWN($K33*BF33/100,0) -> 0 | BH33: 0 | BI33: =-ROUNDDOWN($K33*BH33/100,0) -> 0 | BJ33: =IF(AND(BJ$7="○",$A33>=BJ$8,$A33<=BJ$9),IF(SUM(BJ$10:BJ32)-ROUNDDOWN($M33*BJ$5/100,0)<-BJ$6,-BJ$6-SUM(BJ$10:BJ32),-ROUNDDOWN($M33*BJ$5/100,0)),0) -> 0 | BK33: =IF(AND(BK$7="○",$A33>=BK$8,$A33<=BK$9),IF(SUM(BK$10:BK32)-ROUNDDOWN($L33*BK$5/100,0)<-BK$6,-BK$6-SUM(BK$10:BK32),-ROUNDDOWN($L33*BK$5/100,0)),0) -> 0 | BL33: =IF(AND(BL$7="○",$A33>=BL$8,$A33<=BL$9),IF(SUM(BL$10:BL32)-ROUNDDOWN($L33*BL$5/100,0)<-BL$6,-BL$6-SUM(BL$10:BL32),-ROUNDDOWN($L33*BL$5/100,0)),0) -> 0 | BM33: =IF(AND(BM$7="○",$A33>=BM$8,$A33<=BM$9),IF(SUM(BM$10:BM32)-ROUNDDOWN($M33*BM$5/100,0)<-BM$6,-BM$6-SUM(BM$10:BM32),-ROUNDDOWN($M33*BM$5/100,0)),0) -> 0 | BN33: =IF(AND(BN$7="○",$A33>=BN$8,$A33<=BN$9),IF(SUM(BN$10:BN32)-ROUNDDOWN($M33*BN$5/100,0)<-BN$6,-BN$6-SUM(BN$10:BN32),-ROUNDDOWN($M33*BN$5/100,0)),0) -> 0 | BO33: =IF(AND(BO$7="○",$A33>=BO$8,$A33<=BO$9),IF(SUM(BO$10:BO32)-ROUNDDOWN($M33*BO$5/100,0)<-BO$6,-BO$6-SUM(BO$10:BO32),-ROUNDDOWN($M33*BO$5/100,0)),0) -> 0 | BP33: =IF(AND(BP$7="○",$A33>=BP$8,$A33<=BP$9),IF(SUM(BP$10:BP32)-ROUNDDOWN($M33*BP$5/100,0)<-BP$6,-BP$6-SUM(BP$10:BP32),-ROUNDDOWN($M33*BP$5/100,0)),0) -> 0 | BQ33: =IF(AND(BQ$7="○",$A33>=BQ$8,$A33<=BQ$9),IF(SUM(BQ$10:BQ32)-ROUNDDOWN($L33*BQ$5/100,0)<-BQ$6,-BQ$6-SUM(BQ$10:BQ32),-ROUNDDOWN($L33*BQ$5/100,0)),0) -> 0 | BR33: =IF(AND(BR$7="○",$A33>=BR$8,$A33<=BR$9),IF(SUM(BR$10:BR32)-ROUNDDOWN($M33*BR$5/100,0)<-BR$6,-BR$6-SUM(BR$10:BR32),-ROUNDDOWN($M33*BR$5/100,0)),0) -> 0 | BS33: =IF(AND(BS$7="○",$A33>=BS$8,$A33<=BS$9),IF(SUM(BS$10:BS32)-ROUNDDOWN($M33*BS$5/100,0)<-BS$6,-BS$6-SUM(BS$10:BS32),-ROUNDDOWN($M33*BS$5/100,0)),0) -> 0 | BT33: =IF(AND(BT$7="○",$A33>=BT$8,$A33<=BT$9),IF(SUM(BT$10:BT32)-ROUNDDOWN($M33*BT$5/100,0)<-BT$6,-BT$6-SUM(BT$10:BT32),-ROUNDDOWN($M33*BT$5/100,0)),0) -> 0 | BU33: =IF(AND(BU$7="○",$A33>=BU$8,$A33<=BU$9),IF(SUM(BU$10:BU32)-ROUNDDOWN($M33*BU$5/100,0)<-BU$6,-BU$6-SUM(BU$10:BU32),-ROUNDDOWN($M33*BU$5/100,0)),0) -> 0 | BV33: =IF(AND(BV$7="○",$A33>=BV$8,$A33<=BV$9),IF(SUM(BV$10:BV32)-ROUNDDOWN($M33*BV$5/100,0)<-BV$6,-BV$6-SUM(BV$10:BV32),-ROUNDDOWN($M33*BV$5/100,0)),0) -> 0 | BW33: =IF(AND(BW$7="○",$A33>=BW$8,$A33<=BW$9),IF(SUM(BW$10:BW32)-ROUNDDOWN($M33*BW$5/100,0)<-BW$6,-BW$6-SUM(BW$10:BW32),-ROUNDDOWN($M33*BW$5/100,0)),0) -> 0 | BX33: =IF(AND(T33="○",$A33>=BX$8,$A33<=BX$9),IF(SUM(BX$10:BX32)-ROUNDDOWN($K33*BX$5/100,0)<-BX$6,-BX$6-SUM(BX$10:BX32),-ROUNDDOWN($K33*BX$5/100,0)),0) -> 0 | BY33: =IF(AND(U33="○",$A33>=BY$8,$A33<=BY$9),IF(SUM(BY$10:BY32)-ROUNDDOWN($K33*BY$5/100,0)<-BY$6,-BY$6-SUM(BY$10:BY32),-ROUNDDOWN($K33*BY$5/100,0)),0) -> 0 | BZ33: =IF(AND(V33="○",$A33>=BZ$8,$A33<=BZ$9),IF(SUM(BZ$10:BZ32)-ROUNDDOWN($K33*BZ$5/100,0)<-BZ$6,-BZ$6-SUM(BZ$10:BZ32),-ROUNDDOWN($K33*BZ$5/100,0)),0) -> 0 | CA33: =IF(AND(W33="○",$A33>=CA$8,$A33<=CA$9),IF(SUM(CA$10:CA32)-ROUNDDOWN($K33*CA$5/100,0)<-CA$6,-CA$6-SUM(CA$10:CA32),-ROUNDDOWN($K33*CA$5/100,0)),0) -> 0 | CG33: =+SUM(AJ33:CF33,BC33,BE33,AZ33,BA33,BG33,BI33) -> 0 | CH33: =+CG33+N33 -> 0 | CI33: =IFERROR(ROUNDDOWN((CH33/G33),0),0) -> 0 | CO33: =IFERROR(CN33-CI33,0) -> 0 | CP33: =IFERROR(CN33/CI33,0) -> 0 | CR33: =+CO33*G33 -> 0 | CT33: =INDEX([2]マスタ!$A:$A,MATCH(D33,[2]マスタ!$C:$C,0)) -> #N/A | CU33: =IFERROR(TEXT(TODAY(),"yyyymmdd")&"_"&ROUNDDOWN(H33+I33,0)&"-"&ROUNDDOWN(CI33,0),"") -> 20260620_0-0
G34: 1 | H34: =+F34*G34 -> 0 | K34: =+ROUNDDOWN((H34+I34)/100,0)*100 -> 0 | L34: =+ROUNDDOWN((H34+I34)/1.1/100,0)*100 -> 0 | M34: =+ROUNDDOWN((H34+I34)/1.1/200,0)*200 -> 0 | N34: =+H34+I34+J34 -> 0 | O34: =IF(OR(WEEKDAY($A34,2)=2,WEEKDAY($A34,2)=4),"○","✕") -> ✕ | P34: =+IF(MOD(TEXT($A34,"DD"),5)=0,"○","✕") -> ○ | Q34: =+IF((TEXT($A34,"DD")+0)=1,"○","✕") -> ✕ | R34: =+IF((TEXT($A34,"DD")+0)=18,"○","✕") -> ✕ | S34: 0 | T34: ✕ | U34: ✕ | V34: ✕ | W34: ✕ | X34: ○ | Y34: ✕ | Z34: ✕ | AA34: ✕ | AB34: ✕ | AC34: ✕ | AD34: =+IF(ISERROR(VLOOKUP($B34,AD$10:AD33,1,0)),IF(AND($N34>=1000,$A34>=AO$8,$A34<=AO$9),$B34,""),"") | AE34: =+IF(ISERROR(VLOOKUP($B34,AE$10:AE33,1,0)),IF(AND($N34>=1000,$A34>=AP$8,$A34<=AP$9),$B34,""),"") | AF34: =+IF(ISERROR(VLOOKUP($B34,AF$10:AF33,1,0)),IF(AND($N34>=1000,$A34>=AQ$8,$A34<=AQ$9),$B34,""),"") | AG34: =+IF(ISERROR(VLOOKUP($B34,AG$10:AG33,1,0)),IF(AND($N34>=1000,$A34>=AR$8,$A34<=AR$9),$B34,""),"") | AI34: 0 | AJ34: =IF(AND(AJ$7="○",$A34>=AJ$8,$A34<=AJ$9),IF(SUM(AJ$10:AJ33)-ROUNDDOWN($K34*AJ$5/100,0)<-AJ$6,-AJ$6-SUM(AJ$10:AJ33),-ROUNDDOWN($K34*AJ$5/100,0)),0) -> 0 | AK34: =IF(AND(AK$7="○",$A34>=AK$8,$A34<=AK$9),IF(SUM(AK$10:AK33)-ROUNDDOWN($L34*AK$5/100,0)<-AK$6,-AK$6-SUM(AK$10:AK33),-ROUNDDOWN($L34*AK$5/100,0)),0) -> 0 | AL34: =IF(AND(AL$7="○",$A34>=AL$8,$A34<=AL$9),IF(SUM(AL$10:AL33)-ROUNDDOWN($N34*AL$5/100,0)<-AL$6,-AL$6-SUM(AL$10:AL33),-ROUNDDOWN($N34*AL$5/100,0)),0) -> 0 | AM34: =IF(AND(AM$7="○",$A34>=AM$8,$A34<=AM$9),IF(SUM(AM$10:AM33)-ROUNDDOWN($L34*AM$5/100,0)<-AM$6,-AM$6-SUM(AM$10:AM33),-ROUNDDOWN($L34*AM$5/100,0)),0) -> 0 | AN34: =IF(AND(AN$7="○",$A34>=AN$8,$A34<=AN$9),IF(SUM(AN$10:AN33)-ROUNDDOWN($M34*AN$5/100,0)<-AN$6,-AN$6-SUM(AN$10:AN33),-ROUNDDOWN($M34*AN$5/100,0)),0) -> 0 | AO34: =IF(AND($A34>=AO$8,$A34<=AO$9),IF(SUM(AO$10:AO33)-ROUNDDOWN($K34*AO$5/100,0)<-AO$6,-AO$6-SUM(AO$10:AO33),-ROUNDDOWN($K34*AO$5/100,0)),0) -> 0 | AP34: =IF(AND($A34>=AP$8,$A34<=AP$9),IF(SUM(AP$10:AP33)-ROUNDDOWN($K34*AP$5/100,0)<-AP$6,-AP$6-SUM(AP$10:AP33),-ROUNDDOWN($K34*AP$5/100,0)),0) -> 0 | AQ34: =IF(AND($A34>=AQ$8,$A34<=AQ$9),IF(SUM(AQ$10:AQ33)-ROUNDDOWN($K34*AQ$5/100,0)<-AQ$6,-AQ$6-SUM(AQ$10:AQ33),-ROUNDDOWN($K34*AQ$5/100,0)),0) -> 0 | AR34: =IF(AND($A34>=AR$8,$A34<=AR$9),IF(SUM(AR$10:AR33)-ROUNDDOWN($K34*AR$5/100,0)<-AR$6,-AR$6-SUM(AR$10:AR33),-ROUNDDOWN($K34*AR$5/100,0)),0) -> 0 | AS34: =IF(SUMIFS(AS$10:AS33,$A$10:$A33,$A34)-ROUNDDOWN($K34*$S34/100,0)<-$S34*1000,-$S34*1000-SUMIFS(AS$10:AS33,$A$10:$A33,$A34),-ROUNDDOWN($K34*$S34/100,0)) -> 0 | AT34: =IF(AND(X34="○",$A34>=AT$8,$A34<=AT$9,K34>=3980),IF(SUM(AT$10:AT33)-ROUNDDOWN($K34*AT$5/100,0)<-AT$6,-AT$6-SUM(AT$10:AT33),-ROUNDDOWN($K34*AT$5/100,0)),0) -> 0 | AU34: =IF(O34="○",IF(SUM(AU$10:AU33)-ROUNDDOWN($K34*AU$5/100,0)<-AU$6,-AU$6-SUM(AU$10:AU33),-ROUNDDOWN($K34*AU$5/100,0)),0) -> 0 | AV34: =IF(P34="○",IF(SUM(AV$10:AV33)-ROUNDDOWN($K34*AV$5/100,0)<-AV$6,-AV$6-SUM(AV$10:AV33),-ROUNDDOWN($K34*AV$5/100,0)),0) -> 0 | AW34: =IF(Q34="○",IF(SUM(AW$10:AW33)-ROUNDDOWN($K34*AW$5/100,0)<-AW$6,-AW$6-SUM(AW$10:AW33),-ROUNDDOWN($K34*AW$5/100,0)),0) -> 0 | AX34: =IF(R34="○",IF(SUM(AX$10:AX33)-ROUNDDOWN($K34*AX$5/100,0)<-AX$6,-AX$6-SUM(AX$10:AX33),-ROUNDDOWN($K34*AX$5/100,0)),0) -> 0 | AY34: 0 | AZ34: =-ROUNDDOWN($K34*AY34/100,0) -> 0 | BA34: =-ROUNDDOWN($K34*AI34/100,0) -> 0 | BC34: =-ROUNDDOWN($K34*BB34/100,0) -> 0 | BD34: 0 | BE34: =-ROUNDDOWN($K34*BD34/100,0) -> 0 | BF34: 0 | BG34: =-ROUNDDOWN($K34*BF34/100,0) -> 0 | BH34: 0 | BI34: =-ROUNDDOWN($K34*BH34/100,0) -> 0 | BJ34: =IF(AND(BJ$7="○",$A34>=BJ$8,$A34<=BJ$9),IF(SUM(BJ$10:BJ33)-ROUNDDOWN($M34*BJ$5/100,0)<-BJ$6,-BJ$6-SUM(BJ$10:BJ33),-ROUNDDOWN($M34*BJ$5/100,0)),0) -> 0 | BK34: =IF(AND(BK$7="○",$A34>=BK$8,$A34<=BK$9),IF(SUM(BK$10:BK33)-ROUNDDOWN($L34*BK$5/100,0)<-BK$6,-BK$6-SUM(BK$10:BK33),-ROUNDDOWN($L34*BK$5/100,0)),0) -> 0 | BL34: =IF(AND(BL$7="○",$A34>=BL$8,$A34<=BL$9),IF(SUM(BL$10:BL33)-ROUNDDOWN($L34*BL$5/100,0)<-BL$6,-BL$6-SUM(BL$10:BL33),-ROUNDDOWN($L34*BL$5/100,0)),0) -> 0 | BM34: =IF(AND(BM$7="○",$A34>=BM$8,$A34<=BM$9),IF(SUM(BM$10:BM33)-ROUNDDOWN($M34*BM$5/100,0)<-BM$6,-BM$6-SUM(BM$10:BM33),-ROUNDDOWN($M34*BM$5/100,0)),0) -> 0 | BN34: =IF(AND(BN$7="○",$A34>=BN$8,$A34<=BN$9),IF(SUM(BN$10:BN33)-ROUNDDOWN($M34*BN$5/100,0)<-BN$6,-BN$6-SUM(BN$10:BN33),-ROUNDDOWN($M34*BN$5/100,0)),0) -> 0 | BO34: =IF(AND(BO$7="○",$A34>=BO$8,$A34<=BO$9),IF(SUM(BO$10:BO33)-ROUNDDOWN($M34*BO$5/100,0)<-BO$6,-BO$6-SUM(BO$10:BO33),-ROUNDDOWN($M34*BO$5/100,0)),0) -> 0 | BP34: =IF(AND(BP$7="○",$A34>=BP$8,$A34<=BP$9),IF(SUM(BP$10:BP33)-ROUNDDOWN($M34*BP$5/100,0)<-BP$6,-BP$6-SUM(BP$10:BP33),-ROUNDDOWN($M34*BP$5/100,0)),0) -> 0 | BQ34: =IF(AND(BQ$7="○",$A34>=BQ$8,$A34<=BQ$9),IF(SUM(BQ$10:BQ33)-ROUNDDOWN($L34*BQ$5/100,0)<-BQ$6,-BQ$6-SUM(BQ$10:BQ33),-ROUNDDOWN($L34*BQ$5/100,0)),0) -> 0 | BR34: =IF(AND(BR$7="○",$A34>=BR$8,$A34<=BR$9),IF(SUM(BR$10:BR33)-ROUNDDOWN($M34*BR$5/100,0)<-BR$6,-BR$6-SUM(BR$10:BR33),-ROUNDDOWN($M34*BR$5/100,0)),0) -> 0 | BS34: =IF(AND(BS$7="○",$A34>=BS$8,$A34<=BS$9),IF(SUM(BS$10:BS33)-ROUNDDOWN($M34*BS$5/100,0)<-BS$6,-BS$6-SUM(BS$10:BS33),-ROUNDDOWN($M34*BS$5/100,0)),0) -> 0 | BT34: =IF(AND(BT$7="○",$A34>=BT$8,$A34<=BT$9),IF(SUM(BT$10:BT33)-ROUNDDOWN($M34*BT$5/100,0)<-BT$6,-BT$6-SUM(BT$10:BT33),-ROUNDDOWN($M34*BT$5/100,0)),0) -> 0 | BU34: =IF(AND(BU$7="○",$A34>=BU$8,$A34<=BU$9),IF(SUM(BU$10:BU33)-ROUNDDOWN($M34*BU$5/100,0)<-BU$6,-BU$6-SUM(BU$10:BU33),-ROUNDDOWN($M34*BU$5/100,0)),0) -> 0 | BV34: =IF(AND(BV$7="○",$A34>=BV$8,$A34<=BV$9),IF(SUM(BV$10:BV33)-ROUNDDOWN($M34*BV$5/100,0)<-BV$6,-BV$6-SUM(BV$10:BV33),-ROUNDDOWN($M34*BV$5/100,0)),0) -> 0 | BW34: =IF(AND(BW$7="○",$A34>=BW$8,$A34<=BW$9),IF(SUM(BW$10:BW33)-ROUNDDOWN($M34*BW$5/100,0)<-BW$6,-BW$6-SUM(BW$10:BW33),-ROUNDDOWN($M34*BW$5/100,0)),0) -> 0 | BX34: =IF(AND(T34="○",$A34>=BX$8,$A34<=BX$9),IF(SUM(BX$10:BX33)-ROUNDDOWN($K34*BX$5/100,0)<-BX$6,-BX$6-SUM(BX$10:BX33),-ROUNDDOWN($K34*BX$5/100,0)),0) -> 0 | BY34: =IF(AND(U34="○",$A34>=BY$8,$A34<=BY$9),IF(SUM(BY$10:BY33)-ROUNDDOWN($K34*BY$5/100,0)<-BY$6,-BY$6-SUM(BY$10:BY33),-ROUNDDOWN($K34*BY$5/100,0)),0) -> 0 | BZ34: =IF(AND(V34="○",$A34>=BZ$8,$A34<=BZ$9),IF(SUM(BZ$10:BZ33)-ROUNDDOWN($K34*BZ$5/100,0)<-BZ$6,-BZ$6-SUM(BZ$10:BZ33),-ROUNDDOWN($K34*BZ$5/100,0)),0) -> 0 | CA34: =IF(AND(W34="○",$A34>=CA$8,$A34<=CA$9),IF(SUM(CA$10:CA33)-ROUNDDOWN($K34*CA$5/100,0)<-CA$6,-CA$6-SUM(CA$10:CA33),-ROUNDDOWN($K34*CA$5/100,0)),0) -> 0 | CG34: =+SUM(AJ34:CF34,BC34,BE34,AZ34,BA34,BG34,BI34) -> 0 | CH34: =+CG34+N34 -> 0 | CI34: =IFERROR(ROUNDDOWN((CH34/G34),0),0) -> 0 | CO34: =IFERROR(CN34-CI34,0) -> 0 | CP34: =IFERROR(CN34/CI34,0) -> 0 | CR34: =+CO34*G34 -> 0 | CT34: =INDEX([2]マスタ!$A:$A,MATCH(D34,[2]マスタ!$C:$C,0)) -> #N/A | CU34: =IFERROR(TEXT(TODAY(),"yyyymmdd")&"_"&ROUNDDOWN(H34+I34,0)&"-"&ROUNDDOWN(CI34,0),"") -> 20260620_0-0
G35: 1 | H35: =+F35*G35 -> 0 | K35: =+ROUNDDOWN((H35+I35)/100,0)*100 -> 0 | L35: =+ROUNDDOWN((H35+I35)/1.1/100,0)*100 -> 0 | M35: =+ROUNDDOWN((H35+I35)/1.1/200,0)*200 -> 0 | N35: =+H35+I35+J35 -> 0 | O35: =IF(OR(WEEKDAY($A35,2)=2,WEEKDAY($A35,2)=4),"○","✕") -> ✕ | P35: =+IF(MOD(TEXT($A35,"DD"),5)=0,"○","✕") -> ○ | Q35: =+IF((TEXT($A35,"DD")+0)=1,"○","✕") -> ✕ | R35: =+IF((TEXT($A35,"DD")+0)=18,"○","✕") -> ✕ | S35: 0 | T35: ✕ | U35: ✕ | V35: ✕ | W35: ✕ | X35: ○ | Y35: ✕ | Z35: ✕ | AA35: ✕ | AB35: ✕ | AC35: ✕ | AD35: =+IF(ISERROR(VLOOKUP($B35,AD$10:AD34,1,0)),IF(AND($N35>=1000,$A35>=AO$8,$A35<=AO$9),$B35,""),"") | AE35: =+IF(ISERROR(VLOOKUP($B35,AE$10:AE34,1,0)),IF(AND($N35>=1000,$A35>=AP$8,$A35<=AP$9),$B35,""),"") | AF35: =+IF(ISERROR(VLOOKUP($B35,AF$10:AF34,1,0)),IF(AND($N35>=1000,$A35>=AQ$8,$A35<=AQ$9),$B35,""),"") | AG35: =+IF(ISERROR(VLOOKUP($B35,AG$10:AG34,1,0)),IF(AND($N35>=1000,$A35>=AR$8,$A35<=AR$9),$B35,""),"") | AI35: 0 | AJ35: =IF(AND(AJ$7="○",$A35>=AJ$8,$A35<=AJ$9),IF(SUM(AJ$10:AJ34)-ROUNDDOWN($K35*AJ$5/100,0)<-AJ$6,-AJ$6-SUM(AJ$10:AJ34),-ROUNDDOWN($K35*AJ$5/100,0)),0) -> 0 | AK35: =IF(AND(AK$7="○",$A35>=AK$8,$A35<=AK$9),IF(SUM(AK$10:AK34)-ROUNDDOWN($L35*AK$5/100,0)<-AK$6,-AK$6-SUM(AK$10:AK34),-ROUNDDOWN($L35*AK$5/100,0)),0) -> 0 | AL35: =IF(AND(AL$7="○",$A35>=AL$8,$A35<=AL$9),IF(SUM(AL$10:AL34)-ROUNDDOWN($N35*AL$5/100,0)<-AL$6,-AL$6-SUM(AL$10:AL34),-ROUNDDOWN($N35*AL$5/100,0)),0) -> 0 | AM35: =IF(AND(AM$7="○",$A35>=AM$8,$A35<=AM$9),IF(SUM(AM$10:AM34)-ROUNDDOWN($L35*AM$5/100,0)<-AM$6,-AM$6-SUM(AM$10:AM34),-ROUNDDOWN($L35*AM$5/100,0)),0) -> 0 | AN35: =IF(AND(AN$7="○",$A35>=AN$8,$A35<=AN$9),IF(SUM(AN$10:AN34)-ROUNDDOWN($M35*AN$5/100,0)<-AN$6,-AN$6-SUM(AN$10:AN34),-ROUNDDOWN($M35*AN$5/100,0)),0) -> 0 | AO35: =IF(AND($A35>=AO$8,$A35<=AO$9),IF(SUM(AO$10:AO34)-ROUNDDOWN($K35*AO$5/100,0)<-AO$6,-AO$6-SUM(AO$10:AO34),-ROUNDDOWN($K35*AO$5/100,0)),0) -> 0 | AP35: =IF(AND($A35>=AP$8,$A35<=AP$9),IF(SUM(AP$10:AP34)-ROUNDDOWN($K35*AP$5/100,0)<-AP$6,-AP$6-SUM(AP$10:AP34),-ROUNDDOWN($K35*AP$5/100,0)),0) -> 0 | AQ35: =IF(AND($A35>=AQ$8,$A35<=AQ$9),IF(SUM(AQ$10:AQ34)-ROUNDDOWN($K35*AQ$5/100,0)<-AQ$6,-AQ$6-SUM(AQ$10:AQ34),-ROUNDDOWN($K35*AQ$5/100,0)),0) -> 0 | AR35: =IF(AND($A35>=AR$8,$A35<=AR$9),IF(SUM(AR$10:AR34)-ROUNDDOWN($K35*AR$5/100,0)<-AR$6,-AR$6-SUM(AR$10:AR34),-ROUNDDOWN($K35*AR$5/100,0)),0) -> 0 | AS35: =IF(SUMIFS(AS$10:AS34,$A$10:$A34,$A35)-ROUNDDOWN($K35*$S35/100,0)<-$S35*1000,-$S35*1000-SUMIFS(AS$10:AS34,$A$10:$A34,$A35),-ROUNDDOWN($K35*$S35/100,0)) -> 0 | AT35: =IF(AND(X35="○",$A35>=AT$8,$A35<=AT$9,K35>=3980),IF(SUM(AT$10:AT34)-ROUNDDOWN($K35*AT$5/100,0)<-AT$6,-AT$6-SUM(AT$10:AT34),-ROUNDDOWN($K35*AT$5/100,0)),0) -> 0 | AU35: =IF(O35="○",IF(SUM(AU$10:AU34)-ROUNDDOWN($K35*AU$5/100,0)<-AU$6,-AU$6-SUM(AU$10:AU34),-ROUNDDOWN($K35*AU$5/100,0)),0) -> 0 | AV35: =IF(P35="○",IF(SUM(AV$10:AV34)-ROUNDDOWN($K35*AV$5/100,0)<-AV$6,-AV$6-SUM(AV$10:AV34),-ROUNDDOWN($K35*AV$5/100,0)),0) -> 0 | AW35: =IF(Q35="○",IF(SUM(AW$10:AW34)-ROUNDDOWN($K35*AW$5/100,0)<-AW$6,-AW$6-SUM(AW$10:AW34),-ROUNDDOWN($K35*AW$5/100,0)),0) -> 0 | AX35: =IF(R35="○",IF(SUM(AX$10:AX34)-ROUNDDOWN($K35*AX$5/100,0)<-AX$6,-AX$6-SUM(AX$10:AX34),-ROUNDDOWN($K35*AX$5/100,0)),0) -> 0 | AY35: 0 | AZ35: =-ROUNDDOWN($K35*AY35/100,0) -> 0 | BA35: =-ROUNDDOWN($K35*AI35/100,0) -> 0 | BC35: =-ROUNDDOWN($K35*BB35/100,0) -> 0 | BD35: 0 | BE35: =-ROUNDDOWN($K35*BD35/100,0) -> 0 | BF35: 0 | BG35: =-ROUNDDOWN($K35*BF35/100,0) -> 0 | BH35: 0 | BI35: =-ROUNDDOWN($K35*BH35/100,0) -> 0 | BJ35: =IF(AND(BJ$7="○",$A35>=BJ$8,$A35<=BJ$9),IF(SUM(BJ$10:BJ34)-ROUNDDOWN($M35*BJ$5/100,0)<-BJ$6,-BJ$6-SUM(BJ$10:BJ34),-ROUNDDOWN($M35*BJ$5/100,0)),0) -> 0 | BK35: =IF(AND(BK$7="○",$A35>=BK$8,$A35<=BK$9),IF(SUM(BK$10:BK34)-ROUNDDOWN($L35*BK$5/100,0)<-BK$6,-BK$6-SUM(BK$10:BK34),-ROUNDDOWN($L35*BK$5/100,0)),0) -> 0 | BL35: =IF(AND(BL$7="○",$A35>=BL$8,$A35<=BL$9),IF(SUM(BL$10:BL34)-ROUNDDOWN($L35*BL$5/100,0)<-BL$6,-BL$6-SUM(BL$10:BL34),-ROUNDDOWN($L35*BL$5/100,0)),0) -> 0 | BM35: =IF(AND(BM$7="○",$A35>=BM$8,$A35<=BM$9),IF(SUM(BM$10:BM34)-ROUNDDOWN($M35*BM$5/100,0)<-BM$6,-BM$6-SUM(BM$10:BM34),-ROUNDDOWN($M35*BM$5/100,0)),0) -> 0 | BN35: =IF(AND(BN$7="○",$A35>=BN$8,$A35<=BN$9),IF(SUM(BN$10:BN34)-ROUNDDOWN($M35*BN$5/100,0)<-BN$6,-BN$6-SUM(BN$10:BN34),-ROUNDDOWN($M35*BN$5/100,0)),0) -> 0 | BO35: =IF(AND(BO$7="○",$A35>=BO$8,$A35<=BO$9),IF(SUM(BO$10:BO34)-ROUNDDOWN($M35*BO$5/100,0)<-BO$6,-BO$6-SUM(BO$10:BO34),-ROUNDDOWN($M35*BO$5/100,0)),0) -> 0 | BP35: =IF(AND(BP$7="○",$A35>=BP$8,$A35<=BP$9),IF(SUM(BP$10:BP34)-ROUNDDOWN($M35*BP$5/100,0)<-BP$6,-BP$6-SUM(BP$10:BP34),-ROUNDDOWN($M35*BP$5/100,0)),0) -> 0 | BQ35: =IF(AND(BQ$7="○",$A35>=BQ$8,$A35<=BQ$9),IF(SUM(BQ$10:BQ34)-ROUNDDOWN($L35*BQ$5/100,0)<-BQ$6,-BQ$6-SUM(BQ$10:BQ34),-ROUNDDOWN($L35*BQ$5/100,0)),0) -> 0 | BR35: =IF(AND(BR$7="○",$A35>=BR$8,$A35<=BR$9),IF(SUM(BR$10:BR34)-ROUNDDOWN($M35*BR$5/100,0)<-BR$6,-BR$6-SUM(BR$10:BR34),-ROUNDDOWN($M35*BR$5/100,0)),0) -> 0 | BS35: =IF(AND(BS$7="○",$A35>=BS$8,$A35<=BS$9),IF(SUM(BS$10:BS34)-ROUNDDOWN($M35*BS$5/100,0)<-BS$6,-BS$6-SUM(BS$10:BS34),-ROUNDDOWN($M35*BS$5/100,0)),0) -> 0 | BT35: =IF(AND(BT$7="○",$A35>=BT$8,$A35<=BT$9),IF(SUM(BT$10:BT34)-ROUNDDOWN($M35*BT$5/100,0)<-BT$6,-BT$6-SUM(BT$10:BT34),-ROUNDDOWN($M35*BT$5/100,0)),0) -> 0 | BU35: =IF(AND(BU$7="○",$A35>=BU$8,$A35<=BU$9),IF(SUM(BU$10:BU34)-ROUNDDOWN($M35*BU$5/100,0)<-BU$6,-BU$6-SUM(BU$10:BU34),-ROUNDDOWN($M35*BU$5/100,0)),0) -> 0 | BV35: =IF(AND(BV$7="○",$A35>=BV$8,$A35<=BV$9),IF(SUM(BV$10:BV34)-ROUNDDOWN($M35*BV$5/100,0)<-BV$6,-BV$6-SUM(BV$10:BV34),-ROUNDDOWN($M35*BV$5/100,0)),0) -> 0 | BW35: =IF(AND(BW$7="○",$A35>=BW$8,$A35<=BW$9),IF(SUM(BW$10:BW34)-ROUNDDOWN($M35*BW$5/100,0)<-BW$6,-BW$6-SUM(BW$10:BW34),-ROUNDDOWN($M35*BW$5/100,0)),0) -> 0 | BX35: =IF(AND(T35="○",$A35>=BX$8,$A35<=BX$9),IF(SUM(BX$10:BX34)-ROUNDDOWN($K35*BX$5/100,0)<-BX$6,-BX$6-SUM(BX$10:BX34),-ROUNDDOWN($K35*BX$5/100,0)),0) -> 0 | BY35: =IF(AND(U35="○",$A35>=BY$8,$A35<=BY$9),IF(SUM(BY$10:BY34)-ROUNDDOWN($K35*BY$5/100,0)<-BY$6,-BY$6-SUM(BY$10:BY34),-ROUNDDOWN($K35*BY$5/100,0)),0) -> 0 | BZ35: =IF(AND(V35="○",$A35>=BZ$8,$A35<=BZ$9),IF(SUM(BZ$10:BZ34)-ROUNDDOWN($K35*BZ$5/100,0)<-BZ$6,-BZ$6-SUM(BZ$10:BZ34),-ROUNDDOWN($K35*BZ$5/100,0)),0) -> 0 | CA35: =IF(AND(W35="○",$A35>=CA$8,$A35<=CA$9),IF(SUM(CA$10:CA34)-ROUNDDOWN($K35*CA$5/100,0)<-CA$6,-CA$6-SUM(CA$10:CA34),-ROUNDDOWN($K35*CA$5/100,0)),0) -> 0 | CG35: =+SUM(AJ35:CF35,BC35,BE35,AZ35,BA35,BG35,BI35) -> 0 | CH35: =+CG35+N35 -> 0 | CI35: =IFERROR(ROUNDDOWN((CH35/G35),0),0) -> 0 | CO35: =IFERROR(CN35-CI35,0) -> 0 | CP35: =IFERROR(CN35/CI35,0) -> 0 | CR35: =+CO35*G35 -> 0 | CT35: =INDEX([2]マスタ!$A:$A,MATCH(D35,[2]マスタ!$C:$C,0)) -> #N/A | CU35: =IFERROR(TEXT(TODAY(),"yyyymmdd")&"_"&ROUNDDOWN(H35+I35,0)&"-"&ROUNDDOWN(CI35,0),"") -> 20260620_0-0
G36: 1 | H36: =+F36*G36 -> 0 | K36: =+ROUNDDOWN((H36+I36+J36)/100,0)*100 -> 0 | L36: =+ROUNDDOWN((H36+I36)/1.1/100,0)*100 -> 0 | M36: =+ROUNDDOWN((H36+I36)/1.1/200,0)*200 -> 0 | N36: =+H36+I36+J36 -> 0 | O36: =IF(OR(WEEKDAY($A36,2)=2,WEEKDAY($A36,2)=4),"○","✕") -> ✕ | P36: =+IF(MOD(TEXT($A36,"DD"),5)=0,"○","✕") -> ○ | Q36: =+IF((TEXT(A36,"DD")+0)=1,"○","✕") -> ✕ | R36: =+IF((TEXT($A36,"DD")+0)=18,"○","✕") -> ✕ | S36: 0 | T36: ✕ | U36: ✕ | V36: ✕ | W36: ✕ | X36: ○ | Y36: ✕ | Z36: ✕ | AA36: ✕ | AB36: ✕ | AC36: ✕ | AD36: =+IF(ISERROR(VLOOKUP($B36,AD$10:AD35,1,0)),IF(AND($N36>=1000,$A36>=AO$8,$A36<=AO$9),$B36,""),"") | AE36: =+IF(ISERROR(VLOOKUP($B36,AE$10:AE35,1,0)),IF(AND($N36>=1000,$A36>=AP$8,$A36<=AP$9),$B36,""),"") | AF36: =+IF(ISERROR(VLOOKUP($B36,AF$10:AF35,1,0)),IF(AND($N36>=1000,$A36>=AQ$8,$A36<=AQ$9),$B36,""),"") | AG36: =+IF(ISERROR(VLOOKUP($B36,AG$10:AG35,1,0)),IF(AND($N36>=1000,$A36>=AR$8,$A36<=AR$9),$B36,""),"") | AI36: 0 | AJ36: =IF(AND(AJ$7="○",$A36>=AJ$8,$A36<=AJ$9),IF(SUM(AJ$10:AJ35)-ROUNDDOWN($K36*AJ$5/100,0)<-AJ$6,-AJ$6-SUM(AJ$10:AJ35),-ROUNDDOWN($K36*AJ$5/100,0)),0) -> 0 | AK36: =IF(AND(AK$7="○",$A36>=AK$8,$A36<=AK$9),IF(SUM(AK$10:AK35)-ROUNDDOWN($L36*AK$5/100,0)<-AK$6,-AK$6-SUM(AK$10:AK35),-ROUNDDOWN($L36*AK$5/100,0)),0) -> 0 | AL36: =IF(AND(AL$7="○",$A36>=AL$8,$A36<=AL$9),IF(SUM(AL$10:AL35)-ROUNDDOWN($N36*AL$5/100,0)<-AL$6,-AL$6-SUM(AL$10:AL35),-ROUNDDOWN($N36*AL$5/100,0)),0) -> 0 | AM36: =IF(AND(AM$7="○",$A36>=AM$8,$A36<=AM$9),IF(SUM(AM$10:AM35)-ROUNDDOWN($L36*AM$5/100,0)<-AM$6,-AM$6-SUM(AM$10:AM35),-ROUNDDOWN($L36*AM$5/100,0)),0) -> 0 | AN36: =IF(AND(AN$7="○",$A36>=AN$8,$A36<=AN$9),IF(SUM(AN$10:AN35)-ROUNDDOWN($M36*AN$5/100,0)<-AN$6,-AN$6-SUM(AN$10:AN35),-ROUNDDOWN($M36*AN$5/100,0)),0) -> 0 | AO36: =IF(AND($A36>=AO$8,$A36<=AO$9),IF(SUM(AO$10:AO35)-ROUNDDOWN($K36*AO$5/100,0)<-AO$6,-AO$6-SUM(AO$10:AO35),-ROUNDDOWN($K36*AO$5/100,0)),0) -> 0 | AP36: =IF(AND($A36>=AP$8,$A36<=AP$9),IF(SUM(AP$10:AP35)-ROUNDDOWN($K36*AP$5/100,0)<-AP$6,-AP$6-SUM(AP$10:AP35),-ROUNDDOWN($K36*AP$5/100,0)),0) -> 0 | AQ36: =IF(AND($A36>=AQ$8,$A36<=AQ$9),IF(SUM(AQ$10:AQ35)-ROUNDDOWN($K36*AQ$5/100,0)<-AQ$6,-AQ$6-SUM(AQ$10:AQ35),-ROUNDDOWN($K36*AQ$5/100,0)),0) -> 0 | AR36: =IF(AND($A36>=AR$8,$A36<=AR$9),IF(SUM(AR$10:AR35)-ROUNDDOWN($K36*AR$5/100,0)<-AR$6,-AR$6-SUM(AR$10:AR35),-ROUNDDOWN($K36*AR$5/100,0)),0) -> 0 | AS36: =IF(SUMIFS(AS$10:AS35,$A$10:$A35,$A36)-ROUNDDOWN($K36*$S36/100,0)<-$S36*1000,-$S36*1000-SUMIFS(AS$10:AS35,$A$10:$A35,$A36),-ROUNDDOWN($K36*$S36/100,0)) -> 0 | AT36: =IF(AND(X36="○",$A36>=AT$8,$A36<=AT$9,K36>=3980),IF(SUM(AT$10:AT35)-ROUNDDOWN($K36*AT$5/100,0)<-AT$6,-AT$6-SUM(AT$10:AT35),-ROUNDDOWN($K36*AT$5/100,0)),0) -> 0 | AU36: =IF(O36="○",IF(SUM(AU$10:AU35)-ROUNDDOWN($K36*AU$5/100,0)<-AU$6,-AU$6-SUM(AU$10:AU35),-ROUNDDOWN($K36*AU$5/100,0)),0) -> 0 | AV36: =IF(P36="○",IF(SUM(AV$10:AV35)-ROUNDDOWN($K36*AV$5/100,0)<-AV$6,-AV$6-SUM(AV$10:AV35),-ROUNDDOWN($K36*AV$5/100,0)),0) -> 0 | AW36: =IF(Q36="○",IF(SUM(AW$10:AW35)-ROUNDDOWN($K36*AW$5/100,0)<-AW$6,-AW$6-SUM(AW$10:AW35),-ROUNDDOWN($K36*AW$5/100,0)),0) -> 0 | AX36: =IF(R36="○",IF(SUM(AX$10:AX35)-ROUNDDOWN($K36*AX$5/100,0)<-AX$6,-AX$6-SUM(AX$10:AX35),-ROUNDDOWN($K36*AX$5/100,0)),0) -> 0 | AY36: 0 | AZ36: =-ROUNDDOWN($K36*AY36/100,0) -> 0 | BA36: =-ROUNDDOWN($K36*AI36/100,0) -> 0 | BC36: =-ROUNDDOWN($K36*BB36/100,0) -> 0 | BD36: 0 | BE36: =-ROUNDDOWN($K36*BD36/100,0) -> 0 | BF36: 0 | BG36: =-ROUNDDOWN($K36*BF36/100,0) -> 0 | BH36: 0 | BI36: =-ROUNDDOWN($K36*BH36/100,0) -> 0 | BJ36: =IF(AND(BJ$7="○",$A36>=BJ$8,$A36<=BJ$9),IF(SUM(BJ$10:BJ35)-ROUNDDOWN($M36*BJ$5/100,0)<-BJ$6,-BJ$6-SUM(BJ$10:BJ35),-ROUNDDOWN($M36*BJ$5/100,0)),0) -> 0 | BK36: =IF(AND(BK$7="○",$A36>=BK$8,$A36<=BK$9),IF(SUM(BK$10:BK35)-ROUNDDOWN($L36*BK$5/100,0)<-BK$6,-BK$6-SUM(BK$10:BK35),-ROUNDDOWN($L36*BK$5/100,0)),0) -> 0 | BL36: =IF(AND(BL$7="○",$A36>=BL$8,$A36<=BL$9),IF(SUM(BL$10:BL35)-ROUNDDOWN($L36*BL$5/100,0)<-BL$6,-BL$6-SUM(BL$10:BL35),-ROUNDDOWN($L36*BL$5/100,0)),0) -> 0 | BM36: =IF(AND(BM$7="○",$A36>=BM$8,$A36<=BM$9),IF(SUM(BM$10:BM35)-ROUNDDOWN($M36*BM$5/100,0)<-BM$6,-BM$6-SUM(BM$10:BM35),-ROUNDDOWN($M36*BM$5/100,0)),0) -> 0 | BN36: =IF(AND(BN$7="○",$A36>=BN$8,$A36<=BN$9),IF(SUM(BN$10:BN35)-ROUNDDOWN($M36*BN$5/100,0)<-BN$6,-BN$6-SUM(BN$10:BN35),-ROUNDDOWN($M36*BN$5/100,0)),0) -> 0 | BO36: =IF(AND(BO$7="○",$A36>=BO$8,$A36<=BO$9),IF(SUM(BO$10:BO35)-ROUNDDOWN($M36*BO$5/100,0)<-BO$6,-BO$6-SUM(BO$10:BO35),-ROUNDDOWN($M36*BO$5/100,0)),0) -> 0 | BP36: =IF(AND(BP$7="○",$A36>=BP$8,$A36<=BP$9),IF(SUM(BP$10:BP35)-ROUNDDOWN($M36*BP$5/100,0)<-BP$6,-BP$6-SUM(BP$10:BP35),-ROUNDDOWN($M36*BP$5/100,0)),0) -> 0 | BQ36: =IF(AND(BQ$7="○",$A36>=BQ$8,$A36<=BQ$9),IF(SUM(BQ$10:BQ35)-ROUNDDOWN($L36*BQ$5/100,0)<-BQ$6,-BQ$6-SUM(BQ$10:BQ35),-ROUNDDOWN($L36*BQ$5/100,0)),0) -> 0 | BR36: =IF(AND(BR$7="○",$A36>=BR$8,$A36<=BR$9),IF(SUM(BR$10:BR35)-ROUNDDOWN($M36*BR$5/100,0)<-BR$6,-BR$6-SUM(BR$10:BR35),-ROUNDDOWN($M36*BR$5/100,0)),0) -> 0 | BS36: =IF(AND(BS$7="○",$A36>=BS$8,$A36<=BS$9),IF(SUM(BS$10:BS35)-ROUNDDOWN($M36*BS$5/100,0)<-BS$6,-BS$6-SUM(BS$10:BS35),-ROUNDDOWN($M36*BS$5/100,0)),0) -> 0 | BT36: =IF(AND(BT$7="○",$A36>=BT$8,$A36<=BT$9),IF(SUM(BT$10:BT35)-ROUNDDOWN($M36*BT$5/100,0)<-BT$6,-BT$6-SUM(BT$10:BT35),-ROUNDDOWN($M36*BT$5/100,0)),0) -> 0 | BU36: =IF(AND(BU$7="○",$A36>=BU$8,$A36<=BU$9),IF(SUM(BU$10:BU35)-ROUNDDOWN($M36*BU$5/100,0)<-BU$6,-BU$6-SUM(BU$10:BU35),-ROUNDDOWN($M36*BU$5/100,0)),0) -> 0 | BV36: =IF(AND(BV$7="○",$A36>=BV$8,$A36<=BV$9),IF(SUM(BV$10:BV35)-ROUNDDOWN($M36*BV$5/100,0)<-BV$6,-BV$6-SUM(BV$10:BV35),-ROUNDDOWN($M36*BV$5/100,0)),0) -> 0 | BW36: =IF(AND(BW$7="○",$A36>=BW$8,$A36<=BW$9),IF(SUM(BW$10:BW35)-ROUNDDOWN($M36*BW$5/100,0)<-BW$6,-BW$6-SUM(BW$10:BW35),-ROUNDDOWN($M36*BW$5/100,0)),0) -> 0 | BX36: =IF(AND(T36="○",$A36>=BX$8,$A36<=BX$9),IF(SUM(BX$10:BX35)-ROUNDDOWN($K36*BX$5/100,0)<-BX$6,-BX$6-SUM(BX$10:BX35),-ROUNDDOWN($K36*BX$5/100,0)),0) -> 0 | BY36: =IF(AND(U36="○",$A36>=BY$8,$A36<=BY$9),IF(SUM(BY$10:BY35)-ROUNDDOWN($K36*BY$5/100,0)<-BY$6,-BY$6-SUM(BY$10:BY35),-ROUNDDOWN($K36*BY$5/100,0)),0) -> 0 | BZ36: =IF(AND(V36="○",$A36>=BZ$8,$A36<=BZ$9),IF(SUM(BZ$10:BZ35)-ROUNDDOWN($K36*BZ$5/100,0)<-BZ$6,-BZ$6-SUM(BZ$10:BZ35),-ROUNDDOWN($K36*BZ$5/100,0)),0) -> 0 | CA36: =IF(AND(W36="○",$A36>=CA$8,$A36<=CA$9),IF(SUM(CA$10:CA35)-ROUNDDOWN($K36*CA$5/100,0)<-CA$6,-CA$6-SUM(CA$10:CA35),-ROUNDDOWN($K36*CA$5/100,0)),0) -> 0 | CG36: =+SUM(AJ36:CF36,BC36,BE36,AZ36,BA36,BG36,BI36) -> 0 | CH36: =+CG36+N36 -> 0 | CI36: =IFERROR(ROUNDDOWN((CH36/G36),0),0) -> 0 | CO36: =IFERROR(CN36-CI36,0) -> 0 | CP36: =IFERROR(CN36/CI36,0) -> 0 | CR36: =+CO36*G36 -> 0 | CT36: =INDEX([2]マスタ!$A:$A,MATCH(D36,[2]マスタ!$C:$C,0)) -> #N/A | CU36: =IFERROR(TEXT(TODAY(),"yyyymmdd")&"_"&ROUNDDOWN(H36+I36,0)&"-"&ROUNDDOWN(CI36,0),"") -> 20260620_0-0
G37: 1 | H37: =+F37*G37 -> 0 | K37: =+ROUNDDOWN((H37+I37+J37)/100,0)*100 -> 0 | L37: =+ROUNDDOWN((H37+I37)/1.1/100,0)*100 -> 0 | M37: =+ROUNDDOWN((H37+I37)/1.1/200,0)*200 -> 0 | N37: =+H37+I37+J37 -> 0 | O37: =IF(OR(WEEKDAY($A37,2)=2,WEEKDAY($A37,2)=4),"○","✕") -> ✕ | P37: =+IF(MOD(TEXT($A37,"DD"),5)=0,"○","✕") -> ○ | Q37: =+IF((TEXT(A37,"DD")+0)=1,"○","✕") -> ✕ | R37: =+IF((TEXT($A37,"DD")+0)=18,"○","✕") -> ✕ | S37: 0 | T37: ✕ | U37: ✕ | V37: ✕ | W37: ✕ | X37: ○ | Y37: ✕ | Z37: ✕ | AA37: ✕ | AB37: ✕ | AC37: ✕ | AD37: =+IF(ISERROR(VLOOKUP($B37,AD$10:AD36,1,0)),IF(AND($N37>=1000,$A37>=AO$8,$A37<=AO$9),$B37,""),"") | AE37: =+IF(ISERROR(VLOOKUP($B37,AE$10:AE36,1,0)),IF(AND($N37>=1000,$A37>=AP$8,$A37<=AP$9),$B37,""),"") | AF37: =+IF(ISERROR(VLOOKUP($B37,AF$10:AF36,1,0)),IF(AND($N37>=1000,$A37>=AQ$8,$A37<=AQ$9),$B37,""),"") | AG37: =+IF(ISERROR(VLOOKUP($B37,AG$10:AG36,1,0)),IF(AND($N37>=1000,$A37>=AR$8,$A37<=AR$9),$B37,""),"") | AI37: 0 | AJ37: =IF(AND(AJ$7="○",$A37>=AJ$8,$A37<=AJ$9),IF(SUM(AJ$10:AJ36)-ROUNDDOWN($K37*AJ$5/100,0)<-AJ$6,-AJ$6-SUM(AJ$10:AJ36),-ROUNDDOWN($K37*AJ$5/100,0)),0) -> 0 | AK37: =IF(AND(AK$7="○",$A37>=AK$8,$A37<=AK$9),IF(SUM(AK$10:AK36)-ROUNDDOWN($L37*AK$5/100,0)<-AK$6,-AK$6-SUM(AK$10:AK36),-ROUNDDOWN($L37*AK$5/100,0)),0) -> 0 | AL37: =IF(AND(AL$7="○",$A37>=AL$8,$A37<=AL$9),IF(SUM(AL$10:AL36)-ROUNDDOWN($N37*AL$5/100,0)<-AL$6,-AL$6-SUM(AL$10:AL36),-ROUNDDOWN($N37*AL$5/100,0)),0) -> 0 | AM37: =IF(AND(AM$7="○",$A37>=AM$8,$A37<=AM$9),IF(SUM(AM$10:AM36)-ROUNDDOWN($L37*AM$5/100,0)<-AM$6,-AM$6-SUM(AM$10:AM36),-ROUNDDOWN($L37*AM$5/100,0)),0) -> 0 | AN37: =IF(AND(AN$7="○",$A37>=AN$8,$A37<=AN$9),IF(SUM(AN$10:AN36)-ROUNDDOWN($M37*AN$5/100,0)<-AN$6,-AN$6-SUM(AN$10:AN36),-ROUNDDOWN($M37*AN$5/100,0)),0) -> 0 | AO37: =IF(AND($A37>=AO$8,$A37<=AO$9),IF(SUM(AO$10:AO36)-ROUNDDOWN($K37*AO$5/100,0)<-AO$6,-AO$6-SUM(AO$10:AO36),-ROUNDDOWN($K37*AO$5/100,0)),0) -> 0 | AP37: =IF(AND($A37>=AP$8,$A37<=AP$9),IF(SUM(AP$10:AP36)-ROUNDDOWN($K37*AP$5/100,0)<-AP$6,-AP$6-SUM(AP$10:AP36),-ROUNDDOWN($K37*AP$5/100,0)),0) -> 0 | AQ37: =IF(AND($A37>=AQ$8,$A37<=AQ$9),IF(SUM(AQ$10:AQ36)-ROUNDDOWN($K37*AQ$5/100,0)<-AQ$6,-AQ$6-SUM(AQ$10:AQ36),-ROUNDDOWN($K37*AQ$5/100,0)),0) -> 0 | AR37: =IF(AND($A37>=AR$8,$A37<=AR$9),IF(SUM(AR$10:AR36)-ROUNDDOWN($K37*AR$5/100,0)<-AR$6,-AR$6-SUM(AR$10:AR36),-ROUNDDOWN($K37*AR$5/100,0)),0) -> 0 | AS37: =IF(SUMIFS(AS$10:AS36,$A$10:$A36,$A37)-ROUNDDOWN($K37*$S37/100,0)<-$S37*1000,-$S37*1000-SUMIFS(AS$10:AS36,$A$10:$A36,$A37),-ROUNDDOWN($K37*$S37/100,0)) -> 0 | AT37: =IF(AND(X37="○",$A37>=AT$8,$A37<=AT$9,K37>=3980),IF(SUM(AT$10:AT36)-ROUNDDOWN($K37*AT$5/100,0)<-AT$6,-AT$6-SUM(AT$10:AT36),-ROUNDDOWN($K37*AT$5/100,0)),0) -> 0 | AU37: =IF(O37="○",IF(SUM(AU$10:AU36)-ROUNDDOWN($K37*AU$5/100,0)<-AU$6,-AU$6-SUM(AU$10:AU36),-ROUNDDOWN($K37*AU$5/100,0)),0) -> 0 | AV37: =IF(P37="○",IF(SUM(AV$10:AV36)-ROUNDDOWN($K37*AV$5/100,0)<-AV$6,-AV$6-SUM(AV$10:AV36),-ROUNDDOWN($K37*AV$5/100,0)),0) -> 0 | AW37: =IF(Q37="○",IF(SUM(AW$10:AW36)-ROUNDDOWN($K37*AW$5/100,0)<-AW$6,-AW$6-SUM(AW$10:AW36),-ROUNDDOWN($K37*AW$5/100,0)),0) -> 0 | AX37: =IF(R37="○",IF(SUM(AX$10:AX36)-ROUNDDOWN($K37*AX$5/100,0)<-AX$6,-AX$6-SUM(AX$10:AX36),-ROUNDDOWN($K37*AX$5/100,0)),0) -> 0 | AY37: 0 | AZ37: =-ROUNDDOWN($K37*AY37/100,0) -> 0 | BA37: =-ROUNDDOWN($K37*AI37/100,0) -> 0 | BC37: =-ROUNDDOWN($K37*BB37/100,0) -> 0 | BD37: 0 | BE37: =-ROUNDDOWN($K37*BD37/100,0) -> 0 | BF37: 0 | BG37: =-ROUNDDOWN($K37*BF37/100,0) -> 0 | BH37: 0 | BI37: =-ROUNDDOWN($K37*BH37/100,0) -> 0 | BJ37: =IF(AND(BJ$7="○",$A37>=BJ$8,$A37<=BJ$9),IF(SUM(BJ$10:BJ36)-ROUNDDOWN($M37*BJ$5/100,0)<-BJ$6,-BJ$6-SUM(BJ$10:BJ36),-ROUNDDOWN($M37*BJ$5/100,0)),0) -> 0 | BK37: =IF(AND(BK$7="○",$A37>=BK$8,$A37<=BK$9),IF(SUM(BK$10:BK36)-ROUNDDOWN($L37*BK$5/100,0)<-BK$6,-BK$6-SUM(BK$10:BK36),-ROUNDDOWN($L37*BK$5/100,0)),0) -> 0 | BL37: =IF(AND(BL$7="○",$A37>=BL$8,$A37<=BL$9),IF(SUM(BL$10:BL36)-ROUNDDOWN($L37*BL$5/100,0)<-BL$6,-BL$6-SUM(BL$10:BL36),-ROUNDDOWN($L37*BL$5/100,0)),0) -> 0 | BM37: =IF(AND(BM$7="○",$A37>=BM$8,$A37<=BM$9),IF(SUM(BM$10:BM36)-ROUNDDOWN($M37*BM$5/100,0)<-BM$6,-BM$6-SUM(BM$10:BM36),-ROUNDDOWN($M37*BM$5/100,0)),0) -> 0 | BN37: =IF(AND(BN$7="○",$A37>=BN$8,$A37<=BN$9),IF(SUM(BN$10:BN36)-ROUNDDOWN($M37*BN$5/100,0)<-BN$6,-BN$6-SUM(BN$10:BN36),-ROUNDDOWN($M37*BN$5/100,0)),0) -> 0 | BO37: =IF(AND(BO$7="○",$A37>=BO$8,$A37<=BO$9),IF(SUM(BO$10:BO36)-ROUNDDOWN($M37*BO$5/100,0)<-BO$6,-BO$6-SUM(BO$10:BO36),-ROUNDDOWN($M37*BO$5/100,0)),0) -> 0 | BP37: =IF(AND(BP$7="○",$A37>=BP$8,$A37<=BP$9),IF(SUM(BP$10:BP36)-ROUNDDOWN($M37*BP$5/100,0)<-BP$6,-BP$6-SUM(BP$10:BP36),-ROUNDDOWN($M37*BP$5/100,0)),0) -> 0 | BQ37: =IF(AND(BQ$7="○",$A37>=BQ$8,$A37<=BQ$9),IF(SUM(BQ$10:BQ36)-ROUNDDOWN($L37*BQ$5/100,0)<-BQ$6,-BQ$6-SUM(BQ$10:BQ36),-ROUNDDOWN($L37*BQ$5/100,0)),0) -> 0 | BR37: =IF(AND(BR$7="○",$A37>=BR$8,$A37<=BR$9),IF(SUM(BR$10:BR36)-ROUNDDOWN($M37*BR$5/100,0)<-BR$6,-BR$6-SUM(BR$10:BR36),-ROUNDDOWN($M37*BR$5/100,0)),0) -> 0 | BS37: =IF(AND(BS$7="○",$A37>=BS$8,$A37<=BS$9),IF(SUM(BS$10:BS36)-ROUNDDOWN($M37*BS$5/100,0)<-BS$6,-BS$6-SUM(BS$10:BS36),-ROUNDDOWN($M37*BS$5/100,0)),0) -> 0 | BT37: =IF(AND(BT$7="○",$A37>=BT$8,$A37<=BT$9),IF(SUM(BT$10:BT36)-ROUNDDOWN($M37*BT$5/100,0)<-BT$6,-BT$6-SUM(BT$10:BT36),-ROUNDDOWN($M37*BT$5/100,0)),0) -> 0 | BU37: =IF(AND(BU$7="○",$A37>=BU$8,$A37<=BU$9),IF(SUM(BU$10:BU36)-ROUNDDOWN($M37*BU$5/100,0)<-BU$6,-BU$6-SUM(BU$10:BU36),-ROUNDDOWN($M37*BU$5/100,0)),0) -> 0 | BV37: =IF(AND(BV$7="○",$A37>=BV$8,$A37<=BV$9),IF(SUM(BV$10:BV36)-ROUNDDOWN($M37*BV$5/100,0)<-BV$6,-BV$6-SUM(BV$10:BV36),-ROUNDDOWN($M37*BV$5/100,0)),0) -> 0 | BW37: =IF(AND(BW$7="○",$A37>=BW$8,$A37<=BW$9),IF(SUM(BW$10:BW36)-ROUNDDOWN($M37*BW$5/100,0)<-BW$6,-BW$6-SUM(BW$10:BW36),-ROUNDDOWN($M37*BW$5/100,0)),0) -> 0 | BX37: =IF(AND(T37="○",$A37>=BX$8,$A37<=BX$9),IF(SUM(BX$10:BX36)-ROUNDDOWN($K37*BX$5/100,0)<-BX$6,-BX$6-SUM(BX$10:BX36),-ROUNDDOWN($K37*BX$5/100,0)),0) -> 0 | BY37: =IF(AND(U37="○",$A37>=BY$8,$A37<=BY$9),IF(SUM(BY$10:BY36)-ROUNDDOWN($K37*BY$5/100,0)<-BY$6,-BY$6-SUM(BY$10:BY36),-ROUNDDOWN($K37*BY$5/100,0)),0) -> 0 | BZ37: =IF(AND(V37="○",$A37>=BZ$8,$A37<=BZ$9),IF(SUM(BZ$10:BZ36)-ROUNDDOWN($K37*BZ$5/100,0)<-BZ$6,-BZ$6-SUM(BZ$10:BZ36),-ROUNDDOWN($K37*BZ$5/100,0)),0) -> 0 | CA37: =IF(AND(W37="○",$A37>=CA$8,$A37<=CA$9),IF(SUM(CA$10:CA36)-ROUNDDOWN($K37*CA$5/100,0)<-CA$6,-CA$6-SUM(CA$10:CA36),-ROUNDDOWN($K37*CA$5/100,0)),0) -> 0 | CG37: =+SUM(AJ37:CF37,BC37,BE37,AZ37,BA37,BG37,BI37) -> 0 | CH37: =+CG37+N37 -> 0 | CI37: =IFERROR(ROUNDDOWN((CH37/G37),0),0) -> 0 | CO37: =IFERROR(CN37-CI37,0) -> 0 | CP37: =IFERROR(CN37/CI37,0) -> 0 | CR37: =+CO37*G37 -> 0 | CT37: =INDEX([2]マスタ!$A:$A,MATCH(D37,[2]マスタ!$C:$C,0)) -> #N/A | CU37: =IFERROR(TEXT(TODAY(),"yyyymmdd")&"_"&ROUNDDOWN(H37+I37,0)&"-"&ROUNDDOWN(CI37,0),"") -> 20260620_0-0
G38: 1 | H38: =+F38*G38 -> 0 | K38: =+ROUNDDOWN((H38+I38+J38)/100,0)*100 -> 0 | L38: =+ROUNDDOWN((H38+I38)/1.1/100,0)*100 -> 0 | M38: =+ROUNDDOWN((H38+I38)/1.1/200,0)*200 -> 0 | N38: =+H38+I38+J38 -> 0 | O38: =IF(OR(WEEKDAY($A38,2)=2,WEEKDAY($A38,2)=4),"○","✕") -> ✕ | P38: =+IF(MOD(TEXT($A38,"DD"),5)=0,"○","✕") -> ○ | Q38: =+IF((TEXT(A38,"DD")+0)=1,"○","✕") -> ✕ | R38: =+IF((TEXT($A38,"DD")+0)=18,"○","✕") -> ✕ | S38: 0 | T38: ✕ | U38: ✕ | V38: ✕ | W38: ✕ | X38: ○ | Y38: ✕ | Z38: ✕ | AA38: ✕ | AB38: ✕ | AC38: ✕ | AD38: =+IF(ISERROR(VLOOKUP($B38,AD$10:AD37,1,0)),IF(AND($N38>=1000,$A38>=AO$8,$A38<=AO$9),$B38,""),"") | AE38: =+IF(ISERROR(VLOOKUP($B38,AE$10:AE37,1,0)),IF(AND($N38>=1000,$A38>=AP$8,$A38<=AP$9),$B38,""),"") | AF38: =+IF(ISERROR(VLOOKUP($B38,AF$10:AF37,1,0)),IF(AND($N38>=1000,$A38>=AQ$8,$A38<=AQ$9),$B38,""),"") | AG38: =+IF(ISERROR(VLOOKUP($B38,AG$10:AG37,1,0)),IF(AND($N38>=1000,$A38>=AR$8,$A38<=AR$9),$B38,""),"") | AI38: 0 | AJ38: =IF(AND(AJ$7="○",$A38>=AJ$8,$A38<=AJ$9),IF(SUM(AJ$10:AJ37)-ROUNDDOWN($K38*AJ$5/100,0)<-AJ$6,-AJ$6-SUM(AJ$10:AJ37),-ROUNDDOWN($K38*AJ$5/100,0)),0) -> 0 | AK38: =IF(AND(AK$7="○",$A38>=AK$8,$A38<=AK$9),IF(SUM(AK$10:AK37)-ROUNDDOWN($L38*AK$5/100,0)<-AK$6,-AK$6-SUM(AK$10:AK37),-ROUNDDOWN($L38*AK$5/100,0)),0) -> 0 | AL38: =IF(AND(AL$7="○",$A38>=AL$8,$A38<=AL$9),IF(SUM(AL$10:AL37)-ROUNDDOWN($N38*AL$5/100,0)<-AL$6,-AL$6-SUM(AL$10:AL37),-ROUNDDOWN($N38*AL$5/100,0)),0) -> 0 | AM38: =IF(AND(AM$7="○",$A38>=AM$8,$A38<=AM$9),IF(SUM(AM$10:AM37)-ROUNDDOWN($L38*AM$5/100,0)<-AM$6,-AM$6-SUM(AM$10:AM37),-ROUNDDOWN($L38*AM$5/100,0)),0) -> 0 | AN38: =IF(AND(AN$7="○",$A38>=AN$8,$A38<=AN$9),IF(SUM(AN$10:AN37)-ROUNDDOWN($M38*AN$5/100,0)<-AN$6,-AN$6-SUM(AN$10:AN37),-ROUNDDOWN($M38*AN$5/100,0)),0) -> 0 | AO38: =IF(AND($A38>=AO$8,$A38<=AO$9),IF(SUM(AO$10:AO37)-ROUNDDOWN($K38*AO$5/100,0)<-AO$6,-AO$6-SUM(AO$10:AO37),-ROUNDDOWN($K38*AO$5/100,0)),0) -> 0 | AP38: =IF(AND($A38>=AP$8,$A38<=AP$9),IF(SUM(AP$10:AP37)-ROUNDDOWN($K38*AP$5/100,0)<-AP$6,-AP$6-SUM(AP$10:AP37),-ROUNDDOWN($K38*AP$5/100,0)),0) -> 0 | AQ38: =IF(AND($A38>=AQ$8,$A38<=AQ$9),IF(SUM(AQ$10:AQ37)-ROUNDDOWN($K38*AQ$5/100,0)<-AQ$6,-AQ$6-SUM(AQ$10:AQ37),-ROUNDDOWN($K38*AQ$5/100,0)),0) -> 0 | AR38: =IF(AND($A38>=AR$8,$A38<=AR$9),IF(SUM(AR$10:AR37)-ROUNDDOWN($K38*AR$5/100,0)<-AR$6,-AR$6-SUM(AR$10:AR37),-ROUNDDOWN($K38*AR$5/100,0)),0) -> 0 | AS38: =IF(SUMIFS(AS$10:AS37,$A$10:$A37,$A38)-ROUNDDOWN($K38*$S38/100,0)<-$S38*1000,-$S38*1000-SUMIFS(AS$10:AS37,$A$10:$A37,$A38),-ROUNDDOWN($K38*$S38/100,0)) -> 0 | AT38: =IF(AND(X38="○",$A38>=AT$8,$A38<=AT$9,K38>=3980),IF(SUM(AT$10:AT37)-ROUNDDOWN($K38*AT$5/100,0)<-AT$6,-AT$6-SUM(AT$10:AT37),-ROUNDDOWN($K38*AT$5/100,0)),0) -> 0 | AU38: =IF(O38="○",IF(SUM(AU$10:AU37)-ROUNDDOWN($K38*AU$5/100,0)<-AU$6,-AU$6-SUM(AU$10:AU37),-ROUNDDOWN($K38*AU$5/100,0)),0) -> 0 | AV38: =IF(P38="○",IF(SUM(AV$10:AV37)-ROUNDDOWN($K38*AV$5/100,0)<-AV$6,-AV$6-SUM(AV$10:AV37),-ROUNDDOWN($K38*AV$5/100,0)),0) -> 0 | AW38: =IF(Q38="○",IF(SUM(AW$10:AW37)-ROUNDDOWN($K38*AW$5/100,0)<-AW$6,-AW$6-SUM(AW$10:AW37),-ROUNDDOWN($K38*AW$5/100,0)),0) -> 0 | AX38: =IF(R38="○",IF(SUM(AX$10:AX37)-ROUNDDOWN($K38*AX$5/100,0)<-AX$6,-AX$6-SUM(AX$10:AX37),-ROUNDDOWN($K38*AX$5/100,0)),0) -> 0 | AY38: 0 | AZ38: =-ROUNDDOWN($K38*AY38/100,0) -> 0 | BA38: =-ROUNDDOWN($K38*AI38/100,0) -> 0 | BC38: =-ROUNDDOWN($K38*BB38/100,0) -> 0 | BD38: 0 | BE38: =-ROUNDDOWN($K38*BD38/100,0) -> 0 | BF38: 0 | BG38: =-ROUNDDOWN($K38*BF38/100,0) -> 0 | BH38: 0 | BI38: =-ROUNDDOWN($K38*BH38/100,0) -> 0 | BJ38: =IF(AND(BJ$7="○",$A38>=BJ$8,$A38<=BJ$9),IF(SUM(BJ$10:BJ37)-ROUNDDOWN($M38*BJ$5/100,0)<-BJ$6,-BJ$6-SUM(BJ$10:BJ37),-ROUNDDOWN($M38*BJ$5/100,0)),0) -> 0 | BK38: =IF(AND(BK$7="○",$A38>=BK$8,$A38<=BK$9),IF(SUM(BK$10:BK37)-ROUNDDOWN($L38*BK$5/100,0)<-BK$6,-BK$6-SUM(BK$10:BK37),-ROUNDDOWN($L38*BK$5/100,0)),0) -> 0 | BL38: =IF(AND(BL$7="○",$A38>=BL$8,$A38<=BL$9),IF(SUM(BL$10:BL37)-ROUNDDOWN($L38*BL$5/100,0)<-BL$6,-BL$6-SUM(BL$10:BL37),-ROUNDDOWN($L38*BL$5/100,0)),0) -> 0 | BM38: =IF(AND(BM$7="○",$A38>=BM$8,$A38<=BM$9),IF(SUM(BM$10:BM37)-ROUNDDOWN($M38*BM$5/100,0)<-BM$6,-BM$6-SUM(BM$10:BM37),-ROUNDDOWN($M38*BM$5/100,0)),0) -> 0 | BN38: =IF(AND(BN$7="○",$A38>=BN$8,$A38<=BN$9),IF(SUM(BN$10:BN37)-ROUNDDOWN($M38*BN$5/100,0)<-BN$6,-BN$6-SUM(BN$10:BN37),-ROUNDDOWN($M38*BN$5/100,0)),0) -> 0 | BO38: =IF(AND(BO$7="○",$A38>=BO$8,$A38<=BO$9),IF(SUM(BO$10:BO37)-ROUNDDOWN($M38*BO$5/100,0)<-BO$6,-BO$6-SUM(BO$10:BO37),-ROUNDDOWN($M38*BO$5/100,0)),0) -> 0 | BP38: =IF(AND(BP$7="○",$A38>=BP$8,$A38<=BP$9),IF(SUM(BP$10:BP37)-ROUNDDOWN($M38*BP$5/100,0)<-BP$6,-BP$6-SUM(BP$10:BP37),-ROUNDDOWN($M38*BP$5/100,0)),0) -> 0 | BQ38: =IF(AND(BQ$7="○",$A38>=BQ$8,$A38<=BQ$9),IF(SUM(BQ$10:BQ37)-ROUNDDOWN($L38*BQ$5/100,0)<-BQ$6,-BQ$6-SUM(BQ$10:BQ37),-ROUNDDOWN($L38*BQ$5/100,0)),0) -> 0 | BR38: =IF(AND(BR$7="○",$A38>=BR$8,$A38<=BR$9),IF(SUM(BR$10:BR37)-ROUNDDOWN($M38*BR$5/100,0)<-BR$6,-BR$6-SUM(BR$10:BR37),-ROUNDDOWN($M38*BR$5/100,0)),0) -> 0 | BS38: =IF(AND(BS$7="○",$A38>=BS$8,$A38<=BS$9),IF(SUM(BS$10:BS37)-ROUNDDOWN($M38*BS$5/100,0)<-BS$6,-BS$6-SUM(BS$10:BS37),-ROUNDDOWN($M38*BS$5/100,0)),0) -> 0 | BT38: =IF(AND(BT$7="○",$A38>=BT$8,$A38<=BT$9),IF(SUM(BT$10:BT37)-ROUNDDOWN($M38*BT$5/100,0)<-BT$6,-BT$6-SUM(BT$10:BT37),-ROUNDDOWN($M38*BT$5/100,0)),0) -> 0 | BU38: =IF(AND(BU$7="○",$A38>=BU$8,$A38<=BU$9),IF(SUM(BU$10:BU37)-ROUNDDOWN($M38*BU$5/100,0)<-BU$6,-BU$6-SUM(BU$10:BU37),-ROUNDDOWN($M38*BU$5/100,0)),0) -> 0 | BV38: =IF(AND(BV$7="○",$A38>=BV$8,$A38<=BV$9),IF(SUM(BV$10:BV37)-ROUNDDOWN($M38*BV$5/100,0)<-BV$6,-BV$6-SUM(BV$10:BV37),-ROUNDDOWN($M38*BV$5/100,0)),0) -> 0 | BW38: =IF(AND(BW$7="○",$A38>=BW$8,$A38<=BW$9),IF(SUM(BW$10:BW37)-ROUNDDOWN($M38*BW$5/100,0)<-BW$6,-BW$6-SUM(BW$10:BW37),-ROUNDDOWN($M38*BW$5/100,0)),0) -> 0 | BX38: =IF(AND(T38="○",$A38>=BX$8,$A38<=BX$9),IF(SUM(BX$10:BX37)-ROUNDDOWN($K38*BX$5/100,0)<-BX$6,-BX$6-SUM(BX$10:BX37),-ROUNDDOWN($K38*BX$5/100,0)),0) -> 0 | BY38: =IF(AND(U38="○",$A38>=BY$8,$A38<=BY$9),IF(SUM(BY$10:BY37)-ROUNDDOWN($K38*BY$5/100,0)<-BY$6,-BY$6-SUM(BY$10:BY37),-ROUNDDOWN($K38*BY$5/100,0)),0) -> 0 | BZ38: =IF(AND(V38="○",$A38>=BZ$8,$A38<=BZ$9),IF(SUM(BZ$10:BZ37)-ROUNDDOWN($K38*BZ$5/100,0)<-BZ$6,-BZ$6-SUM(BZ$10:BZ37),-ROUNDDOWN($K38*BZ$5/100,0)),0) -> 0 | CA38: =IF(AND(W38="○",$A38>=CA$8,$A38<=CA$9),IF(SUM(CA$10:CA37)-ROUNDDOWN($K38*CA$5/100,0)<-CA$6,-CA$6-SUM(CA$10:CA37),-ROUNDDOWN($K38*CA$5/100,0)),0) -> 0 | CG38: =+SUM(AJ38:CF38,BC38,BE38,AZ38,BA38,BG38,BI38) -> 0 | CH38: =+CG38+N38 -> 0 | CI38: =IFERROR(ROUNDDOWN((CH38/G38),0),0) -> 0 | CO38: =IFERROR(CN38-CI38,0) -> 0 | CP38: =IFERROR(CN38/CI38,0) -> 0 | CR38: =+CO38*G38 -> 0 | CT38: =INDEX([2]マスタ!$A:$A,MATCH(D38,[2]マスタ!$C:$C,0)) -> #N/A | CU38: =IFERROR(TEXT(TODAY(),"yyyymmdd")&"_"&ROUNDDOWN(H38+I38,0)&"-"&ROUNDDOWN(CI38,0),"") -> 20260620_0-0
G39: 1 | H39: =+F39*G39 -> 0 | K39: =+ROUNDDOWN((H39+I39+J39)/100,0)*100 -> 0 | L39: =+ROUNDDOWN((H39+I39)/1.1/100,0)*100 -> 0 | M39: =+ROUNDDOWN((H39+I39)/1.1/200,0)*200 -> 0 | N39: =+H39+I39+J39 -> 0 | O39: =IF(OR(WEEKDAY($A39,2)=2,WEEKDAY($A39,2)=4),"○","✕") -> ✕ | P39: =+IF(MOD(TEXT($A39,"DD"),5)=0,"○","✕") -> ○ | Q39: =+IF((TEXT(A39,"DD")+0)=1,"○","✕") -> ✕ | R39: =+IF((TEXT($A39,"DD")+0)=18,"○","✕") -> ✕ | S39: 0 | T39: ✕ | U39: ✕ | V39: ✕ | W39: ✕ | X39: ○ | Y39: ✕ | Z39: ✕ | AA39: ✕ | AB39: ✕ | AC39: ✕ | AD39: =+IF(ISERROR(VLOOKUP($B39,AD$10:AD38,1,0)),IF(AND($N39>=1000,$A39>=AO$8,$A39<=AO$9),$B39,""),"") | AE39: =+IF(ISERROR(VLOOKUP($B39,AE$10:AE38,1,0)),IF(AND($N39>=1000,$A39>=AP$8,$A39<=AP$9),$B39,""),"") | AF39: =+IF(ISERROR(VLOOKUP($B39,AF$10:AF38,1,0)),IF(AND($N39>=1000,$A39>=AQ$8,$A39<=AQ$9),$B39,""),"") | AG39: =+IF(ISERROR(VLOOKUP($B39,AG$10:AG38,1,0)),IF(AND($N39>=1000,$A39>=AR$8,$A39<=AR$9),$B39,""),"") | AI39: 0 | AJ39: =IF(AND(AJ$7="○",$A39>=AJ$8,$A39<=AJ$9),IF(SUM(AJ$10:AJ38)-ROUNDDOWN($K39*AJ$5/100,0)<-AJ$6,-AJ$6-SUM(AJ$10:AJ38),-ROUNDDOWN($K39*AJ$5/100,0)),0) -> 0 | AK39: =IF(AND(AK$7="○",$A39>=AK$8,$A39<=AK$9),IF(SUM(AK$10:AK38)-ROUNDDOWN($L39*AK$5/100,0)<-AK$6,-AK$6-SUM(AK$10:AK38),-ROUNDDOWN($L39*AK$5/100,0)),0) -> 0 | AL39: =IF(AND(AL$7="○",$A39>=AL$8,$A39<=AL$9),IF(SUM(AL$10:AL38)-ROUNDDOWN($N39*AL$5/100,0)<-AL$6,-AL$6-SUM(AL$10:AL38),-ROUNDDOWN($N39*AL$5/100,0)),0) -> 0 | AM39: =IF(AND(AM$7="○",$A39>=AM$8,$A39<=AM$9),IF(SUM(AM$10:AM38)-ROUNDDOWN($L39*AM$5/100,0)<-AM$6,-AM$6-SUM(AM$10:AM38),-ROUNDDOWN($L39*AM$5/100,0)),0) -> 0 | AN39: =IF(AND(AN$7="○",$A39>=AN$8,$A39<=AN$9),IF(SUM(AN$10:AN38)-ROUNDDOWN($M39*AN$5/100,0)<-AN$6,-AN$6-SUM(AN$10:AN38),-ROUNDDOWN($M39*AN$5/100,0)),0) -> 0 | AO39: =IF(AND($A39>=AO$8,$A39<=AO$9),IF(SUM(AO$10:AO38)-ROUNDDOWN($K39*AO$5/100,0)<-AO$6,-AO$6-SUM(AO$10:AO38),-ROUNDDOWN($K39*AO$5/100,0)),0) -> 0 | AP39: =IF(AND($A39>=AP$8,$A39<=AP$9),IF(SUM(AP$10:AP38)-ROUNDDOWN($K39*AP$5/100,0)<-AP$6,-AP$6-SUM(AP$10:AP38),-ROUNDDOWN($K39*AP$5/100,0)),0) -> 0 | AQ39: =IF(AND($A39>=AQ$8,$A39<=AQ$9),IF(SUM(AQ$10:AQ38)-ROUNDDOWN($K39*AQ$5/100,0)<-AQ$6,-AQ$6-SUM(AQ$10:AQ38),-ROUNDDOWN($K39*AQ$5/100,0)),0) -> 0 | AR39: =IF(AND($A39>=AR$8,$A39<=AR$9),IF(SUM(AR$10:AR38)-ROUNDDOWN($K39*AR$5/100,0)<-AR$6,-AR$6-SUM(AR$10:AR38),-ROUNDDOWN($K39*AR$5/100,0)),0) -> 0 | AS39: =IF(SUMIFS(AS$10:AS38,$A$10:$A38,$A39)-ROUNDDOWN($K39*$S39/100,0)<-$S39*1000,-$S39*1000-SUMIFS(AS$10:AS38,$A$10:$A38,$A39),-ROUNDDOWN($K39*$S39/100,0)) -> 0 | AT39: =IF(AND(X39="○",$A39>=AT$8,$A39<=AT$9,K39>=3980),IF(SUM(AT$10:AT38)-ROUNDDOWN($K39*AT$5/100,0)<-AT$6,-AT$6-SUM(AT$10:AT38),-ROUNDDOWN($K39*AT$5/100,0)),0) -> 0 | AU39: =IF(O39="○",IF(SUM(AU$10:AU38)-ROUNDDOWN($K39*AU$5/100,0)<-AU$6,-AU$6-SUM(AU$10:AU38),-ROUNDDOWN($K39*AU$5/100,0)),0) -> 0 | AV39: =IF(P39="○",IF(SUM(AV$10:AV38)-ROUNDDOWN($K39*AV$5/100,0)<-AV$6,-AV$6-SUM(AV$10:AV38),-ROUNDDOWN($K39*AV$5/100,0)),0) -> 0 | AW39: =IF(Q39="○",IF(SUM(AW$10:AW38)-ROUNDDOWN($K39*AW$5/100,0)<-AW$6,-AW$6-SUM(AW$10:AW38),-ROUNDDOWN($K39*AW$5/100,0)),0) -> 0 | AX39: =IF(R39="○",IF(SUM(AX$10:AX38)-ROUNDDOWN($K39*AX$5/100,0)<-AX$6,-AX$6-SUM(AX$10:AX38),-ROUNDDOWN($K39*AX$5/100,0)),0) -> 0 | AY39: 0 | AZ39: =-ROUNDDOWN($K39*AY39/100,0) -> 0 | BA39: =-ROUNDDOWN($K39*AI39/100,0) -> 0 | BC39: =-ROUNDDOWN($K39*BB39/100,0) -> 0 | BD39: 0 | BE39: =-ROUNDDOWN($K39*BD39/100,0) -> 0 | BF39: 0 | BG39: =-ROUNDDOWN($K39*BF39/100,0) -> 0 | BH39: 0 | BI39: =-ROUNDDOWN($K39*BH39/100,0) -> 0 | BJ39: =IF(AND(BJ$7="○",$A39>=BJ$8,$A39<=BJ$9),IF(SUM(BJ$10:BJ38)-ROUNDDOWN($M39*BJ$5/100,0)<-BJ$6,-BJ$6-SUM(BJ$10:BJ38),-ROUNDDOWN($M39*BJ$5/100,0)),0) -> 0 | BK39: =IF(AND(BK$7="○",$A39>=BK$8,$A39<=BK$9),IF(SUM(BK$10:BK38)-ROUNDDOWN($L39*BK$5/100,0)<-BK$6,-BK$6-SUM(BK$10:BK38),-ROUNDDOWN($L39*BK$5/100,0)),0) -> 0 | BL39: =IF(AND(BL$7="○",$A39>=BL$8,$A39<=BL$9),IF(SUM(BL$10:BL38)-ROUNDDOWN($L39*BL$5/100,0)<-BL$6,-BL$6-SUM(BL$10:BL38),-ROUNDDOWN($L39*BL$5/100,0)),0) -> 0 | BM39: =IF(AND(BM$7="○",$A39>=BM$8,$A39<=BM$9),IF(SUM(BM$10:BM38)-ROUNDDOWN($M39*BM$5/100,0)<-BM$6,-BM$6-SUM(BM$10:BM38),-ROUNDDOWN($M39*BM$5/100,0)),0) -> 0 | BN39: =IF(AND(BN$7="○",$A39>=BN$8,$A39<=BN$9),IF(SUM(BN$10:BN38)-ROUNDDOWN($M39*BN$5/100,0)<-BN$6,-BN$6-SUM(BN$10:BN38),-ROUNDDOWN($M39*BN$5/100,0)),0) -> 0 | BO39: =IF(AND(BO$7="○",$A39>=BO$8,$A39<=BO$9),IF(SUM(BO$10:BO38)-ROUNDDOWN($M39*BO$5/100,0)<-BO$6,-BO$6-SUM(BO$10:BO38),-ROUNDDOWN($M39*BO$5/100,0)),0) -> 0 | BP39: =IF(AND(BP$7="○",$A39>=BP$8,$A39<=BP$9),IF(SUM(BP$10:BP38)-ROUNDDOWN($M39*BP$5/100,0)<-BP$6,-BP$6-SUM(BP$10:BP38),-ROUNDDOWN($M39*BP$5/100,0)),0) -> 0 | BQ39: =IF(AND(BQ$7="○",$A39>=BQ$8,$A39<=BQ$9),IF(SUM(BQ$10:BQ38)-ROUNDDOWN($L39*BQ$5/100,0)<-BQ$6,-BQ$6-SUM(BQ$10:BQ38),-ROUNDDOWN($L39*BQ$5/100,0)),0) -> 0 | BR39: =IF(AND(BR$7="○",$A39>=BR$8,$A39<=BR$9),IF(SUM(BR$10:BR38)-ROUNDDOWN($M39*BR$5/100,0)<-BR$6,-BR$6-SUM(BR$10:BR38),-ROUNDDOWN($M39*BR$5/100,0)),0) -> 0 | BS39: =IF(AND(BS$7="○",$A39>=BS$8,$A39<=BS$9),IF(SUM(BS$10:BS38)-ROUNDDOWN($M39*BS$5/100,0)<-BS$6,-BS$6-SUM(BS$10:BS38),-ROUNDDOWN($M39*BS$5/100,0)),0) -> 0 | BT39: =IF(AND(BT$7="○",$A39>=BT$8,$A39<=BT$9),IF(SUM(BT$10:BT38)-ROUNDDOWN($M39*BT$5/100,0)<-BT$6,-BT$6-SUM(BT$10:BT38),-ROUNDDOWN($M39*BT$5/100,0)),0) -> 0 | BU39: =IF(AND(BU$7="○",$A39>=BU$8,$A39<=BU$9),IF(SUM(BU$10:BU38)-ROUNDDOWN($M39*BU$5/100,0)<-BU$6,-BU$6-SUM(BU$10:BU38),-ROUNDDOWN($M39*BU$5/100,0)),0) -> 0 | BV39: =IF(AND(BV$7="○",$A39>=BV$8,$A39<=BV$9),IF(SUM(BV$10:BV38)-ROUNDDOWN($M39*BV$5/100,0)<-BV$6,-BV$6-SUM(BV$10:BV38),-ROUNDDOWN($M39*BV$5/100,0)),0) -> 0 | BW39: =IF(AND(BW$7="○",$A39>=BW$8,$A39<=BW$9),IF(SUM(BW$10:BW38)-ROUNDDOWN($M39*BW$5/100,0)<-BW$6,-BW$6-SUM(BW$10:BW38),-ROUNDDOWN($M39*BW$5/100,0)),0) -> 0 | BX39: =IF(AND(T39="○",$A39>=BX$8,$A39<=BX$9),IF(SUM(BX$10:BX38)-ROUNDDOWN($K39*BX$5/100,0)<-BX$6,-BX$6-SUM(BX$10:BX38),-ROUNDDOWN($K39*BX$5/100,0)),0) -> 0 | BY39: =IF(AND(U39="○",$A39>=BY$8,$A39<=BY$9),IF(SUM(BY$10:BY38)-ROUNDDOWN($K39*BY$5/100,0)<-BY$6,-BY$6-SUM(BY$10:BY38),-ROUNDDOWN($K39*BY$5/100,0)),0) -> 0 | BZ39: =IF(AND(V39="○",$A39>=BZ$8,$A39<=BZ$9),IF(SUM(BZ$10:BZ38)-ROUNDDOWN($K39*BZ$5/100,0)<-BZ$6,-BZ$6-SUM(BZ$10:BZ38),-ROUNDDOWN($K39*BZ$5/100,0)),0) -> 0 | CA39: =IF(AND(W39="○",$A39>=CA$8,$A39<=CA$9),IF(SUM(CA$10:CA38)-ROUNDDOWN($K39*CA$5/100,0)<-CA$6,-CA$6-SUM(CA$10:CA38),-ROUNDDOWN($K39*CA$5/100,0)),0) -> 0 | CG39: =+SUM(AJ39:CF39,BC39,BE39,AZ39,BA39,BG39,BI39) -> 0 | CH39: =+CG39+N39 -> 0 | CI39: =IFERROR(ROUNDDOWN((CH39/G39),0),0) -> 0 | CO39: =IFERROR(CN39-CI39,0) -> 0 | CP39: =IFERROR(CN39/CI39,0) -> 0 | CR39: =+CO39*G39 -> 0 | CT39: =INDEX([2]マスタ!$A:$A,MATCH(D39,[2]マスタ!$C:$C,0)) -> #N/A | CU39: =IFERROR(TEXT(TODAY(),"yyyymmdd")&"_"&ROUNDDOWN(H39+I39,0)&"-"&ROUNDDOWN(CI39,0),"") -> 20260620_0-0
G40: 1 | H40: =+F40*G40 -> 0 | K40: =+ROUNDDOWN((H40+I40+J40)/100,0)*100 -> 0 | L40: =+ROUNDDOWN((H40+I40)/1.1/100,0)*100 -> 0 | M40: =+ROUNDDOWN((H40+I40)/1.1/200,0)*200 -> 0 | N40: =+H40+I40+J40 -> 0 | O40: =IF(OR(WEEKDAY($A40,2)=2,WEEKDAY($A40,2)=4),"○","✕") -> ✕ | P40: =+IF(MOD(TEXT($A40,"DD"),5)=0,"○","✕") -> ○ | Q40: =+IF((TEXT(A40,"DD")+0)=1,"○","✕") -> ✕ | R40: =+IF((TEXT($A40,"DD")+0)=18,"○","✕") -> ✕ | S40: 0 | T40: ✕ | U40: ✕ | V40: ✕ | W40: ✕ | X40: ○ | Y40: ✕ | Z40: ✕ | AA40: ✕ | AB40: ✕ | AC40: ✕ | AD40: =+IF(ISERROR(VLOOKUP($B40,AD$10:AD39,1,0)),IF(AND($N40>=1000,$A40>=AO$8,$A40<=AO$9),$B40,""),"") | AE40: =+IF(ISERROR(VLOOKUP($B40,AE$10:AE39,1,0)),IF(AND($N40>=1000,$A40>=AP$8,$A40<=AP$9),$B40,""),"") | AF40: =+IF(ISERROR(VLOOKUP($B40,AF$10:AF39,1,0)),IF(AND($N40>=1000,$A40>=AQ$8,$A40<=AQ$9),$B40,""),"") | AG40: =+IF(ISERROR(VLOOKUP($B40,AG$10:AG39,1,0)),IF(AND($N40>=1000,$A40>=AR$8,$A40<=AR$9),$B40,""),"") | AI40: 0 | AJ40: =IF(AND(AJ$7="○",$A40>=AJ$8,$A40<=AJ$9),IF(SUM(AJ$10:AJ39)-ROUNDDOWN($K40*AJ$5/100,0)<-AJ$6,-AJ$6-SUM(AJ$10:AJ39),-ROUNDDOWN($K40*AJ$5/100,0)),0) -> 0 | AK40: =IF(AND(AK$7="○",$A40>=AK$8,$A40<=AK$9),IF(SUM(AK$10:AK39)-ROUNDDOWN($L40*AK$5/100,0)<-AK$6,-AK$6-SUM(AK$10:AK39),-ROUNDDOWN($L40*AK$5/100,0)),0) -> 0 | AL40: =IF(AND(AL$7="○",$A40>=AL$8,$A40<=AL$9),IF(SUM(AL$10:AL39)-ROUNDDOWN($N40*AL$5/100,0)<-AL$6,-AL$6-SUM(AL$10:AL39),-ROUNDDOWN($N40*AL$5/100,0)),0) -> 0 | AM40: =IF(AND(AM$7="○",$A40>=AM$8,$A40<=AM$9),IF(SUM(AM$10:AM39)-ROUNDDOWN($L40*AM$5/100,0)<-AM$6,-AM$6-SUM(AM$10:AM39),-ROUNDDOWN($L40*AM$5/100,0)),0) -> 0 | AN40: =IF(AND(AN$7="○",$A40>=AN$8,$A40<=AN$9),IF(SUM(AN$10:AN39)-ROUNDDOWN($M40*AN$5/100,0)<-AN$6,-AN$6-SUM(AN$10:AN39),-ROUNDDOWN($M40*AN$5/100,0)),0) -> 0 | AO40: =IF(AND($A40>=AO$8,$A40<=AO$9),IF(SUM(AO$10:AO39)-ROUNDDOWN($K40*AO$5/100,0)<-AO$6,-AO$6-SUM(AO$10:AO39),-ROUNDDOWN($K40*AO$5/100,0)),0) -> 0 | AP40: =IF(AND($A40>=AP$8,$A40<=AP$9),IF(SUM(AP$10:AP39)-ROUNDDOWN($K40*AP$5/100,0)<-AP$6,-AP$6-SUM(AP$10:AP39),-ROUNDDOWN($K40*AP$5/100,0)),0) -> 0 | AQ40: =IF(AND($A40>=AQ$8,$A40<=AQ$9),IF(SUM(AQ$10:AQ39)-ROUNDDOWN($K40*AQ$5/100,0)<-AQ$6,-AQ$6-SUM(AQ$10:AQ39),-ROUNDDOWN($K40*AQ$5/100,0)),0) -> 0 | AR40: =IF(AND($A40>=AR$8,$A40<=AR$9),IF(SUM(AR$10:AR39)-ROUNDDOWN($K40*AR$5/100,0)<-AR$6,-AR$6-SUM(AR$10:AR39),-ROUNDDOWN($K40*AR$5/100,0)),0) -> 0 | AS40: =IF(SUMIFS(AS$10:AS39,$A$10:$A39,$A40)-ROUNDDOWN($K40*$S40/100,0)<-$S40*1000,-$S40*1000-SUMIFS(AS$10:AS39,$A$10:$A39,$A40),-ROUNDDOWN($K40*$S40/100,0)) -> 0 | AT40: =IF(AND(X40="○",$A40>=AT$8,$A40<=AT$9,K40>=3980),IF(SUM(AT$10:AT39)-ROUNDDOWN($K40*AT$5/100,0)<-AT$6,-AT$6-SUM(AT$10:AT39),-ROUNDDOWN($K40*AT$5/100,0)),0) -> 0 | AU40: =IF(O40="○",IF(SUM(AU$10:AU39)-ROUNDDOWN($K40*AU$5/100,0)<-AU$6,-AU$6-SUM(AU$10:AU39),-ROUNDDOWN($K40*AU$5/100,0)),0) -> 0 | AV40: =IF(P40="○",IF(SUM(AV$10:AV39)-ROUNDDOWN($K40*AV$5/100,0)<-AV$6,-AV$6-SUM(AV$10:AV39),-ROUNDDOWN($K40*AV$5/100,0)),0) -> 0 | AW40: =IF(Q40="○",IF(SUM(AW$10:AW39)-ROUNDDOWN($K40*AW$5/100,0)<-AW$6,-AW$6-SUM(AW$10:AW39),-ROUNDDOWN($K40*AW$5/100,0)),0) -> 0 | AX40: =IF(R40="○",IF(SUM(AX$10:AX39)-ROUNDDOWN($K40*AX$5/100,0)<-AX$6,-AX$6-SUM(AX$10:AX39),-ROUNDDOWN($K40*AX$5/100,0)),0) -> 0 | AY40: 0 | AZ40: =-ROUNDDOWN($K40*AY40/100,0) -> 0 | BA40: =-ROUNDDOWN($K40*AI40/100,0) -> 0 | BC40: =-ROUNDDOWN($K40*BB40/100,0) -> 0 | BD40: 0 | BE40: =-ROUNDDOWN($K40*BD40/100,0) -> 0 | BF40: 0 | BG40: =-ROUNDDOWN($K40*BF40/100,0) -> 0 | BH40: 0 | BI40: =-ROUNDDOWN($K40*BH40/100,0) -> 0 | BJ40: =IF(AND(BJ$7="○",$A40>=BJ$8,$A40<=BJ$9),IF(SUM(BJ$10:BJ39)-ROUNDDOWN($M40*BJ$5/100,0)<-BJ$6,-BJ$6-SUM(BJ$10:BJ39),-ROUNDDOWN($M40*BJ$5/100,0)),0) -> 0 | BK40: =IF(AND(BK$7="○",$A40>=BK$8,$A40<=BK$9),IF(SUM(BK$10:BK39)-ROUNDDOWN($L40*BK$5/100,0)<-BK$6,-BK$6-SUM(BK$10:BK39),-ROUNDDOWN($L40*BK$5/100,0)),0) -> 0 | BL40: =IF(AND(BL$7="○",$A40>=BL$8,$A40<=BL$9),IF(SUM(BL$10:BL39)-ROUNDDOWN($L40*BL$5/100,0)<-BL$6,-BL$6-SUM(BL$10:BL39),-ROUNDDOWN($L40*BL$5/100,0)),0) -> 0 | BM40: =IF(AND(BM$7="○",$A40>=BM$8,$A40<=BM$9),IF(SUM(BM$10:BM39)-ROUNDDOWN($M40*BM$5/100,0)<-BM$6,-BM$6-SUM(BM$10:BM39),-ROUNDDOWN($M40*BM$5/100,0)),0) -> 0 | BN40: =IF(AND(BN$7="○",$A40>=BN$8,$A40<=BN$9),IF(SUM(BN$10:BN39)-ROUNDDOWN($M40*BN$5/100,0)<-BN$6,-BN$6-SUM(BN$10:BN39),-ROUNDDOWN($M40*BN$5/100,0)),0) -> 0 | BO40: =IF(AND(BO$7="○",$A40>=BO$8,$A40<=BO$9),IF(SUM(BO$10:BO39)-ROUNDDOWN($M40*BO$5/100,0)<-BO$6,-BO$6-SUM(BO$10:BO39),-ROUNDDOWN($M40*BO$5/100,0)),0) -> 0 | BP40: =IF(AND(BP$7="○",$A40>=BP$8,$A40<=BP$9),IF(SUM(BP$10:BP39)-ROUNDDOWN($M40*BP$5/100,0)<-BP$6,-BP$6-SUM(BP$10:BP39),-ROUNDDOWN($M40*BP$5/100,0)),0) -> 0 | BQ40: =IF(AND(BQ$7="○",$A40>=BQ$8,$A40<=BQ$9),IF(SUM(BQ$10:BQ39)-ROUNDDOWN($L40*BQ$5/100,0)<-BQ$6,-BQ$6-SUM(BQ$10:BQ39),-ROUNDDOWN($L40*BQ$5/100,0)),0) -> 0 | BR40: =IF(AND(BR$7="○",$A40>=BR$8,$A40<=BR$9),IF(SUM(BR$10:BR39)-ROUNDDOWN($M40*BR$5/100,0)<-BR$6,-BR$6-SUM(BR$10:BR39),-ROUNDDOWN($M40*BR$5/100,0)),0) -> 0 | BS40: =IF(AND(BS$7="○",$A40>=BS$8,$A40<=BS$9),IF(SUM(BS$10:BS39)-ROUNDDOWN($M40*BS$5/100,0)<-BS$6,-BS$6-SUM(BS$10:BS39),-ROUNDDOWN($M40*BS$5/100,0)),0) -> 0 | BT40: =IF(AND(BT$7="○",$A40>=BT$8,$A40<=BT$9),IF(SUM(BT$10:BT39)-ROUNDDOWN($M40*BT$5/100,0)<-BT$6,-BT$6-SUM(BT$10:BT39),-ROUNDDOWN($M40*BT$5/100,0)),0) -> 0 | BU40: =IF(AND(BU$7="○",$A40>=BU$8,$A40<=BU$9),IF(SUM(BU$10:BU39)-ROUNDDOWN($M40*BU$5/100,0)<-BU$6,-BU$6-SUM(BU$10:BU39),-ROUNDDOWN($M40*BU$5/100,0)),0) -> 0 | BV40: =IF(AND(BV$7="○",$A40>=BV$8,$A40<=BV$9),IF(SUM(BV$10:BV39)-ROUNDDOWN($M40*BV$5/100,0)<-BV$6,-BV$6-SUM(BV$10:BV39),-ROUNDDOWN($M40*BV$5/100,0)),0) -> 0 | BW40: =IF(AND(BW$7="○",$A40>=BW$8,$A40<=BW$9),IF(SUM(BW$10:BW39)-ROUNDDOWN($M40*BW$5/100,0)<-BW$6,-BW$6-SUM(BW$10:BW39),-ROUNDDOWN($M40*BW$5/100,0)),0) -> 0 | BX40: =IF(AND(T40="○",$A40>=BX$8,$A40<=BX$9),IF(SUM(BX$10:BX39)-ROUNDDOWN($K40*BX$5/100,0)<-BX$6,-BX$6-SUM(BX$10:BX39),-ROUNDDOWN($K40*BX$5/100,0)),0) -> 0 | BY40: =IF(AND(U40="○",$A40>=BY$8,$A40<=BY$9),IF(SUM(BY$10:BY39)-ROUNDDOWN($K40*BY$5/100,0)<-BY$6,-BY$6-SUM(BY$10:BY39),-ROUNDDOWN($K40*BY$5/100,0)),0) -> 0 | BZ40: =IF(AND(V40="○",$A40>=BZ$8,$A40<=BZ$9),IF(SUM(BZ$10:BZ39)-ROUNDDOWN($K40*BZ$5/100,0)<-BZ$6,-BZ$6-SUM(BZ$10:BZ39),-ROUNDDOWN($K40*BZ$5/100,0)),0) -> 0 | CA40: =IF(AND(W40="○",$A40>=CA$8,$A40<=CA$9),IF(SUM(CA$10:CA39)-ROUNDDOWN($K40*CA$5/100,0)<-CA$6,-CA$6-SUM(CA$10:CA39),-ROUNDDOWN($K40*CA$5/100,0)),0) -> 0 | CG40: =+SUM(AJ40:CF40,BC40,BE40,AZ40,BA40,BG40,BI40) -> 0 | CH40: =+CG40+N40 -> 0 | CI40: =IFERROR(ROUNDDOWN((CH40/G40),0),0) -> 0 | CO40: =IFERROR(CN40-CI40,0) -> 0 | CP40: =IFERROR(CN40/CI40,0) -> 0 | CR40: =+CO40*G40 -> 0 | CT40: =INDEX([2]マスタ!$A:$A,MATCH(D40,[2]マスタ!$C:$C,0)) -> #N/A | CU40: =IFERROR(TEXT(TODAY(),"yyyymmdd")&"_"&ROUNDDOWN(H40+I40,0)&"-"&ROUNDDOWN(CI40,0),"") -> 20260620_0-0
G41: 1 | H41: =+F41*G41 -> 0 | K41: =+ROUNDDOWN((H41+I41+J41)/100,0)*100 -> 0 | L41: =+ROUNDDOWN((H41+I41)/1.1/100,0)*100 -> 0 | M41: =+ROUNDDOWN((H41+I41)/1.1/200,0)*200 -> 0 | N41: =+H41+I41+J41 -> 0 | O41: =IF(OR(WEEKDAY($A41,2)=2,WEEKDAY($A41,2)=4),"○","✕") -> ✕ | P41: =+IF(MOD(TEXT($A41,"DD"),5)=0,"○","✕") -> ○ | Q41: =+IF((TEXT(A41,"DD")+0)=1,"○","✕") -> ✕ | R41: =+IF((TEXT($A41,"DD")+0)=18,"○","✕") -> ✕ | S41: 0 | T41: ✕ | U41: ✕ | V41: ✕ | W41: ✕ | X41: ○ | Y41: ✕ | Z41: ✕ | AA41: ✕ | AB41: ✕ | AC41: ✕ | AD41: =+IF(ISERROR(VLOOKUP($B41,AD$10:AD40,1,0)),IF(AND($N41>=1000,$A41>=AO$8,$A41<=AO$9),$B41,""),"") | AE41: =+IF(ISERROR(VLOOKUP($B41,AE$10:AE40,1,0)),IF(AND($N41>=1000,$A41>=AP$8,$A41<=AP$9),$B41,""),"") | AF41: =+IF(ISERROR(VLOOKUP($B41,AF$10:AF40,1,0)),IF(AND($N41>=1000,$A41>=AQ$8,$A41<=AQ$9),$B41,""),"") | AG41: =+IF(ISERROR(VLOOKUP($B41,AG$10:AG40,1,0)),IF(AND($N41>=1000,$A41>=AR$8,$A41<=AR$9),$B41,""),"") | AI41: 0 | AJ41: =IF(AND(AJ$7="○",$A41>=AJ$8,$A41<=AJ$9),IF(SUM(AJ$10:AJ40)-ROUNDDOWN($K41*AJ$5/100,0)<-AJ$6,-AJ$6-SUM(AJ$10:AJ40),-ROUNDDOWN($K41*AJ$5/100,0)),0) -> 0 | AK41: =IF(AND(AK$7="○",$A41>=AK$8,$A41<=AK$9),IF(SUM(AK$10:AK40)-ROUNDDOWN($L41*AK$5/100,0)<-AK$6,-AK$6-SUM(AK$10:AK40),-ROUNDDOWN($L41*AK$5/100,0)),0) -> 0 | AL41: =IF(AND(AL$7="○",$A41>=AL$8,$A41<=AL$9),IF(SUM(AL$10:AL40)-ROUNDDOWN($N41*AL$5/100,0)<-AL$6,-AL$6-SUM(AL$10:AL40),-ROUNDDOWN($N41*AL$5/100,0)),0) -> 0 | AM41: =IF(AND(AM$7="○",$A41>=AM$8,$A41<=AM$9),IF(SUM(AM$10:AM40)-ROUNDDOWN($L41*AM$5/100,0)<-AM$6,-AM$6-SUM(AM$10:AM40),-ROUNDDOWN($L41*AM$5/100,0)),0) -> 0 | AN41: =IF(AND(AN$7="○",$A41>=AN$8,$A41<=AN$9),IF(SUM(AN$10:AN40)-ROUNDDOWN($M41*AN$5/100,0)<-AN$6,-AN$6-SUM(AN$10:AN40),-ROUNDDOWN($M41*AN$5/100,0)),0) -> 0 | AO41: =IF(AND($A41>=AO$8,$A41<=AO$9),IF(SUM(AO$10:AO40)-ROUNDDOWN($K41*AO$5/100,0)<-AO$6,-AO$6-SUM(AO$10:AO40),-ROUNDDOWN($K41*AO$5/100,0)),0) -> 0 | AP41: =IF(AND($A41>=AP$8,$A41<=AP$9),IF(SUM(AP$10:AP40)-ROUNDDOWN($K41*AP$5/100,0)<-AP$6,-AP$6-SUM(AP$10:AP40),-ROUNDDOWN($K41*AP$5/100,0)),0) -> 0 | AQ41: =IF(AND($A41>=AQ$8,$A41<=AQ$9),IF(SUM(AQ$10:AQ40)-ROUNDDOWN($K41*AQ$5/100,0)<-AQ$6,-AQ$6-SUM(AQ$10:AQ40),-ROUNDDOWN($K41*AQ$5/100,0)),0) -> 0 | AR41: =IF(AND($A41>=AR$8,$A41<=AR$9),IF(SUM(AR$10:AR40)-ROUNDDOWN($K41*AR$5/100,0)<-AR$6,-AR$6-SUM(AR$10:AR40),-ROUNDDOWN($K41*AR$5/100,0)),0) -> 0 | AS41: =IF(SUMIFS(AS$10:AS40,$A$10:$A40,$A41)-ROUNDDOWN($K41*$S41/100,0)<-$S41*1000,-$S41*1000-SUMIFS(AS$10:AS40,$A$10:$A40,$A41),-ROUNDDOWN($K41*$S41/100,0)) -> 0 | AT41: =IF(AND(X41="○",$A41>=AT$8,$A41<=AT$9,K41>=3980),IF(SUM(AT$10:AT40)-ROUNDDOWN($K41*AT$5/100,0)<-AT$6,-AT$6-SUM(AT$10:AT40),-ROUNDDOWN($K41*AT$5/100,0)),0) -> 0 | AU41: =IF(O41="○",IF(SUM(AU$10:AU40)-ROUNDDOWN($K41*AU$5/100,0)<-AU$6,-AU$6-SUM(AU$10:AU40),-ROUNDDOWN($K41*AU$5/100,0)),0) -> 0 | AV41: =IF(P41="○",IF(SUM(AV$10:AV40)-ROUNDDOWN($K41*AV$5/100,0)<-AV$6,-AV$6-SUM(AV$10:AV40),-ROUNDDOWN($K41*AV$5/100,0)),0) -> 0 | AW41: =IF(Q41="○",IF(SUM(AW$10:AW40)-ROUNDDOWN($K41*AW$5/100,0)<-AW$6,-AW$6-SUM(AW$10:AW40),-ROUNDDOWN($K41*AW$5/100,0)),0) -> 0 | AX41: =IF(R41="○",IF(SUM(AX$10:AX40)-ROUNDDOWN($K41*AX$5/100,0)<-AX$6,-AX$6-SUM(AX$10:AX40),-ROUNDDOWN($K41*AX$5/100,0)),0) -> 0 | AY41: 0 | AZ41: =-ROUNDDOWN($K41*AY41/100,0) -> 0 | BA41: =-ROUNDDOWN($K41*AI41/100,0) -> 0 | BC41: =-ROUNDDOWN($K41*BB41/100,0) -> 0 | BD41: 0 | BE41: =-ROUNDDOWN($K41*BD41/100,0) -> 0 | BF41: 0 | BG41: =-ROUNDDOWN($K41*BF41/100,0) -> 0 | BH41: 0 | BI41: =-ROUNDDOWN($K41*BH41/100,0) -> 0 | BJ41: =IF(AND(BJ$7="○",$A41>=BJ$8,$A41<=BJ$9),IF(SUM(BJ$10:BJ40)-ROUNDDOWN($M41*BJ$5/100,0)<-BJ$6,-BJ$6-SUM(BJ$10:BJ40),-ROUNDDOWN($M41*BJ$5/100,0)),0) -> 0 | BK41: =IF(AND(BK$7="○",$A41>=BK$8,$A41<=BK$9),IF(SUM(BK$10:BK40)-ROUNDDOWN($L41*BK$5/100,0)<-BK$6,-BK$6-SUM(BK$10:BK40),-ROUNDDOWN($L41*BK$5/100,0)),0) -> 0 | BL41: =IF(AND(BL$7="○",$A41>=BL$8,$A41<=BL$9),IF(SUM(BL$10:BL40)-ROUNDDOWN($L41*BL$5/100,0)<-BL$6,-BL$6-SUM(BL$10:BL40),-ROUNDDOWN($L41*BL$5/100,0)),0) -> 0 | BM41: =IF(AND(BM$7="○",$A41>=BM$8,$A41<=BM$9),IF(SUM(BM$10:BM40)-ROUNDDOWN($M41*BM$5/100,0)<-BM$6,-BM$6-SUM(BM$10:BM40),-ROUNDDOWN($M41*BM$5/100,0)),0) -> 0 | BN41: =IF(AND(BN$7="○",$A41>=BN$8,$A41<=BN$9),IF(SUM(BN$10:BN40)-ROUNDDOWN($M41*BN$5/100,0)<-BN$6,-BN$6-SUM(BN$10:BN40),-ROUNDDOWN($M41*BN$5/100,0)),0) -> 0 | BO41: =IF(AND(BO$7="○",$A41>=BO$8,$A41<=BO$9),IF(SUM(BO$10:BO40)-ROUNDDOWN($M41*BO$5/100,0)<-BO$6,-BO$6-SUM(BO$10:BO40),-ROUNDDOWN($M41*BO$5/100,0)),0) -> 0 | BP41: =IF(AND(BP$7="○",$A41>=BP$8,$A41<=BP$9),IF(SUM(BP$10:BP40)-ROUNDDOWN($M41*BP$5/100,0)<-BP$6,-BP$6-SUM(BP$10:BP40),-ROUNDDOWN($M41*BP$5/100,0)),0) -> 0 | BQ41: =IF(AND(BQ$7="○",$A41>=BQ$8,$A41<=BQ$9),IF(SUM(BQ$10:BQ40)-ROUNDDOWN($L41*BQ$5/100,0)<-BQ$6,-BQ$6-SUM(BQ$10:BQ40),-ROUNDDOWN($L41*BQ$5/100,0)),0) -> 0 | BR41: =IF(AND(BR$7="○",$A41>=BR$8,$A41<=BR$9),IF(SUM(BR$10:BR40)-ROUNDDOWN($M41*BR$5/100,0)<-BR$6,-BR$6-SUM(BR$10:BR40),-ROUNDDOWN($M41*BR$5/100,0)),0) -> 0 | BS41: =IF(AND(BS$7="○",$A41>=BS$8,$A41<=BS$9),IF(SUM(BS$10:BS40)-ROUNDDOWN($M41*BS$5/100,0)<-BS$6,-BS$6-SUM(BS$10:BS40),-ROUNDDOWN($M41*BS$5/100,0)),0) -> 0 | BT41: =IF(AND(BT$7="○",$A41>=BT$8,$A41<=BT$9),IF(SUM(BT$10:BT40)-ROUNDDOWN($M41*BT$5/100,0)<-BT$6,-BT$6-SUM(BT$10:BT40),-ROUNDDOWN($M41*BT$5/100,0)),0) -> 0 | BU41: =IF(AND(BU$7="○",$A41>=BU$8,$A41<=BU$9),IF(SUM(BU$10:BU40)-ROUNDDOWN($M41*BU$5/100,0)<-BU$6,-BU$6-SUM(BU$10:BU40),-ROUNDDOWN($M41*BU$5/100,0)),0) -> 0 | BV41: =IF(AND(BV$7="○",$A41>=BV$8,$A41<=BV$9),IF(SUM(BV$10:BV40)-ROUNDDOWN($M41*BV$5/100,0)<-BV$6,-BV$6-SUM(BV$10:BV40),-ROUNDDOWN($M41*BV$5/100,0)),0) -> 0 | BW41: =IF(AND(BW$7="○",$A41>=BW$8,$A41<=BW$9),IF(SUM(BW$10:BW40)-ROUNDDOWN($M41*BW$5/100,0)<-BW$6,-BW$6-SUM(BW$10:BW40),-ROUNDDOWN($M41*BW$5/100,0)),0) -> 0 | BX41: =IF(AND(T41="○",$A41>=BX$8,$A41<=BX$9),IF(SUM(BX$10:BX40)-ROUNDDOWN($K41*BX$5/100,0)<-BX$6,-BX$6-SUM(BX$10:BX40),-ROUNDDOWN($K41*BX$5/100,0)),0) -> 0 | BY41: =IF(AND(U41="○",$A41>=BY$8,$A41<=BY$9),IF(SUM(BY$10:BY40)-ROUNDDOWN($K41*BY$5/100,0)<-BY$6,-BY$6-SUM(BY$10:BY40),-ROUNDDOWN($K41*BY$5/100,0)),0) -> 0 | BZ41: =IF(AND(V41="○",$A41>=BZ$8,$A41<=BZ$9),IF(SUM(BZ$10:BZ40)-ROUNDDOWN($K41*BZ$5/100,0)<-BZ$6,-BZ$6-SUM(BZ$10:BZ40),-ROUNDDOWN($K41*BZ$5/100,0)),0) -> 0 | CA41: =IF(AND(W41="○",$A41>=CA$8,$A41<=CA$9),IF(SUM(CA$10:CA40)-ROUNDDOWN($K41*CA$5/100,0)<-CA$6,-CA$6-SUM(CA$10:CA40),-ROUNDDOWN($K41*CA$5/100,0)),0) -> 0 | CG41: =+SUM(AJ41:CF41,BC41,BE41,AZ41,BA41,BG41,BI41) -> 0 | CH41: =+CG41+N41 -> 0 | CI41: =IFERROR(ROUNDDOWN((CH41/G41),0),0) -> 0 | CO41: =IFERROR(CN41-CI41,0) -> 0 | CP41: =IFERROR(CN41/CI41,0) -> 0 | CR41: =+CO41*G41 -> 0 | CT41: =INDEX([2]マスタ!$A:$A,MATCH(D41,[2]マスタ!$C:$C,0)) -> #N/A | CU41: =IFERROR(TEXT(TODAY(),"yyyymmdd")&"_"&ROUNDDOWN(H41+I41,0)&"-"&ROUNDDOWN(CI41,0),"") -> 20260620_0-0
G42: 1 | H42: =+F42*G42 -> 0 | K42: =+ROUNDDOWN((H42+I42+J42)/100,0)*100 -> 0 | L42: =+ROUNDDOWN((H42+I42)/1.1/100,0)*100 -> 0 | M42: =+ROUNDDOWN((H42+I42)/1.1/200,0)*200 -> 0 | N42: =+H42+I42+J42 -> 0 | O42: =IF(OR(WEEKDAY($A42,2)=2,WEEKDAY($A42,2)=4),"○","✕") -> ✕ | P42: =+IF(MOD(TEXT($A42,"DD"),5)=0,"○","✕") -> ○ | Q42: =+IF((TEXT(A42,"DD")+0)=1,"○","✕") -> ✕ | R42: =+IF((TEXT($A42,"DD")+0)=18,"○","✕") -> ✕ | S42: 0 | T42: ✕ | U42: ✕ | V42: ✕ | W42: ✕ | X42: ○ | Y42: ✕ | Z42: ✕ | AA42: ✕ | AB42: ✕ | AC42: ✕ | AD42: =+IF(ISERROR(VLOOKUP($B42,AD$10:AD41,1,0)),IF(AND($N42>=1000,$A42>=AO$8,$A42<=AO$9),$B42,""),"") | AE42: =+IF(ISERROR(VLOOKUP($B42,AE$10:AE41,1,0)),IF(AND($N42>=1000,$A42>=AP$8,$A42<=AP$9),$B42,""),"") | AF42: =+IF(ISERROR(VLOOKUP($B42,AF$10:AF41,1,0)),IF(AND($N42>=1000,$A42>=AQ$8,$A42<=AQ$9),$B42,""),"") | AG42: =+IF(ISERROR(VLOOKUP($B42,AG$10:AG41,1,0)),IF(AND($N42>=1000,$A42>=AR$8,$A42<=AR$9),$B42,""),"") | AI42: 0 | AJ42: =IF(AND(AJ$7="○",$A42>=AJ$8,$A42<=AJ$9),IF(SUM(AJ$10:AJ41)-ROUNDDOWN($K42*AJ$5/100,0)<-AJ$6,-AJ$6-SUM(AJ$10:AJ41),-ROUNDDOWN($K42*AJ$5/100,0)),0) -> 0 | AK42: =IF(AND(AK$7="○",$A42>=AK$8,$A42<=AK$9),IF(SUM(AK$10:AK41)-ROUNDDOWN($L42*AK$5/100,0)<-AK$6,-AK$6-SUM(AK$10:AK41),-ROUNDDOWN($L42*AK$5/100,0)),0) -> 0 | AL42: =IF(AND(AL$7="○",$A42>=AL$8,$A42<=AL$9),IF(SUM(AL$10:AL41)-ROUNDDOWN($N42*AL$5/100,0)<-AL$6,-AL$6-SUM(AL$10:AL41),-ROUNDDOWN($N42*AL$5/100,0)),0) -> 0 | AM42: =IF(AND(AM$7="○",$A42>=AM$8,$A42<=AM$9),IF(SUM(AM$10:AM41)-ROUNDDOWN($L42*AM$5/100,0)<-AM$6,-AM$6-SUM(AM$10:AM41),-ROUNDDOWN($L42*AM$5/100,0)),0) -> 0 | AN42: =IF(AND(AN$7="○",$A42>=AN$8,$A42<=AN$9),IF(SUM(AN$10:AN41)-ROUNDDOWN($M42*AN$5/100,0)<-AN$6,-AN$6-SUM(AN$10:AN41),-ROUNDDOWN($M42*AN$5/100,0)),0) -> 0 | AO42: =IF(AND($A42>=AO$8,$A42<=AO$9),IF(SUM(AO$10:AO41)-ROUNDDOWN($K42*AO$5/100,0)<-AO$6,-AO$6-SUM(AO$10:AO41),-ROUNDDOWN($K42*AO$5/100,0)),0) -> 0 | AP42: =IF(AND($A42>=AP$8,$A42<=AP$9),IF(SUM(AP$10:AP41)-ROUNDDOWN($K42*AP$5/100,0)<-AP$6,-AP$6-SUM(AP$10:AP41),-ROUNDDOWN($K42*AP$5/100,0)),0) -> 0 | AQ42: =IF(AND($A42>=AQ$8,$A42<=AQ$9),IF(SUM(AQ$10:AQ41)-ROUNDDOWN($K42*AQ$5/100,0)<-AQ$6,-AQ$6-SUM(AQ$10:AQ41),-ROUNDDOWN($K42*AQ$5/100,0)),0) -> 0 | AR42: =IF(AND($A42>=AR$8,$A42<=AR$9),IF(SUM(AR$10:AR41)-ROUNDDOWN($K42*AR$5/100,0)<-AR$6,-AR$6-SUM(AR$10:AR41),-ROUNDDOWN($K42*AR$5/100,0)),0) -> 0 | AS42: =IF(SUMIFS(AS$10:AS41,$A$10:$A41,$A42)-ROUNDDOWN($K42*$S42/100,0)<-$S42*1000,-$S42*1000-SUMIFS(AS$10:AS41,$A$10:$A41,$A42),-ROUNDDOWN($K42*$S42/100,0)) -> 0 | AT42: =IF(AND(X42="○",$A42>=AT$8,$A42<=AT$9,K42>=3980),IF(SUM(AT$10:AT41)-ROUNDDOWN($K42*AT$5/100,0)<-AT$6,-AT$6-SUM(AT$10:AT41),-ROUNDDOWN($K42*AT$5/100,0)),0) -> 0 | AU42: =IF(O42="○",IF(SUM(AU$10:AU41)-ROUNDDOWN($K42*AU$5/100,0)<-AU$6,-AU$6-SUM(AU$10:AU41),-ROUNDDOWN($K42*AU$5/100,0)),0) -> 0 | AV42: =IF(P42="○",IF(SUM(AV$10:AV41)-ROUNDDOWN($K42*AV$5/100,0)<-AV$6,-AV$6-SUM(AV$10:AV41),-ROUNDDOWN($K42*AV$5/100,0)),0) -> 0 | AW42: =IF(Q42="○",IF(SUM(AW$10:AW41)-ROUNDDOWN($K42*AW$5/100,0)<-AW$6,-AW$6-SUM(AW$10:AW41),-ROUNDDOWN($K42*AW$5/100,0)),0) -> 0 | AX42: =IF(R42="○",IF(SUM(AX$10:AX41)-ROUNDDOWN($K42*AX$5/100,0)<-AX$6,-AX$6-SUM(AX$10:AX41),-ROUNDDOWN($K42*AX$5/100,0)),0) -> 0 | AY42: 0 | AZ42: =-ROUNDDOWN($K42*AY42/100,0) -> 0 | BA42: =-ROUNDDOWN($K42*AI42/100,0) -> 0 | BC42: =-ROUNDDOWN($K42*BB42/100,0) -> 0 | BD42: 0 | BE42: =-ROUNDDOWN($K42*BD42/100,0) -> 0 | BF42: 0 | BG42: =-ROUNDDOWN($K42*BF42/100,0) -> 0 | BH42: 0 | BI42: =-ROUNDDOWN($K42*BH42/100,0) -> 0 | BJ42: =IF(AND(BJ$7="○",$A42>=BJ$8,$A42<=BJ$9),IF(SUM(BJ$10:BJ41)-ROUNDDOWN($M42*BJ$5/100,0)<-BJ$6,-BJ$6-SUM(BJ$10:BJ41),-ROUNDDOWN($M42*BJ$5/100,0)),0) -> 0 | BK42: =IF(AND(BK$7="○",$A42>=BK$8,$A42<=BK$9),IF(SUM(BK$10:BK41)-ROUNDDOWN($L42*BK$5/100,0)<-BK$6,-BK$6-SUM(BK$10:BK41),-ROUNDDOWN($L42*BK$5/100,0)),0) -> 0 | BL42: =IF(AND(BL$7="○",$A42>=BL$8,$A42<=BL$9),IF(SUM(BL$10:BL41)-ROUNDDOWN($L42*BL$5/100,0)<-BL$6,-BL$6-SUM(BL$10:BL41),-ROUNDDOWN($L42*BL$5/100,0)),0) -> 0 | BM42: =IF(AND(BM$7="○",$A42>=BM$8,$A42<=BM$9),IF(SUM(BM$10:BM41)-ROUNDDOWN($M42*BM$5/100,0)<-BM$6,-BM$6-SUM(BM$10:BM41),-ROUNDDOWN($M42*BM$5/100,0)),0) -> 0 | BN42: =IF(AND(BN$7="○",$A42>=BN$8,$A42<=BN$9),IF(SUM(BN$10:BN41)-ROUNDDOWN($M42*BN$5/100,0)<-BN$6,-BN$6-SUM(BN$10:BN41),-ROUNDDOWN($M42*BN$5/100,0)),0) -> 0 | BO42: =IF(AND(BO$7="○",$A42>=BO$8,$A42<=BO$9),IF(SUM(BO$10:BO41)-ROUNDDOWN($M42*BO$5/100,0)<-BO$6,-BO$6-SUM(BO$10:BO41),-ROUNDDOWN($M42*BO$5/100,0)),0) -> 0 | BP42: =IF(AND(BP$7="○",$A42>=BP$8,$A42<=BP$9),IF(SUM(BP$10:BP41)-ROUNDDOWN($M42*BP$5/100,0)<-BP$6,-BP$6-SUM(BP$10:BP41),-ROUNDDOWN($M42*BP$5/100,0)),0) -> 0 | BQ42: =IF(AND(BQ$7="○",$A42>=BQ$8,$A42<=BQ$9),IF(SUM(BQ$10:BQ41)-ROUNDDOWN($L42*BQ$5/100,0)<-BQ$6,-BQ$6-SUM(BQ$10:BQ41),-ROUNDDOWN($L42*BQ$5/100,0)),0) -> 0 | BR42: =IF(AND(BR$7="○",$A42>=BR$8,$A42<=BR$9),IF(SUM(BR$10:BR41)-ROUNDDOWN($M42*BR$5/100,0)<-BR$6,-BR$6-SUM(BR$10:BR41),-ROUNDDOWN($M42*BR$5/100,0)),0) -> 0 | BS42: =IF(AND(BS$7="○",$A42>=BS$8,$A42<=BS$9),IF(SUM(BS$10:BS41)-ROUNDDOWN($M42*BS$5/100,0)<-BS$6,-BS$6-SUM(BS$10:BS41),-ROUNDDOWN($M42*BS$5/100,0)),0) -> 0 | BT42: =IF(AND(BT$7="○",$A42>=BT$8,$A42<=BT$9),IF(SUM(BT$10:BT41)-ROUNDDOWN($M42*BT$5/100,0)<-BT$6,-BT$6-SUM(BT$10:BT41),-ROUNDDOWN($M42*BT$5/100,0)),0) -> 0 | BU42: =IF(AND(BU$7="○",$A42>=BU$8,$A42<=BU$9),IF(SUM(BU$10:BU41)-ROUNDDOWN($M42*BU$5/100,0)<-BU$6,-BU$6-SUM(BU$10:BU41),-ROUNDDOWN($M42*BU$5/100,0)),0) -> 0 | BV42: =IF(AND(BV$7="○",$A42>=BV$8,$A42<=BV$9),IF(SUM(BV$10:BV41)-ROUNDDOWN($M42*BV$5/100,0)<-BV$6,-BV$6-SUM(BV$10:BV41),-ROUNDDOWN($M42*BV$5/100,0)),0) -> 0 | BW42: =IF(AND(BW$7="○",$A42>=BW$8,$A42<=BW$9),IF(SUM(BW$10:BW41)-ROUNDDOWN($M42*BW$5/100,0)<-BW$6,-BW$6-SUM(BW$10:BW41),-ROUNDDOWN($M42*BW$5/100,0)),0) -> 0 | BX42: =IF(AND(T42="○",$A42>=BX$8,$A42<=BX$9),IF(SUM(BX$10:BX41)-ROUNDDOWN($K42*BX$5/100,0)<-BX$6,-BX$6-SUM(BX$10:BX41),-ROUNDDOWN($K42*BX$5/100,0)),0) -> 0 | BY42: =IF(AND(U42="○",$A42>=BY$8,$A42<=BY$9),IF(SUM(BY$10:BY41)-ROUNDDOWN($K42*BY$5/100,0)<-BY$6,-BY$6-SUM(BY$10:BY41),-ROUNDDOWN($K42*BY$5/100,0)),0) -> 0 | BZ42: =IF(AND(V42="○",$A42>=BZ$8,$A42<=BZ$9),IF(SUM(BZ$10:BZ41)-ROUNDDOWN($K42*BZ$5/100,0)<-BZ$6,-BZ$6-SUM(BZ$10:BZ41),-ROUNDDOWN($K42*BZ$5/100,0)),0) -> 0 | CA42: =IF(AND(W42="○",$A42>=CA$8,$A42<=CA$9),IF(SUM(CA$10:CA41)-ROUNDDOWN($K42*CA$5/100,0)<-CA$6,-CA$6-SUM(CA$10:CA41),-ROUNDDOWN($K42*CA$5/100,0)),0) -> 0 | CG42: =+SUM(AJ42:CF42,BC42,BE42,AZ42,BA42,BG42,BI42) -> 0 | CH42: =+CG42+N42 -> 0 | CI42: =IFERROR(ROUNDDOWN((CH42/G42),0),0) -> 0 | CO42: =IFERROR(CN42-CI42,0) -> 0 | CP42: =IFERROR(CN42/CI42,0) -> 0 | CR42: =+CO42*G42 -> 0 | CT42: =INDEX([2]マスタ!$A:$A,MATCH(D42,[2]マスタ!$C:$C,0)) -> #N/A | CU42: =IFERROR(TEXT(TODAY(),"yyyymmdd")&"_"&ROUNDDOWN(H42+I42,0)&"-"&ROUNDDOWN(CI42,0),"") -> 20260620_0-0
